Workbook

Sheet Portafolio_Proyectos
A1: Programa estratégico | B1: Sistema productivo | C1: Área temática | D1: Nombre del proyecto | E1: Investigador líder | F1: Rol CI Palmira | G1: Institución ejecutora | H1: Aliados estratégicos | I1: Rol del aliado | J1: Problema abordado | K1: Objetivo del proyecto | L1: Justificación estratégica | M1: Política pública asociada | N1: Metodología principal | O1: Variables evaluadas | P1: Tipo de intervención (I+D+i, Canales OT, Fortalecimiento) | Q1: Resultados principales | R1: Productos generados | S1: Publicaciones | T1: Oferta tecnológica | U1: Tipo de tecnología | V1: TRL inicial | W1: TRL final | X1: Estado tecnológico | Y1: Impacto técnico | Z1: Impacto económico | AA1: Impacto social | AB1: Impacto ambiental | AC1: Departamentos | AD1: Municipios | AE1: Tipo de beneficiarios | AF1: Beneficiarios directos | AG1: Beneficiarios indirectos | AH1: Área potenciales de adopción | AI1: Activos generados | AJ1: Estado propiedad intelectual | AK1: Financiador | AL1: Monto del proyecto | AM1: Año inicio | AN1: Año final | AO1: Estado del proyecto | AP1: Capacidad_emergente | AQ1: Capacidad_consolidada | AR1: Capacidad_distintiva
A2: Bioeconomía: Prácticas de agricultura sostenible | B2: Aguacate Hass | C2: Fisiología vegetal y nutrición | D2: Convenio 1790. Manejo integrado del cultivo | E2: Alexander Rebolledo Roa | F2: Ejecutor | G2: AGROSAVIA | H2: 1. Colciencias 2. Aproare 3. Asfruher | I2: 1. Financiador 2 y 3. Vertice sociedad civil organizada | J2: Desconocimiento de factores hídricos y nutricionales asociados a productividad del cultivo (Abscisión, cuajado, rendimiento y calidad de fruto) | K2: Optimizar la floración y productividad del aguacate Hass mediante manejo hídrico y nutricional. | L2: Los bajos rendimientos del aguacate combinado con la proyección de nuevas zonas de siembra para incrementar la participación en el mercado internacional, requieren del desarrollo de tecnologías que conduzcan a un incremento en la productividad. | M2: CONPES 3582 DEL 25 DE ABRIL DE 2009 "Política Nacional de Ciencia, Tecnología e Innovación" | N2: Nutrición. metodología del índice de balance de nutrientes (ibn) Kenworthy . Riego. cálculo de la ETo por el método de la FAO-Penman Monteith (Allen et al., 2006) y el cálculo de la lámina de riego con base en el balance hídrico. | O2: 1. Abscisión 2. Crecimiento del fruto (MS, diámetro, Peso). 3. Estados fenológicos 4. Variables climáticas 5. Contenido nutrientes del suelo 6. Contenido mineral del fruto | P2: Investigación | Q2: 1. Caracterización de la fenología floral (140 días a antesis), 2. Abscisión global. 99,85 % (276.455 flores) 3. Cuajado. 0,15 % 4. Incremento en rendimiento con manejo de IBN + riego. de 7,5 a 14 t/ha y la producción por planta de 61 a 98 kg. | R2: 1. Protocolo aplicación láminas de riego Antioquia, Tolima, Cauca (Fase 1. Palmira) 2. Protocolo para manejo de la fertilización (Antioquia, Tolima, Cauca) (Fase 1). | S2: Artículo científico. Pattern of flower and fruit abscision and fruit growth of hass avocado under tropical conditions chrome-extension://efaidnbmnnnibpcajpcglclefindmkaj/ https://www.cropj.com/Roa_18_09_2024_547_554.pdf Libros. 1. Criterios para la definición de planes de fertilización en el cultivo de aguacate Hass con un enfoque tecnificado https://doi.org/10.21930/agrosavia.manual.7402384 2. Requerimientos hídricos del cultivo de aguacate (Persea americana) variedad Hass en zonas productoras de Colombia https://doi.org/10.21930/agrosavia.manual.7402322 | U2: Resultado de investigación | V2: 46115 | W2: No definido | X2: Investigación | Y2: 1. Disponibilidad de proocolos estandarizados para aplicación de nutrición y riego. 2. Incremento den rendimiento | Z2: ncremento de la productividad del cultivo (de 7,5 a 14 t/ha), mejorando la rentabilidad del sistema productivo de aguacate Hass. | AA2: Fortalecimiento de las capacidades de manejo productivo de los agricultores mediante prácticas de riego y nutrición más eficientes. | AB2: Uso más eficiente del agua y de los nutrientes mediante manejo hídrico y nutricional basado en criterios técnicos. | AC2: Antioquia, Tolima, Cauca | AD2: Rionegro, Herveo, Morales | AE2: Asociación de productores | AF2: Asociación de Productores de Frutas y Hortalizas de Herveo (ASFRUHER) Asociación de Productores de Aguacate de El Retiro (APROARE) | AG2: Productores de aguacate Hass de Herveo (Tolima) y El Retiro (Antioquia), técnicos y otros productores de las zonas productoras de aguacate en Colombia. | AH2: Zonas productoras de aguacate Hass a nivel nacional | AI2: NA | AJ2: NA | AK2: Colciencias | AL2: 3000000000 | AM2: 2013 | AN2: 2016 | AO2: Finalizado | AP2: Indicadores de sostenibilidad ambiental
A3: Bioeconomía: Biodiversidad | B3: Agraz | C3: Fisiología vegetal y nutrición | D3: Aprovechamiento sostenible de agraz en el Cauca | AK3: Entes Nacionales y Territoriales
A4: Bioeconomía: Biodiversidad | B4: Agraz | C4: Material de siembra y mejoramiento genético | D4: Aprovechamiento sostenible de agraz en el Cauca | AK4: Entes Nacionales y Territoriales
A5: Bioeconomía: Biodiversidad | B5: Agraz | C5: Material de siembra y mejoramiento genético | D5: Aprovechamiento sostenible de agraz en el Cauca | AK5: Entes Nacionales y Territoriales
A6: ACI:Productividad agrícola agroambientalmente eficiente e integralmente sostenible | B6: Aguacate Hass | C6: Fisiología vegetal y nutrición | D6: Convenio 1929. Desarrollo y validación de tecnologías para incrementar la productividad del cultivo | E6: Alexander Rebolledo Roa | F6: Ejecutor | G6: AGROSAVIA | H6: 1. Gobernación del Cauca, 2. Universidad del Cauca | I6: 1. Supervisor. 2. Cojejecutor Vertice Institución de educación superior | J6: Baja disponibilidad de opciones tecnológicas para el manejo de riego y nutrición | K6: Validar tecnologías de nutrición y riego para incrementar productividad del aguacate Hass en el Cauca | L6: Mejora la eficiencia hídrica y nutricional en aguacate Hass, reduciendo alternancia de cosechas y aumentando rendimiento en zonas productoras del Cauca | M6: CONPES 3582 — Política Nacional de Ciencia, Tecnología e Innovación; Plan Nacional de Desarrollo | N6: IBN de Kenworthy (1973); ETo FAO-Penman-Monteith (Allen et al., 2006); lámina de riego por balance hídrico; escala fenológica BBCH (Alcaraz et al., 2013) | O6: Diámetro de fruto, peso fresco, peso seco, materia seca, abscisión, cuajado, estados fenológicos BBCH, IBN foliar, ETo, lámina de riego | P6: Desarrollo | Q6: Fertilización basada en IBN incrementó diámetro de fruto (T2: 61,43 mm vs T1: 54,77 mm). Abscisión 98–99,9%. Cuajado 0,15–0,87%. Riego 0,75 ETo mejoró peso seco del mesocarpo | R6: Protocolo de fertilización basada en IBN para aguacate Hass Cauca, protocolo de riego por balance hídrico, modelo fenológico BBCH, aplicativo web de recomendación nutricional e hídrica | S6: 1. Criterios para la definición de planes de manejo de la fertilización y para la aplicación de riego en cultivos de aguacate Hass con un enfoque tecnificado. https://editorial.agrosavia.co/index.php/publicaciones/catalog/book/355. 2. Prácticas de manejo sostenible para fertilización y riego de aguacate Hass en el departamento del Cauca. https://editorial.agrosavia.co/index.php/publicaciones/catalog/book/357 3. Nutrient balance in Hass avocado trees as a tool to optimize crop fertilization management. https://www.mdpi.com/2073-4395/13/8/1956 4. Rodríguez P., Villamizar J., Rebolledo A. (2025). Impact of Fruit Development Age on Postharvest Quality of Hass Avocado. Int J Fruit Sci, 25, 18–35. DOI: 10.1080/15538362.2025.2480570 Rebolledo-Roa A., Burbano-Díaz R.A., Medina-Cano C.I. (2024). | T6: Sistema Experto TecnoHass | U6: Aplicativo Web | V6: 5 | W6: 7 | X6: Finalizado | Y6: Incremento de 12% en diámetro de fruto con fertilización IBN; reducción de abscisión ~1,4% con fertilización foliar B+N en estado fenológico coliflor EF515 | Z6: Mayor proporción de frutos en calibres comerciales de alto valor (178–325 g/fruto) con fertilización IBN; rendimiento de hasta 17 t/ha en finca con riego vs promedios menores sin manejo | AA6: 1.440 productores de aguacate Hass de Morales, El Tambo y municipios del Cauca beneficiados con tecnologías de nutrición y riego de alta precisión y bajo costo de implementación | AB6: Uso eficiente del agua con riego 0,75 ETo; reducción de fertilizantes excesivos mediante IBN, disminuyendo riesgo de lixiviación de nutrientes y contaminación de fuentes hídricas | AC6: Cauca | AD6: Morales, Cajibío, Piendamó, Caldono, Tambo, Timbío, Popayán, Sotará, Caloto, Corinto, Toribío. | AE6: Asociación de productores | AF6: 1440 | AG6: Productores de aguacate Hass de zonas productoras del Cauca y regiones andinas colombianas con condiciones agroecológicas similares | AH6: Departamento del Cauca y zonas productoras de aguacate Hass en regiones andinas colombianas | AI6: Aplicativo Web | AK6: Sistema General de Regalías-Cauca | AM6: 2018 | AN6: 2023 | AO6: En ejecución | AP6: Indicadores de sostenibilidad ambiental | AQ6: Fertilización por sitio específico
A7: ACI:Productividad agrícola agroambientalmente eficiente e integralmente sostenible | B7: Aguacate Hass | C7: Fisiología vegetal y nutrición | D7: Portafolio. Fortalecimiento cadena de valor de aguacate. Convocatoria 42. SGR-Región Pacífico | E7: Alexander Rebolledo Roa | F7: Líder | G7: AGROSAVIA | H7: SENA CEAI, Universidad Cooperativa de Colombia, CREATIC, BIOINNOVA, Cámara de Comercio de Palmira, CITRIVIVEROS, Alcaldías de Popayán, Piendamó, El Tambo, Sotará, Palmira, Caicedonia, Versalles, San José del Palmar, asociaciones de productores locales | I7: SENA CEAI: coejecución en actividades de apropiación social del conocimiento y fortalecimiento TIC. Universidad Cooperativa de Colombia: coejecución en cursos de formación sobre plataforma TecnoHass. CREATIC: desarrollo y mejora de plataformas digitales. BIOINNOVA: apropiación social del conocimiento. Cámara de Comercio de Palmira: vinculación tecnológica y fortalecimiento de modelos de negocio. | J7: Deficiente orientación técnica en fertilización y riego en aguacate Hass y Lorena en Cauca y Valle del Cauca | K7: Validar tecnologías de fertilización y riego para aguacate Hass y Lorena en Cauca y Valle del Cauca | L7: Escala tecnologías IBN y balance hídrico de Hass hacia Lorena, ampliando cobertura a Valle del Cauca y cerrando brecha tecnológica en ambos sistemas productivos | M7: PND 2022-2026 'Colombia Potencia Mundial de la Vida', Convergencia Regional; CONPES 4069 de 2021 CTI; Planes de Desarrollo Departamentales Cauca y Valle del Cauca | N7: IBN de Kenworthy (1973); ETo FAO-Penman Monteith (Allen et al., 2006); escala BBCH (Salazar-García et al., 1998); monitoreo Agro 4.0 de variables climáticas | O7: Diámetro y peso del fruto, materia seca, calibre Codex, rendimiento kg/árbol, abscisión, cuajado, IBN foliar, ETo y lámina de riego, estados fenológicos BBCH | P7: Innovación | Q7: Fertilización IBN incrementó producción de 7 a 14 t/ha; lámina 75% ETo fue óptima; fertilización foliar N+B aumentó producción en 14 t/ha; rendimiento de hasta 20 kg/árbol con IBN | R7: Planes de manejo de nutrición y riego (Hass y Lorena, Cauca y Valle del Cauca), módulo fertilización y riego TecnoHass (TRL 8), manuales técnicos, artículos científicos indexados | S7: Rebolledo A. y Dorado J. (2017). Manejo de la fertilización y del riego en cultivos de aguacate Hass en Cauca. AGROSAVIA. Rebolledo A. y Burbano R.A. (2023). Nutrición basada en IBN para aguacate Hass en condiciones tropicales colombianas. AGROSAVIA. Rodríguez P. et al. (2023). Factores territoriales y calidad del fruto en sistemas de aguacate en la región pacífico. AGROSAVIA. | T7: Protocolos de fertilización y riego para aguacate Hass y Lorena integrados en plataforma TecnoHass (Cauca y Valle del Cauca) | U7: Resultado de investigación / Herramienta tecnológica digital (aplicativo web) | V7: 4 | W7: 8 | X7: En ejecución | Y7: Incremento de 7 a 14 t/ha con IBN + riego 75% ETo; mayor proporción calibre 22 (165–196 g); menor descarte | Z7: Reducción de descarte en planta exportadora del 6%; incremento de 20 kg/árbol con IBN (segundo año de cosecha); potencial de reducción de pérdidas poscosecha del 60% | AA7: 889 productores (Hass y Lorena) en Cauca y Valle del Cauca con acceso a tecnologías de nutrición y riego de precisión | AB7: Reducción del uso indiscriminado de fertilizantes de síntesis química; uso eficiente del agua (riego por ETo vs gravedad); disminución de escorrentía y riesgo de lixiviación de nutrientes | AC7: Chocó, Cauca, Valle del Cauca | AD7: San José del Palmar, El Tambo, Piendamó, Sotará, Popayán, Caicedonia, Versalles, Palmira | AE7: Asociación de productores | AF7: 889 | AG7: Productores de aguacate Hass y Lorena en subregiones del Cauca y Valle del Cauca no incluidos directamente; asistentes técnicos y extensionistas agropecuarios de la región | AH7: Zonas productoras de aguacate Hass (exportación) y Lorena (consumo interno) en Cauca y Valle del Cauca; extensible a región pacífico | AI7: Aplicativo web TecnoHass — módulo fertilización y riego (TRL 8); protocolos de manejo nutricional y de riego para aguacate Hass y Lorena; bases de datos de extracción de nutrientes y curvas de crecimiento de fruto | AK7: Entes Nacionales y Territoriales | AL7: 24876204138 | AM7: 2024 | AN7: 2027 | AO7: En ejecución | AP7: Nutrición y riego para aguacate de consumo interno (Lorena) | AQ7: Fertilización por sitio específico (IBN) y riego por balance hídrico
A8: Bioeconomía: Prácticas de agricultura sostenible | B8: Aguacate Hass | C8: Fisiología vegetal y nutrición | D8: Convenio 2207. Desarrollo de modelo fenológico aguacate Hass Pijao – Quindío (Fase 1) | E8: Alexander Rebolledo Roa | F8: Líder | G8: AGROSAVIA | H8: Global Green SAS | I8: Financiador y co-ejecutor técnico de apoyo logístico en campo; propietario de los activos instalados (estaciones climáticas) | J8: Ausencia de modelo fenológico predictivo para aguacate Hass en gradiente altitudinal andino del Quindío que dificulta el manejo oportuno del cultivo | K8: Desarrollar un modelo fenológico predictivo basado en GDD para aguacate Hass en gradiente altitudinal de Pijao, Quindío | L8: Permite anticipar eventos críticos (floración, cosecha) con base en temperatura acumulada, optimizando manejo agronómico y reduciendo incertidumbre productiva | M8: Plan Nacional de Desarrollo — Bioeconomía; CONPES 3582 — Política Nacional CTI; Pacto por Colombia — Pacto por la productividad agropecuaria | N8: Escala fenológica BBCH (Alcaraz et al., 2013); grados-día de crecimiento GDD (base 10°C, Aubert 1972); análisis factorial confirmatorio CFA; estadística circular; estaciones GeoCampo/NASA | O8: Estados fenológicos BBCH (EF010–EF719), GDD acumulados, temperatura máx/mín/media, humedad relativa, velocidad del viento, diámetro ecuatorial de fruto, peso fresco, peso seco, materia seca | P8: Investigación | Q8: Gradiente térmico-hídrico determina sincronía fenológica. Altitud ~2200 m es óptima (antesis ρ=0,82). GDD predice progresión fenológica. L3 (~2056 m): 20,58 kg/árbol cosecha 2, materia seca 22,8 % | R8: Documento técnico con modelo fenológico GDD, caracterización climática altitudinal y clasificación Codex; 1 artículo científico sometido a revista indexada; 2 estaciones climáticas automatizadas instaladas | S8: Rebolledo, A., Burbano, R., Villamizar, J., & Corrales, D. (2025). Climatic Drivers of Flowering Synchrony in ‘Hass’ Avocado Under Tropical Andean Conditions. Plants, 14(24), 3822. | T8: Modelo fenológico predictivo basado en GDD para aguacate Hass en gradiente altitudinal andino tropical del Quindío | U8: Resultado de investigación | V8: 2 | W8: 5 | X8: Finalizado | Y8: GDD predice progresión fenológica con alta precisión (CFI=0,976); sincronía óptima en ~2200 m (ρ=0,82); L3 produce frutos 62–64 mm vs L5 55–59 mm | Z8: L3 produce materia seca 22,8 % y aceite 58,5 % base seca (cosecha tardía); rendimiento 20,58 kg/árbol cosecha 2; segmentación de mercado por altitud y momento de cosecha optimiza valor comercial | AA8: 115 beneficiarios directos (productores de aguacate de Pijao, Quindío) con acceso a modelo fenológico que mejora planificación de cosecha y reducción de pérdidas por asincronía floral | AB8: Manejo basado en señales térmicas reales reduce aplicaciones innecesarias de insumos; monitoreo microclimático continuo aporta base para adaptación al cambio climático en sistemas andinos tropicales | AC8: Quindío | AD8: Pijao | AE8: Otro | AF8: 115 | AG8: Productores de aguacate Hass en zonas andinas colombianas con gradiente altitudinal 1600–2500 m.s.n.m. | AH8: Zonas productoras de aguacate Hass en gradiente altitudinal andino 1600–2500 m.s.n.m. en Colombia | AK8: Sector privado | AL8: 496881755 | AM8: 2024 | AN8: 2025 | AO8: Finalizado | AP8: Modelación fenológica con acumulación térmica (GDD) en sistemas frutícolas altoandinos | AQ8: Fertilización por sitio específico
A9: Bioeconomía: Prácticas de agricultura sostenible | B9: Aguacate Hass | C9: Manejo sanitario y fitosanitario | D9: Actividad 6. Generar practicas de manejo fitosanitario de plags de importancia cuarentenaria validadas en regiones productoras del departamento. | AK9: Entes Nacionales y Territoriales
A10: ACI: Adaptación y resiliencia de los sistemas productivos agropecuarios frente a condiciones de clima cambiante | B10: Aguacate Hass | C10: Manejo ambiental y sostenibilidad | D10: convenio 1929. Actividad 1. Valoración de la oferta biofísica y caracterización socioeconómica de sistemas de producción de aguacate para la identificación de nichos productivos y tecnología requerida en el desarrollo de cultivos de aguacate Hass en el Departamento del Cauca. Lider: Diana Lucia Correa Moreno | AK10: Entes Nacionales y Territoriales
A11: Inclusión social en el desarrollo tecnológico: Apropiación social del conocimiento desde la ciencia ciudadana y la ciencia comunitaria | B11: Aguacate Hass | C11: Manejo ambiental y sostenibilidad | D11: convenio 1929. Actividad 6. Divulgación de la oferta tecnológica disponible del sistema productivo de aguacate y las tecnologías validadas . Lider: Diana Lucia Correa Moreno | AK11: Entes Nacionales y Territoriales
A12: Bioeconomía: Biodiversidad | B12: Aguacate Hass | C12: Manejo sanitario y fitosanitario | D12: Aumento de la productividad del aguacate mediante el uso de polinizadores en tres zonas productoras de Colombia. | AK12: Entes Nacionales y Territoriales
A13: ACI: Adaptación y resiliencia de los sistemas productivos agropecuarios frente a condiciones de clima cambiante | B13: Aguacate Hass | C13: Manejo ambiental y sostenibilidad | D13: Reducción del riesgo y adaptación al cambio climático_Modelos de adaptación agroclimática (MAPA). Aguacate Hass (Persea americana Mill.) var. Hass. Facilitadora Regional MAPA: Diana Lucia Correa Moreno | AK13: Entes Nacionales y Territoriales
A14: Otro | B14: Aguacate Hass | C14: Manejo sanitario y fitosanitario | D14: Identificación de ácaros e insectos escamas y sus enemigos naturales promisorios para una producción competitiva de aguacate en Colombia. | AK14: Entes Nacionales y Territoriales
A15: Bioeconomía: Biodiversidad | B15: Aguacate Hass | C15: Material de siembra y mejoramiento genético | D15: Bases tecnológicas para la producción de material de siembra de aguacate de alta calidad Fase 1 | AK15: Entes Nacionales y Territoriales
A16: Bioeconomía: Biodiversidad | B16: Aguacate Hass | C16: Material de siembra y mejoramiento genético | D16: Bases tecnológicas para la producción de material de siembra de aguacate de alta calidad Fase 2 | AK16: Entes Nacionales y Territoriales
A17: Bioeconomía: Economía circular | B17: Aguacate Hass | C17: Material de siembra y mejoramiento genético | D17: Bases tecnológicas para la producción de material de siembra de aguacate de alta calidad Fase 3 | AK17: Entes Nacionales y Territoriales
A18: ACI:Productividad agrícola agroambientalmente eficiente e integralmente sostenible | B18: Aguacate Hass | C18: Manejo ambiental y sostenibilidad | D18: Validación metodológica para caracterizar las condiciones biofísicas, socioeconómicas y productivas a escala 1:25.000, para el cultivo de aguacate en la región productora del Tolima, como soporte para el desarrollo de tecnologías de manejo agronómico del cultivo. Lider: Diana Lucia Correa Moreno | AC18: Tolima | AK18: Entes Nacionales y Territoriales
A19: ACI: Adaptación y resiliencia de los sistemas productivos agropecuarios frente a condiciones de clima cambiante | B19: Aguacate Hass | C19: Manejo ambiental y sostenibilidad | D19: Condiciones biofísicas y socioeconómicas del sistema productivo de aguacate - variedad Lorena caracterizadas en la región productora del Tolima, como soporte para el desarrollo de tecnologías de manejo agronómico específicas. Lider: Diana Lucia Correa Moreno | AC19: Tolima | AK19: Entes Nacionales y Territoriales
A20: ACI: Adaptación y resiliencia de los sistemas productivos agropecuarios frente a condiciones de clima cambiante | B20: Aguacate Hass | C20: Manejo ambiental y sostenibilidad | D20: Caracterización de áreas potenciales con enfoque territorial y de adaptación para el desarrollo y producción de cultivos de aguacate con atributos de valor. Lider: Diana Lucia Correa Moreno | AC20: Tolima | AK20: Entes Nacionales y Territoriales
A21: Bioeconomía: Biodiversidad | B21: Ají | C21: Material de siembra y mejoramiento genético | D21: Selección de materiales de Capsicum spp. con atributos diferenciales y ventajas competitivas agronómicas y agroindustriales | AK21: Entes Nacionales y Territoriales
A22: Bioeconomía: Biodiversidad | B22: Bancos de Germoplasma | C22: Material de siembra y mejoramiento genético | D22: 2025 BGA Conservación en Campo BG Vegetal ID 1003076 | AK22: Entes Nacionales y Territoriales
A23: Bioeconomía: Biodiversidad | B23: Cacao | C23: Material de siembra y mejoramiento genético | D23: Identificación de atributos agronómicos en cacao cuya expresión es afectada por el patrón con miras a establecer un programa de mejoramiento genético de patrones que contribuya a realzar el comportamiento de clones de interés | AK23: Entes Internacionales
A24: Bioeconomía: Biodiversidad | B24: Cacao | C24: Material de siembra y mejoramiento genético | D24: Selección de patrones de cacao mediante la identificación de atributos agronómicos cuya expresión es afectada por el patrón, con miras a establecer un programa de mejoramiento genético de patrones que contribuya a realzar el comportamiento de clones de interés. | AK24: Entes Nacionales y Territoriales
A25: Bioeconomía: Biodiversidad | B25: Cacao | C25: Material de siembra y mejoramiento genético | D25: Evaluación de la acumulación de cadmio de genotipos de cacao, bajo diferentes condiciones edafoclimáticas, como estrategia de mitigación del impacto de contenidos de cadmio biodisponible en suelo | AK25: Entes Internacionales
A26: Bioeconomía: Biodiversidad | B26: Cacao | C26: Material de siembra y mejoramiento genético | D26: Fase II Cacao para la paz | AK26: Entes Internacionales
A27: Bioeconomía: Prácticas de agricultura sostenible | B27: Cacao | C27: Manejo de sistemas productivos | D27: Implementación de recomendaciones tecnológicas orientadas al fortalecimiento de capacidades y desarrollo sostenible del sistema productivo de cacao en el suroccidente colombiano a partir de estrategias participativas | AK27: Entes Internacionales
A28: Bioeconomía: Biodiversidad | B28: Cacao | C28: Material de siembra y mejoramiento genético | D28: Merging eco-physiology and ML to select drought tolerant cacao genotypes | AK28: Entes Internacionales
A29: Bioeconomía: Prácticas de agricultura sostenible | B29: Cacao | C29: Manejo de sistemas productivos | D29: Proyecto 88352 - Aplicación y validación de tecnologías para potencializar la competitividad del sistema productivo de cacao en 8 municipios priorizados del departamento del Cauca | AK29: Entes Nacionales y Territoriales
A30: Bioeconomía: Economía circular | B30: Cacao | C30: Manejo cosecha, poscosecha y transformación | D30: 1002666: Viabilidad centros de fermentación en las regiones cacaoteras de Caldas, Huila y Tolima. | E30: Jader Rodríguez Cortina | F30: Líder | G30: AGROSAVIA | H30: Asociaciones de cacaocultores de Caldas, Huila y Tolima: APROCALG, ASOCAGIGANTE, ASOCAPOTRERILLOS, ASOCARECREO, ASOPECA, ASOPROCAR, ASOCACAO, ASOCATES, APROCAPAL, COCOAGRO, ASOPROBEL, ASOVICA, ASOCAMELIAS, AGROCAMUS, ASPRAFAL, ASOCANORA, ASOCANORCA, ASOSEMILLAS DEL CAMPO, ACA SANDIEGO, AMUCCOL, ASOCAT, ASOESTRELLA, ASOPEP, ASOPROLOMAT, ATACONDOR, RENACER LAS BLANCAS, ASAGROLT, ASOACAS, ASOPEROTOL, AGROEMPORTEGA, AMOCAL, APROCAMAITO, APROCASURT, ASOPROSINEV, ASOCATOL, ASOPARAISO ALTAMIRA, ASOPROMECOL, ECOAPROACIM | I30: Beneficiarios | J30: Baja disponibilidad de herramientas para establecer la viabilidad para establecer centros comunitarios de valorización poscosecha en Caldas, Huila y Tolima | K30: Desarrollar de una herramienta en excel para establecer la viabilidad para establecer centros comunitarios de valorización poscosecha en Caldas, Huila y Tolima | L30: Aumentar las capacidades de planificación en transporte, procesamiento, análisis de utilidades y escenarios de establecimientos de centros comunitarios de valorización poscosecha en Caldas, Huila y Tolima | M30: Plan Nacional de Desarrollo, Planes departamentales de Desarrollo, PECTIA y CONPES | N30: Modelación matemática para transporte, procesamiento poscosecha y análisis de utilidades (a corto y largo plazo) y escenarios de análisis. Desarrrolo de herramienta en Microsoft Excel utilizando Visual Basic for Applications (VBA), Análisis agroclimático, georreferenciación, modelación espacial | O30: Temperatura máxima, temperatura mínima, temperatura media, precipitación, radiación solar, velocidad del viento, presión de vapor, productividad, rendimiento en grano, calidad organoléptica. | P30: I+D+i | Q30: Una (1) zonificación agroclimática, Una (1) herramienta de excel para la planificación en transporte, procesamiento, análisis de utilidades y escenarios de establecimientos de centros comunitarios de valorización poscosecha en Caldas, Huila y Tolima | R30: Una (1) herramienta de excel para la planificación en transporte, procesamiento, análisis de utilidades y escenarios de establecimientos de centros comunitarios de valorización poscosecha en Caldas, Huila y Tolima, mapas agroclimáticos, base de datos georreferenciada, estudio de viabilidad, modelo logístico | T30: Modelo de centros regionales de fermentación para cacao con enfoque agroclimático y logístico | U30: Software | V30: 2 | W30: 5 | X30: 5 | Y30: Mejora en la toma de decisiones para optimizar la fermentación, logística y calidad diferenciada del cacao regional. | Z30: Potencial incremento de ingresos mediante valorización del cacao y aprovechamiento comercial de subproductos poscosecha. | AA30: Beneficio a asociaciones cacaoteras de Caldas, Huila y Tolima mediante fortalecimiento organizacional y acceso a modelos asociativos de valor agregado. | AB30: Promueve aprovechamiento de subproductos del cacao y reducción de pérdidas poscosecha mediante modelos sostenibles de transformación regional. | AC30: Caldas, Huila y Tolima | AD30: Gigante, Rivera, Tesalia, Ospina Pérez, Belalcazar, Mariquita, Norcasia, Santiago Pérez, Ortega, Chaparral | AE30: Asociaciones de cacaocultores y extensionistas | AF30: 600 productores y/o asistentes técnicos | AG30: 2.500 beneficiarios: productores, comercializadores, transformadores y actores regionales de la cadena de valor | AH30: Zonas cacaoteras en Colombia | AI30: Una (1) herramienta de excel para la planificación en transporte, procesamiento, análisis de utilidades y escenarios de establecimientos de centros comunitarios de valorización poscosecha en Caldas, Huila y Tolima | AK30: Entes Internacionales | AL30: 438479075 | AM30: 2023 | AN30: 2025 | AO30: Finalizado | AR30: Desarrollo de oferta tecnológica transferible Capacidad de convertir ciencia en productos de valor
A31: Bioeconomía: Economía circular | B31: Cacao | C31: Manejo cosecha, poscosecha y transformación | D31: ID: 1002667. Establecimiento de protocolos apropiados de fermentación basados en perfiles sensoriales del cacao en Caldas, Huila y Tolima. | E31: Jader Rodríguez Cortina | F31: Líder | G31: AGROSAVIA | H31: Asociaciones de cacaocultores de Caldas, Huila y Tolima: APROCALG, ASOCAGIGANTE, ASOCAPOTRERILLOS, ASOCARECREO, ASOPECA, ASOPROCAR, ASOCACAO, ASOCATES, APROCAPAL, COCOAGRO, ASOPROBEL, ASOVICA, ASOCAMELIAS, AGROCAMUS, ASPRAFAL, ASOCANORA, ASOCANORCA, ASOSEMILLAS DEL CAMPO, ACA SANDIEGO, AMUCCOL, ASOCAT, ASOESTRELLA, ASOPEP, ASOPROLOMAT, ATACONDOR, RENACER LAS BLANCAS, ASAGROLT, ASOACAS, ASOPEROTOL, AGROEMPORTEGA, AMOCAL, APROCAMAITO, APROCASURT, ASOPROSINEV, ASOCATOL, ASOPARAISO ALTAMIRA, ASOPROMECOL, ECOAPROACIM | I31: Beneficiarios | J31: Baja disponibilidad de protocolos de fermentación enfocados en obtención de cacao de calidad superior en Caldas, Huila y Tolima | K31: Desarrollar protocolos de fermentación basados en perfiles sensoriales del cacao de Caldas, Huila y Tolima. | L31: Aumentar la visibilización y valorización comercial del potencial de calidad del cacao regional en Caldas, Huila y Tolima a través de la aplicación de adecuadas prácticas poscosecha | M31: Plan Nacional de Desarrollo, Planes departamentales de Desarrollo, PECTIA y CONPES | N31: Metodología de fermentación espontánea con monitoreo de temperatura y pH, y análisis descriptivo de calidad sensorial en cacao según estándares internacionales COEX y CIRAD, Tipificación agroecológica | O31: Zonas agroecológicas, tiempo de fermentación, temperatura de tostado | P31: I+D+i | Q31: 200 Perfiles sensoriales de calidad de 10 zonas agroecológicas en Caldas, Huila y Tolima y recomendaciones de buenas prácticas poscosecha para potenciar la calidad | R31: 200 Perfiles sensoriales de calidad de 10 zonas agroecológicas en Caldas, Huila y Tolima, recomendaciones de buenas prácticas poscosecha para potenciar la calidad, protocolos de fermentación, base de datos espacial, mapas agroecológicos | T31: Protocolos regionales de fermentación para cacao basados en perfiles sensoriales y zonificación agroecológica. | U31: Protocolos | V31: 3 | W31: 6 | X31: 6 | Y31: Estandarización de fermentación y diferenciación sensorial del cacao en 10 zonas agroecológicas en Caldas, Huila y Tolima. | Z31: Potencial incremento de ingresos mediante comercialización de cacao diferenciado con perfiles sensoriales demandados por mercados internacionales. | AA31: Beneficio a productores cacaoteros de Caldas, Huila y Tolima mediante fortalecimiento de capacidades para producir cacao diferenciado de calidad superior y de mayor valor comercial. | AB31: Promueve manejo poscosecha adaptado a condiciones agroecológicas regionales, favoreciendo uso eficiente de recursos y valorización territorial del cacao. | AC31: Caldas, Huila y Tolima | AD31: Gigante, Rivera, Tesalia, Ospina Pérez, Belalcazar, Mariquita, Norcasia, Santiago Pérez, Ortega, Chaparral | AE31: Asociaciones de cacaocultores y extensionistas | AF31: 600 productores y/o asistentes técnicos | AG31: 2.500 beneficiarios: productores, comercializadores, transformadores y actores regionales de la cadena de valor | AH31: Zonas cacaoteras en Colombia | AI31: Equipos para transformación bean to bar de la minichocolatería de la planta de poscosecha | AK31: Entes Internacionales | AL31: 992001757 | AM31: 2023 | AN31: 2025 | AO31: Finalizado | AQ31: Calidad sensorial de cacao Protocolos de fermentación y secado
A32: Bioeconomía: Economía circular | B32: Cacao | C32: Manejo cosecha, poscosecha y transformación | D32: ID: 1002841. Implementación de un modelo para el aprovechamiento integral de las mazorcas de cacao para la generación de productos de valor agregado por medio de alternativas biotecnológicas | E32: Jader Rodríguez Cortina | F32: Líder | G32: AGROSAVIA | H32: Asociación de productores campesinos de Cisneros | I32: Beneficiarios | J32: Alta generación y subutilización de residuos de mazorca de cacao, causando impactos ambientales y baja valorización en sistemas productivos cacaoteros rurales. | K32: Implementar alternativas biotecnológicas para valorizar residuos de mazorca de cacao mediante compostaje, digestión anaerobia y pirólisis | L32: Fortalece la economía circular y la sostenibilidad rural mediante valorización de residuos, generación de bioinsumos y reducción de impactos ambientales en territorios PDET. | M32: Plan Nacional de Desarrollo, Plan departamental de Desarrollo el Valle del Cauca, y PECTIA | N32: Pirólisis para producción de biochar, compostaje y digestión anaerobia; caracterización fisicoquímica, diseño experimental de mezclas, análisis multicriterio TOPSIS y evaluación agronómica (Parra et al 2022) | O32: Temperatura, sólidos totales, ácidos grasos volátiles, metales pesados, nutrientes (NPK), acidez, pH, humedad, conductividad eléctrica, carbono orgánico total, sólidos volátiles, nitrógeno total, fósforo total, producción de metano, índice de germinación, biomasa aérea. | P32: I+D+i | Q32: Obtención de biochar, compost y digestato valorizados; implementación de prototipos piloto y validación agronómica de bioinsumos derivados de residuos de cacao. | R32: 1 prototipo de reactor anaerobio, 1 protocolo de operación, 1 artículo científico, 1 herramienta multicriterio para la selección de biomasa | S32: Parra-Orobio, B., Rodríguez-Cortina, J., Serna-Jiménez, J., Escobar-Parra, S., Santander-Muñoz, M., Martínez-Ruiz, Y., Álvarez-Trujillo, J.D., Soto-Paz, J. Hybrid decision-making tool for selecting co-substrates for the energy and agricultural valorization of cacao pod husk residues within a circular economy model. | U32: Equipos y protocolos | V32: 3 | W32: 6 | X32: 6 | Y32: Implementación piloto de tecnologías biotecnológicas para valorización de residuos, generando bioinsumos y bioproductos con potencial de aplicación agrícola y energética. | Z32: Generación de productos de valor agregado y reducción potencial de costos asociados al manejo de residuos y fertilización convencional | AA32: Beneficio a asociaciones cacaoteras rurales PDET y ZOMAC mediante transferencia tecnológica, fortalecimiento comunitario y participación de mujeres, jóvenes y grupos étnicos | AB32: Reducción de residuos agrícolas y mitigación de impactos sobre suelo mediante aprovechamiento circular, producción de biofertilizantes y disminución potencial de emisiones GEI | AC32: Valle del Cauca | AD32: Cisneros | AE32: Asociaciones de cacaocultores y extensionistas, comunidad académica y de investigación | AF32: 350 productores y/o asistentes técnicos | AG32: 1.800 beneficiarios | AH32: Zonas cacaoteras en Colombia | AI32: Sistema de biodigestión Anaerobia escala piloto, zona de compostaje a escala laboratorio | AK32: Entes Nacionales y Territoriales | AL32: 290000000 | AM32: 2024 | AN32: 2026 | AO32: En ejecución | AQ32: Valorización de subproductos Diseño de equipos de poscosecha Escalamiento de tecnologías en cacao | AR32: Enfoque de bioeconomía en cacao Desarrollo de oferta tecnológica transferible Capacidad de convertir ciencia en productos de valor
A33: Otro | B33: Cacao | C33: Manejo cosecha, poscosecha y transformación | D33: Idea. 0007950. Estrategia poscosecha para la inocuidad y comercio del cacao colombiano | E33: Margareth Santander | F33: Líder | G33: AGROSAVIA | H33: IICA, Asociaciones de cacaocultores de Tumaco | I33: Beneficiarios | AK33: Entes Internacionales
A34: Bioeconomía: Economía circular | B34: Cacao | C34: Manejo cosecha, poscosecha y transformación | D34: Idea. 0007978. Bioeconomía en cacao | E34: Margareth Santander | F34: Líder | G34: AGROSAVIA | H34: CIRAD, Asociaciones de cacaocultores de Caldas y Nariño | I34: Beneficiarios | AK34: Entes Internacionales
A35: Bioeconomía: Prácticas de agricultura sostenible | B35: Cacao | C35: Manejo de sistemas productivos | D35: Proyecto 95883. IMPLEMENTACIÓN DE INNOVACIONES TECNOLÓGICAS BAJO UN MODELO DE ECONOMÍA CIRCULAR, SOCIAL Y SOLIDARIA COMO APORTE A LA SEGURIDAD ALIMENTARIA Y A LA TRANSICIÓN SOSTENIBLE HACIA UN DESARROLLO AGRÍCOLA Y AGROINDUSTRIAL EN 4 MUNICIPIOS DEL DEPARTAMENTO DEL VALLE DEL CAUCA | AK35: Entes Nacionales y Territoriales
A36: Bioeconomía: Economía circular | B36: Cacao | C36: Manejo cosecha, poscosecha y transformación | D36: ID 001451: SGR Arauca poscosecha | E36: Jader Rodríguez Cortina | F36: Líder | G36: AGROSAVIA | H36: Asociaciones de cacaocultores de Arauca: COOMPROCAR, Coopcacao y CABEFAMI, Fedecacao, CIRAD | I36: Beneficiarios, aliados científicos para análisis de calidad, y aliados para trabajo en territorio | J36: Baja innovación tecnológica en productividad, inocuidad, calidad poscosecha y articulación empresarial de la cadena cacaotera en Arauca | K36: Implementar estrategias agroforestales y tecnologías agronómicas y poscosecha para mejorar productividad, inocuidad y calidad del cacao en Arauca. | L36: Fortalece la competitividad del cacao especial mediante innovación tecnológica, sostenibilidad productiva y acceso a mercados diferenciados con mayor valor agregado | M36: Plan Nacional de Desarrollo, Plan departamental de Desarrollo de Arauca, Planes municipales de desarrollo y PECTIA | N36: Modelización agroforestal, agricultura de precisión, geoeléctrica, geomicrobiología, metabolómica, análisis sensorial, evaluación molecular y validación participativa de tecnologías poscosecha | O36: Temperatura, pH, metabolitos precursores del flavour, metabolitos responsables del flavour, compuestos orgánicos volátiles, atributos sensoriales | P36: I+D+i | Q36: Equipos poscosecha, protocolos de fermentación para obtención de cacao de calidad superior | R36: Planta de bioeconomía en cacao, equipos de valorización poscosecha: Fermentador rotatorio, fermentador tipo biorreactor con control de variables de proceso, secador de alta eficiencia energética, secador por ventana refractiva, publicaciones científicas | S36: Llano, S., Zorro, A., Santander, M., Vaillant, F., Boulanger, R., Ocampo, D. M., & Escobar, S. (2025). Metabolomic insights into flavour precursor dynamics during fermentation of cacao beans cultivated in diverse climatic production zones in colombia. Food Research International, 115978. https://doi.org/10.1016/j.foodres.2025.115978 Gonzalez-Orozco, C., Porcel, M., Escobar, S., Bravo, D., Gutierrez Lopez, Y., Yockteng, R., Vaillant, F., Santander, M., Llano, S., Parra, K., Briceño, E., Carmona, J., Torres, S., Contreras, R., Otero, A., Pesca, A., & Carrillo, G. (2023). Cacao (Theobroma cacao L.) climate zones and its associated agrobiodiversity in Arauca, Colombia. Biodiversity Data Journal, 11. https://doi.org/10.3897/BDJ.11.e112771 Llano, S., Vaillant, F., Santander, M., Zorro-González, A., González-Orozco, C. E., Maraval, I., Boulanger, R., & Escobar, S. (2024). Exploring the Impact of Fermentation Time and Climate on Quality of Cocoa Bean-Derived Chocolate: Sensorial Profile and Volatilome Analysis. Foods, 13(16). https://doi.org/10.3390/foods13162614 Quintero, I., Ceccaldi, A., Martínez, H., Santander, M., Rodríguez, J., & Escobar, S. Dry cacao pulp in chocolate bars: a sustainable, nutrient-rich sweetener with enhanced sensory quality through refractance windows drying. (2025). Applied Food Research, 5(1). https://doi.org/10.1016/j.afres.2025.100700 Santander, M., Chica, V., Correa, H. A. M., Rodríguez, J., Villagran, E., Vaillant, F., & Escobar, S. (2025). Unravelling cocoa drying technology: a comprehensive review of the influence on flavor formation and quality. Foods, 14(5), 721. https://doi.org/10.3390/foods14050721 Santander, M., Leguizamón, L., Vaillant, F., Boulanger, R., Zuluaga, M., Maraval, I., Rodríguez, J., Llano, S., Sommerer, N., Meter, A., Escobar, S., & Meudec, E. (2025). Influence of driven fermentation of cacao in bioreactors on quality: decoding the effect of temperature, mixing, and ph on metabolomic, sensory, and volatile profiles. LWT-Food Science and Technology, 231, 1–12. https://doi.org/doi.org/10.1016/j.lwt.2025.118313 Zuluaga, M., Santander, M., Escobar, S., Vaillant, F. (2025). Metabolomics and peptidomics in cocoa: scientometrics analysis and systematic review of flavor-related chemical compounds in postharvest transformation. Journal of Scientometric Research; 14(3):716-731. https://jscires.org/10.5530/jscires.20251393 | T36: 1. Cajón compartimentado de madera para fermentación de cacao 2. Fermentador giratorio para tranformación poscosecha de cacao 3. Secador de alta eficiencia energética 4. Pirolizador | U36: Equipos y protocolos | V36: 3 | W36: 7 | X36: 7 | Y36: Mejora de calidad e inocuidad mediante tecnologías poscosecha estandarizadas | Z36: Incremento potencial de ingresos por acceso a mercados de cacao especial con primas superiores a US$1.000 por tonelada. | AA36: Beneficio directo a asociaciones cacaoteras de Arauca mediante fortalecimiento empresarial, transferencia tecnológica y formación de capital humano rural. | AB36: Impacto positivo al medio ambiente por uso de energías renovables (solar) en los equipos de varlozación poscosecha | AC36: Arauca | AD36: Arauquita, Saravena, Tame y Fortúl | AE36: Asociaciones de cacaocultores | AF36: 480 productores y/o asistentes técnicos | AG36: 3.500 beneficiarios: productores, comercializadores, transformadores y actores regionales de la cadena de cacao en Arauca. | AH36: Zonas cacaoteras en Colombia | AI36: Planta de Bioeconomía en cacao, Equipos de valorización poscosecha: Fermentador rotatorio, fermentador tipo biorreactor con control de variables de proceso, secador de alta eficiencia energética, secador por ventana refractiva | AK36: Entes Nacionales y Territoriales | AL36: 22.000.000 | AM36: 2019 | AN36: 2026 | AO36: En ejecución | AQ36: Calidad sensorial de cacao Protocolos de fermentación y secado Evaluación sensorial y química Escalamiento de tecnologías en cacao Diseño de equipos de poscosecha | AR36: Desarrollo de oferta tecnológica transferible Modelos territoriales replicables Capacidad de convertir ciencia en productos de valor
A37: ACI: Adaptación y resiliencia de los sistemas productivos agropecuarios frente a condiciones de clima cambiante | B37: Chontaduro | C37: Manejo ambiental y sostenibilidad | D37: Reducción del riesgo y adaptación al cambio climático_Modelos de adaptación agroclimática (MAPA). Chontaduro (Bactris gasipae) | AK37: Entes Nacionales y Territoriales
A38: Bioeconomía: Prácticas de agricultura sostenible | B38: Chontaduro | C38: Transf. de tecnologia, asist. técnica e innovación | D38: Gestión del conocimiento para el fortalecimiento productivo de los frutales del Valle del Cauca: Programa integral de Fruticultura PIF. FASE 2 | AK38: Entes Nacionales y Territoriales
A39: Bioeconomía: Prácticas de agricultura sostenible | B39: Chontaduro | C39: Material de siembra y mejoramiento genético | D39: Programa de fortalecimiento al sistema nacional de semillas producto de la intervención de sistemas locales de semillas: PLAN NACIONAL DE SEMILLAS | AK39: Entes Nacionales y Territoriales
A40: Bioeconomía: Prácticas de agricultura sostenible | B40: Chontaduro | C40: Manejo de sistemas productivos | D40: Desarrollo de estrategias para la recuperación de los sistemas productivos de Chontaduro (Bactris gasipaes) en sistemas agroforestales en zona rural del distrito de Buenaventura | AK40: Entes Nacionales y Territoriales
A41: Bioeconomía: Biodiversidad | B41: Coco | C41: Material de siembra y mejoramiento genético | D41: Colección de trabajo de materiales regionales de cocotero como base para repoblamiento y conservación de variabilidad genética. | AK41: Entes Nacionales y Territoriales
A42: Otro | B42: Coco | C42: Manejo de sistemas productivos | D42: Aunar esfuerzos económicos, técnicos, logísticos y humanos para el fortalecimiento del sistema de producción del cocotero en la costa pacífica colombiana a partir de la implementación de las buenas prácticas agrícolas (BPA), transferencia de tecnología en actividades de producción y manejo de viveros en los municipios de Tumaco, el Charco, Francisco Pizarro, La Tola, Mosquera, Santa Bárbara de Iscuande y Olaya Herrera del departamento de Nariño | AK42: Entes Nacionales y Territoriales
A43: Bioeconomía: Prácticas de agricultura sostenible | B43: Fique | C43: Material de siembra y mejoramiento genético | D43: Bases tecnologicas para el programa de mejoramiento del fique | AK43: Entes Nacionales y Territoriales
A44: Bioeconomía: Prácticas de agricultura sostenible | B44: Fique | C44: Fisiología vegetal y nutrición | D44: Bases tecnologicas para el programa de mejoramiento del fique | AK44: Entes Nacionales y Territoriales
A45: Bioeconomía: Biodiversidad | B45: Fique | C45: Manejo ambiental y sostenibilidad | D45: Áreas seleccionadas, especies priorizadas en diferentes regiones y viveros establecidos -Protocolos de producción del material vegetal y establecimiento. | AK45: Entes Nacionales y Territoriales
A46: Bioeconomía: Biodiversidad | B46: Forestal | C46: Manejo ambiental y sostenibilidad | D46: Establecimientos de arboretums en los centros de investigación utilizando material vegetal producido en el año anterior. RA: Diana Lucia Correa Moreno | AK46: Entes Nacionales y Territoriales
A47: Bioeconomía: Biodiversidad | B47: Forestal | C47: Manejo ambiental y sostenibilidad | D47: Datos de crecimiento de las especies en cada uno de los arboretums y sus proyecciones frente al comportamiento en otras regiones tradicionales de uso de las mismas. RA: Diana Lucia Correa Moreno | AK47: Entes Nacionales y Territoriales
A48: Bioeconomía: Biodiversidad | B48: Forestal | C48: Manejo ambiental y sostenibilidad | D48: Materiales nativos e introducidos de especies arbóreas caracterizados y evaluados para uso múltiple. RA: Diana Lucia Correa Moreno | AK48: Entes Nacionales y Territoriales
... A90: Bioeconomía: Prácticas de agricultura sostenible | B90: Maracuya | C90: Manejo sanitario y fitosanitario | D90: Desarrollo de componentes de manejo integrado de Dasiops inedulis (Diptera: Lonchaeidae) en maracuyá en el Valle del Cauca. | AK90: Entes Nacionales y Territoriales
A91: Seguridad alimentaria, nutricional y salud humana y animal | B91: Maracuya | C91: Manejo sanitario y fitosanitario | D91: Evaluación y selección de genotipos élite maracuyá | H91: Universidad Nacional | AC91: Valle del Cauca | AE91: Asociación de productores | AK91: Entes Nacionales y Territoriales
A92: ACI:Productividad agrícola agroambientalmente eficiente e integralmente sostenible | B92: Maracuya | C92: Material de siembra y mejoramiento genético | D92: Evaluación y selección de genotipos élite maracuyá | H92: Universidad Nacional | AC92: Valle del Cauca | AE92: Asociación de productores | AK92: Entes Nacionales y Territoriales
A93: ACI: Adaptación y resiliencia de los sistemas productivos agropecuarios frente a condiciones de clima cambiante | B93: Melón | C93: Manejo ambiental y sostenibilidad | D93: Reducción del riesgo y adaptación al cambio climático_Modelos de adaptación agroclimática (MAPA). Melón (Cucumis melo B). Facilitadora Regional MAPA: Diana Lucia Correa Moreno | AK93: Entes Nacionales y Territoriales
A94: ACI: Adaptación y resiliencia de los sistemas productivos agropecuarios frente a condiciones de clima cambiante | B94: Mora | C94: Manejo ambiental y sostenibilidad | D94: Reducción del riesgo y adaptación al cambio climático_Modelos de adaptación agroclimática (MAPA). Mora (Rubus glaucus B). Facilitadora Regional MAPA: Diana Lucia Correa Moreno | AK94: Entes Nacionales y Territoriales
A95: Bioeconomía: Prácticas de agricultura sostenible | B95: Naranjas | C95: Manejo sanitario y fitosanitario | D95: Validación de estrategias de manejo de poblaciones de Compsus viridivitattus, y ácaros como aporte del componente entomológico a la construcción del modelo productivo en cítricos. | AK95: Entes Nacionales y Territoriales
A96: Bioeconomía: Prácticas de agricultura sostenible | B96: Naranjas | C96: Manejo sanitario y fitosanitario | D96: Manejo de viveros y bases tecnológicas para la certificación genética, fisiológica y sanitaria | AK96: Entes Nacionales y Territoriales
A97: Bioeconomía: Prácticas de agricultura sostenible | B97: Naranjas | C97: Manejo sanitario y fitosanitario | D97: Evaluación de entomopatógenos y productos químicos para el control de Diaphorina citri Kuwayama (Hemiptera: Liviidae) y estudios biológicos de D. citri y su enemigo natural principal Tamarixia radiata (Waterston) (Hymenoptera: Eulophidae). | AK97: Entes Nacionales y Territoriales
A98: Bioeconomía: Prácticas de agricultura sostenible | B98: Naranjas | C98: Manejo sanitario y fitosanitario | D98: Generación de esquemas de indexación a enfermedades sistémicas de cítricos para asegurar la sanidad del material de siembra en Colombia | AK98: Entes Nacionales y Territoriales
A99: Bioeconomía: Biodiversidad | B99: Naranjas | C99: Material de siembra y mejoramiento genético | D99: Cultivares y patrones de cítricos adaptados a diferentes núcleos productivos en Colombia Fase 1. | AK99: Entes Nacionales y Territoriales
A100: Bioeconomía: Biodiversidad | B100: Naranjas | C100: Material de siembra y mejoramiento genético | D100: Cultivares y patrones de cítricos adaptados a diferentes núcleos productivos en Colombia Fase 2. | AK100: Entes Nacionales y Territoriales
A101: Bioeconomía: Biodiversidad | B101: Naranjas | C101: Material de siembra y mejoramiento genético | D101: Cultivares y patrones de cítricos adaptados a diferentes núcleos productivos en Colombia Fase 3. | AK101: Entes Nacionales y Territoriales
A102: Bioeconomía: Biodiversidad | B102: Naranjas | C102: Material de siembra y mejoramiento genético | D102: Cultivares y patrones de cítricos adaptados a diferentes núcleos productivos en Colombia Fase 4. | AK102: Entes Nacionales y Territoriales
A103: Bioeconomía: Economía circular | B103: Otro | C103: Manejo ambiental y sostenibilidad | D103: Proyecto Agroecologico Colombo Aleman (PACA) | AK103: Entes Nacionales y Territoriales
A104: NSA(MPIyS): Sistemas agroalimentarios globales | B104: Otro | C104: Material de siembra y mejoramiento genético | D104: Plataforma regional para impulsar la competitividad del aguacate andino | AK104: N/A
... A110: Bioeconomía: Prácticas de agricultura sostenible | B110: Palmaceas | C110: Manejo sanitario y fitosanitario | D110: Control biológico y químico de la cochinilla acanalada Crypticerya multicicatrices Kondo & Unruh (Hemiptera: Monophlebidae). | AK110: Entes Internacionales
A111: ACI:Productividad agrícola agroambientalmente eficiente e integralmente sostenible | B111: Piña | C111: Material de siembra y mejoramiento genético | D111: Producción de semilla de calidad para Casanare | H111: Bolívar: Asociación de Agricultores Campesinos Chitacorral (Agrocazan), La Vega: Asociación Productora de Quinua Resguardo de Pancitara (Asproquinpa), La Vega: Asociación Productora de Quinua Resguardo de Pancitara (Asproquinpa), Totoró: Asociación de Productores de Quinua (Asoquinua), Silvia: Cooperativa Multiactiva Indígena de Las Delicias | AC111: Cauca | AD111: Bolívar, La Vega, Silvia, Totoró | AE111: Comunidad campesina | AK111: Entes Nacionales y Territoriales
A112: ACI:Productividad agrícola agroambientalmente eficiente e integralmente sostenible | B112: Piña | C112: Fisiología vegetal y nutrición | D112: Estrategias de manejo agronómico para la piña MD2 para sistemas productivos del departamento del Valle del Cauca, potenciando parámetros de adaptación y sostenibilidad. | AK112: Entes Nacionales y Territoriales
A113: Bioeconomía: Prácticas de agricultura sostenible | B113: Piña | C113: Manejo sanitario y fitosanitario | D113: Estrategias para el manejo integrado de las principales enfermedades y plagas que se presentan en el cultivo de piña (cultivar MD2) en los departamentos del Valle del Cauca y Santander. Fase I y Fase II. | AK113: Entes Nacionales y Territoriales
A114: Bioeconomía: Economía circular | B114: Piña | C114: Manejo ambiental y sostenibilidad | D114: Identificación de accesiones de piña (Ananas spp.) por su potencial para la obtención de fibra de la hoja para uso agroindustrial. | AK114: Entes Nacionales y Territoriales
A115: Bioeconomía: Prácticas de agricultura sostenible | B115: Pitaya Amarilla | C115: Manejo sanitario y fitosanitario | D115: Desarrollo de estrategias de manejo integrado de la mosca del botón floral de la pitaya Dasiops sp. en el Valle del Cauca. | AC115: Valle del Cauca | AK115: Entes Nacionales y Territoriales
A116: Bioeconomía: Prácticas de agricultura sostenible | B116: Pitaya Amarilla | C116: Manejo de sistemas productivos | D116: Recomendaciones de manejo agronómico y fitosanitario del cultivo de la Pitaya Amarilla para las regiones productoras de Colombia. | AK116: N/A
A117: ACI:Productividad agrícola agroambientalmente eficiente e integralmente sostenible | B117: Platano | C117: Manejo de suelos y aguas | D117: Propuesta enviada a convocatoria Fontagro2025. Transformación digital del cultivo de plátano: hacia la eficiencia productiva y el relevo generacional
A118: ACI:Productividad agrícola agroambientalmente eficiente e integralmente sostenible | B118: Platano | C118: Manejo de suelos y aguas | D118: Transformación digital del cultivo de plátano: hacia la eficiencia productiva y el relevo generacional | AK118: Entes Internacionales
A119: Seguridad alimentaria, nutricional y salud humana y animal | B119: Platano | C119: Manejo sanitario y fitosanitario | D119: Sanidad Prevención y Control Enfermedades Plátano F1 y F2 | H119: ICA | AC119: Caldas, Risaralda, Cauca y Valle del Cauca | AE119: Asociación de productores | AK119: Entes Nacionales y Territoriales
A120: Bioeconomía: Prácticas de agricultura sostenible | B120: Quinua | C120: Fisiología vegetal y nutrición | D120: Alternativas tecnológicas para el cultivo de la quinua en el departamento del Cauca | AK120: Entes Nacionales y Territoriales
A121: Bioeconomía: Prácticas de agricultura sostenible | B121: Quinua | C121: Fisiología vegetal y nutrición | D121: Alternativas tecnológicas para el cultivo de la quinua en el departamento del Cauca | AC121: Valle del Cauca | AK121: Entes Nacionales y Territoriales
A122: Bioeconomía: Prácticas de agricultura sostenible | B122: Quinua | C122: Fisiología vegetal y nutrición | D122: Desarrollo de modelos de producción de semilla promisorias Quinua en Cauca PNS | AC122: San Andres y Providencia. | AK122: Entes Nacionales y Territoriales
A123: Bioeconomía: Prácticas de agricultura sostenible | B123: Quinua | C123: Manejo de suelos y aguas | D123: Alternativas tecnológicas para el cultivo de la quinua en el departamento del Cauca | H123: ICESI, Hugo Restrepo, Utedé | AC123: Antioquia, Valle del Cauca y Cauca | AD123: Rionegro, Campamento, Palmira, Buga y Timbío | AK123: Entes Nacionales y Territoriales
A124: Bioeconomía: Prácticas de agricultura sostenible | B124: Quinua | C124: Manejo sanitario y fitosanitario | D124: Desarrollo de nuevas recomendaciones tecnológicas para contribuir con la competitividad y la sostenibilidad del sector quinuero del departamento del Cauca, Convenio 1983, Actividad 8: Caracterizar los problemas de enfermedades del cultivo de quinua en el departamento del Cauca (Fase 1), Diana Milena Rodríguez Mora | H124: Asociación de Agricultores Campesinos de la Zanja Chitacorral(Agrocazan), Asociación Productora de Quinua Resguardo de Pancitará (Asproquinpa), Asociación de Productores de Quinua (Asoquinua) y Cooperativa Multiactiva Indígena de Las Delicias | AC124: Cauca | AD124: Bolívar, La Vega, Silvia, Totoró | AE124: Comunidad Indígena | AF124: 792 personas | AK124: Entes Nacionales y Territoriales
A125: ACI: Gestión eficiente de los recursos agua, nutrientes, suelo y energía para la mitigación de GEI en los sistemas de producción agrícola | B125: Quinua | C125: Manejo ambiental y sostenibilidad | D125: Actividad 4.2: Utilización de coberturas vegetales y mitigación de gases de efecto invernadero GEI. RA: Diana Lucia Correa Moreno | AC125: Cauca | AK125: Entes Nacionales y Territoriales
A126: Bioeconomía: Prácticas de agricultura sostenible | B126: Yuca | C126: Material de siembra y mejoramiento genético | D126: Material de siembra con calidad de las Variedades de yuca AGROSAVIA Cumbre 3 y AGROSAVIA La Francesa | H126: Fedecoco | AC126: Nariño | AD126: Tumaco, el Charco, Francisco Pizarro, La Tola, Mosquera, Santa Bárbara de Iscuande y Olaya Herrera | AE126: Comunidad Afrocolombiana | AF126: 300 | AK126: Entes Nacionales y Territoriales
A127: NSA(MPIyS): Sistemas alimentarios regenerativos | B127: Otro | C127: Manejo de sistemas productivos | D127: Ruta Agroecológica_Valle del Cauca. RA: Diana Lucia Correa Moreno | AC127: Valle | AE127: Asociación de productores | AK127: Entes Nacionales y Territoriales
A128: NSA(MPIyS): Sistemas alimentarios regenerativos | B128: Otro | C128: Manejo de sistemas productivos | D128: Mujer rural:conservación de semillas. Lider: Diana Lucia Correa Moreno | AC128: Valle | AE128: Asociación de productores | AK128: Sector privado
A129: NSA(MPIyS): Restauración de los ecosistemas | B129: Otro | C129: Manejo ambiental y sostenibilidad | D129: Restauración participativa de ecosistemas y fortalecimiento de la gobernanza ambiental y resiliencia climática en territorios afrocolombianos de la Cuenca del Rio San Jorge (Alto Patia - Cauca) afectados por deforestación, desertificación y sequía. Lider: Diana Lucia Correa Moreno | AC129: Cauca | AE129: Comunidad Afrocolombiana | AK129: Entes Nacionales y Territoriales
A130: ACI: Adaptación y resiliencia de los sistemas productivos agropecuarios frente a condiciones de clima cambiante | B130: Otro | C130: Manejo ambiental y sostenibilidad | D130: Fortalecimiento de las capacidades de I+D+i del centro de investigación Palmira | AC130: Valle | AE130: Comunidad Afrocolombiana | AK130: Entes Nacionales y Territoriales
A131: Bioeconomía: Prácticas de agricultura sostenible | B131: Aguacate Hass | C131: Manejo sanitario y fitosanitario | D131: Estrategias de prevención y manejo de enfermedades limitantes en la producción de Aguacate en las principales zonas productoras. | H131: Viveristas y comercializadores de aguacate, ICA | AC131: Cauca, Quindío, Risaralda, Valle del Cauca | AD131: Cauca (Timbío), Quindío (Calarcá, La Tebaida, Quimbaya), Risaralda (Cerritos, Pereira), Valle del Cauca (Andalucía, Bolívar, Caicedonia, Candelaria, Cerrito, La Unión, La Victoria, Palmira, Sevilla) | AE131: Comunidad campesina | AK131: Entes Nacionales y Territoriales
A132: Bioeconomía: Prácticas de agricultura sostenible | B132: Pitaya Amarilla | C132: Manejo sanitario y fitosanitario | D132: Opciones de manejo para reducir los principales problemas del cultivo de la Pitaya en el Valle del Cauca | H132: Asoppitaya: Asociación de productores de pitaya- Ingenieros Agrónomos Asociados | AC132: Valle del Cauca | AD132: Municipios de Palmira-Darien-Riofrio | AE132: Asociación de productores | AK132: Entes Nacionales y Territoriales
A133: Bioeconomía: Prácticas de agricultura sostenible | B133: Cacao | C133: Manejo de sistemas productivos | D133: Idea: Proyecto 95883. IMPLEMENTACIÓN DE INNOVACIONES TECNOLÓGICAS BAJO UN MODELO DE ECONOMÍA CIRCULAR, SOCIAL Y SOLIDARIA COMO APORTE A LA SEGURIDAD ALIMENTARIA Y A LA TRANSICIÓN SOSTENIBLE HACIA UN DESARROLLO AGRÍCOLA Y AGROINDUSTRIAL EN 4 MUNICIPIOS DEL DEPARTAMENTO DEL VALLE DEL CAUCA | AK133: Entes Nacionales y Territoriales

Sheet Diccionario_Capacidades
A1: Área temática | B1: Categoría | C1: Capacidad
A2: Enfermedades | B2: Emergente | C2: Monitoreo fitosanitario con herramientas digitales
A3: Enfermedades | B3: Emergente | C3: Agricultura con enfoque agroecológico
A4: Enfermedades | B4: Emergente | C4: Estudios de salud del suelo (microbioma)
A5: Enfermedades | B5: Emergente | C5: Evaluación de impacto ambiental de PQUAs
A6: Enfermedades | B6: Emergente | C6: Implementación de esquemas de aseguramiento fitosanitario (EAS)
A7: Enfermedades | B7: Emergente | C7: Estudios de resistencia genética a patógenos
A8: Enfermedades | B8: Consolidada | C8: Diagnóstico y caracterización de patógenos
A9: Enfermedades | B9: Consolidada | C9: Indexación de enfermedades
A10: Enfermedades | B10: Consolidada | C10: Limpieza fitosanitaria de material vegetal
A11: Enfermedades | B11: Consolidada | C11: Implementación de MIE en múltiples cultivos
A12: Enfermedades | B12: Consolidada | C12: Evaluación de resistencia de plantas
... A84: Poscosecha | B84: Distintiva | C84: Capacidad de convertir ciencia en productos de valor

Sheet Capacidades_CI
A1: ID capacidad | B1: Capacidad | C1: Categoría | D1: Área temática | E1: Sistema productivo | F1: Proyecto asociado | G1: Programa estratégico | H1: Investigador líder
A2: =IFERROR(IF(Portafolio_Proyectos!$AP2="","","CAP-"&ROW()-1),"") -> CAP-1 | B2: =IFERROR(IF(Portafolio_Proyectos!$AP2="","",Portafolio_Proyectos!$AP2),"") -> Indicadores de sostenibilidad ambiental | C2: =IFERROR(IF(Portafolio_Proyectos!$AP2="","","Emergente"),"") -> Emergente | D2: =IFERROR(IF(Portafolio_Proyectos!$AP2="","",Portafolio_Proyectos!$C2),"") -> Fisiología vegetal y nutrición | E2: =IFERROR(IF(Portafolio_Proyectos!$AP2="","",Portafolio_Proyectos!$B2),"") -> Aguacate Hass | F2: =IFERROR(IF(Portafolio_Proyectos!$AP2="","",Portafolio_Proyectos!$D2),"") -> Convenio 1790. Manejo integrado del cultivo | G2: =IFERROR(IF(Portafolio_Proyectos!$AP2="","",Portafolio_Proyectos!$A2),"") -> Bioeconomía: Prácticas de agricultura sostenible | H2: =IFERROR(IF(Portafolio_Proyectos!$AP2="","",Portafolio_Proyectos!$E2),"") -> Alexander Rebolledo Roa
A3: =IFERROR(IF(Portafolio_Proyectos!$AQ2="","","CAP-"&ROW()-1),"") | B3: =IFERROR(IF(Portafolio_Proyectos!$AQ2="","",Portafolio_Proyectos!$AQ2),"") | C3: =IFERROR(IF(Portafolio_Proyectos!$AQ2="","","Consolidada"),"") | D3: =IFERROR(IF(Portafolio_Proyectos!$AQ2="","",Portafolio_Proyectos!$C2),"") | E3: =IFERROR(IF(Portafolio_Proyectos!$AQ2="","",Portafolio_Proyectos!$B2),"") | F3: =IFERROR(IF(Portafolio_Proyectos!$AQ2="","",Portafolio_Proyectos!$D2),"") | G3: =IFERROR(IF(Portafolio_Proyectos!$AQ2="","",Portafolio_Proyectos!$A2),"") | H3: =IFERROR(IF(Portafolio_Proyectos!$AQ2="","",Portafolio_Proyectos!$E2),"")
A4: =IFERROR(IF(Portafolio_Proyectos!$AR2="","","CAP-"&ROW()-1),"") | B4: =IFERROR(IF(Portafolio_Proyectos!$AR2="","",Portafolio_Proyectos!$AR2),"") | C4: =IFERROR(IF(Portafolio_Proyectos!$AR2="","","Distintiva"),"") | D4: =IFERROR(IF(Portafolio_Proyectos!$AR2="","",Portafolio_Proyectos!$C2),"") | E4: =IFERROR(IF(Portafolio_Proyectos!$AR2="","",Portafolio_Proyectos!$B2),"") | F4: =IFERROR(IF(Portafolio_Proyectos!$AR2="","",Portafolio_Proyectos!$D2),"") | G4: =IFERROR(IF(Portafolio_Proyectos!$AR2="","",Portafolio_Proyectos!$A2),"") | H4: =IFERROR(IF(Portafolio_Proyectos!$AR2="","",Portafolio_Proyectos!$E2),"")
A5: =IFERROR(IF(Portafolio_Proyectos!$AP3="","","CAP-"&ROW()-1),"") | B5: =IFERROR(IF(Portafolio_Proyectos!$AP3="","",Portafolio_Proyectos!$AP3),"") | C5: =IFERROR(IF(Portafolio_Proyectos!$AP3="","","Emergente"),"") | D5: =IFERROR(IF(Portafolio_Proyectos!$AP3="","",Portafolio_Proyectos!$C3),"") | E5: =IFERROR(IF(Portafolio_Proyectos!$AP3="","",Portafolio_Proyectos!$B3),"") | F5: =IFERROR(IF(Portafolio_Proyectos!$AP3="","",Portafolio_Proyectos!$D3),"") | G5: =IFERROR(IF(Portafolio_Proyectos!$AP3="","",Portafolio_Proyectos!$A3),"") | H5: =IFERROR(IF(Portafolio_Proyectos!$AP3="","",Portafolio_Proyectos!$E3),"")
A6: =IFERROR(IF(Portafolio_Proyectos!$AQ3="","","CAP-"&ROW()-1),"") | B6: =IFERROR(IF(Portafolio_Proyectos!$AQ3="","",Portafolio_Proyectos!$AQ3),"") | C6: =IFERROR(IF(Portafolio_Proyectos!$AQ3="","","Consolidada"),"") | D6: =IFERROR(IF(Portafolio_Proyectos!$AQ3="","",Portafolio_Proyectos!$C3),"") | E6: =IFERROR(IF(Portafolio_Proyectos!$AQ3="","",Portafolio_Proyectos!$B3),"") | F6: =IFERROR(IF(Portafolio_Proyectos!$AQ3="","",Portafolio_Proyectos!$D3),"") | G6: =IFERROR(IF(Portafolio_Proyectos!$AQ3="","",Portafolio_Proyectos!$A3),"") | H6: =IFERROR(IF(Portafolio_Proyectos!$AQ3="","",Portafolio_Proyectos!$E3),"")
A7: =IFERROR(IF(Portafolio_Proyectos!$AR3="","","CAP-"&ROW()-1),"") | B7: =IFERROR(IF(Portafolio_Proyectos!$AR3="","",Portafolio_Proyectos!$AR3),"") | C7: =IFERROR(IF(Portafolio_Proyectos!$AR3="","","Distintiva"),"") | D7: =IFERROR(IF(Portafolio_Proyectos!$AR3="","",Portafolio_Proyectos!$C3),"") | E7: =IFERROR(IF(Portafolio_Proyectos!$AR3="","",Portafolio_Proyectos!$B3),"") | F7: =IFERROR(IF(Portafolio_Proyectos!$AR3="","",Portafolio_Proyectos!$D3),"") | G7: =IFERROR(IF(Portafolio_Proyectos!$AR3="","",Portafolio_Proyectos!$A3),"") | H7: =IFERROR(IF(Portafolio_Proyectos!$AR3="","",Portafolio_Proyectos!$E3),"")
A8: =IFERROR(IF(Portafolio_Proyectos!$AP4="","","CAP-"&ROW()-1),"") | B8: =IFERROR(IF(Portafolio_Proyectos!$AP4="","",Portafolio_Proyectos!$AP4),"") | C8: =IFERROR(IF(Portafolio_Proyectos!$AP4="","","Emergente"),"") | D8: =IFERROR(IF(Portafolio_Proyectos!$AP4="","",Portafolio_Proyectos!$C4),"") | E8: =IFERROR(IF(Portafolio_Proyectos!$AP4="","",Portafolio_Proyectos!$B4),"") | F8: =IFERROR(IF(Portafolio_Proyectos!$AP4="","",Portafolio_Proyectos!$D4),"") | G8: =IFERROR(IF(Portafolio_Proyectos!$AP4="","",Portafolio_Proyectos!$A4),"") | H8: =IFERROR(IF(Portafolio_Proyectos!$AP4="","",Portafolio_Proyectos!$E4),"")
A9: =IFERROR(IF(Portafolio_Proyectos!$AQ4="","","CAP-"&ROW()-1),"") | B9: =IFERROR(IF(Portafolio_Proyectos!$AQ4="","",Portafolio_Proyectos!$AQ4),"") | C9: =IFERROR(IF(Portafolio_Proyectos!$AQ4="","","Consolidada"),"") | D9: =IFERROR(IF(Portafolio_Proyectos!$AQ4="","",Portafolio_Proyectos!$C4),"") | E9: =IFERROR(IF(Portafolio_Proyectos!$AQ4="","",Portafolio_Proyectos!$B4),"") | F9: =IFERROR(IF(Portafolio_Proyectos!$AQ4="","",Portafolio_Proyectos!$D4),"") | G9: =IFERROR(IF(Portafolio_Proyectos!$AQ4="","",Portafolio_Proyectos!$A4),"") | H9: =IFERROR(IF(Portafolio_Proyectos!$AQ4="","",Portafolio_Proyectos!$E4),"")
A10: =IFERROR(IF(Portafolio_Proyectos!$AR4="","","CAP-"&ROW()-1),"") | B10: =IFERROR(IF(Portafolio_Proyectos!$AR4="","",Portafolio_Proyectos!$AR4),"") | C10: =IFERROR(IF(Portafolio_Proyectos!$AR4="","","Distintiva"),"") | D10: =IFERROR(IF(Portafolio_Proyectos!$AR4="","",Portafolio_Proyectos!$C4),"") | E10: =IFERROR(IF(Portafolio_Proyectos!$AR4="","",Portafolio_Proyectos!$B4),"") | F10: =IFERROR(IF(Portafolio_Proyectos!$AR4="","",Portafolio_Proyectos!$D4),"") | G10: =IFERROR(IF(Portafolio_Proyectos!$AR4="","",Portafolio_Proyectos!$A4),"") | H10: =IFERROR(IF(Portafolio_Proyectos!$AR4="","",Portafolio_Proyectos!$E4),"")
A11: =IFERROR(IF(Portafolio_Proyectos!$AP5="","","CAP-"&ROW()-1),"") | B11: =IFERROR(IF(Portafolio_Proyectos!$AP5="","",Portafolio_Proyectos!$AP5),"") | C11: =IFERROR(IF(Portafolio_Proyectos!$AP5="","","Emergente"),"") | D11: =IFERROR(IF(Portafolio_Proyectos!$AP5="","",Portafolio_Proyectos!$C5),"") | E11: =IFERROR(IF(Portafolio_Proyectos!$AP5="","",Portafolio_Proyectos!$B5),"") | F11: =IFERROR(IF(Portafolio_Proyectos!$AP5="","",Portafolio_Proyectos!$D5),"") | G11: =IFERROR(IF(Portafolio_Proyectos!$AP5="","",Portafolio_Proyectos!$A5),"") | H11: =IFERROR(IF(Portafolio_Proyectos!$AP5="","",Portafolio_Proyectos!$E5),"")
A12: =IFERROR(IF(Portafolio_Proyectos!$AQ5="","","CAP-"&ROW()-1),"") | B12: =IFERROR(IF(Portafolio_Proyectos!$AQ5="","",Portafolio_Proyectos!$AQ5),"") | C12: =IFERROR(IF(Portafolio_Proyectos!$AQ5="","","Consolidada"),"") | D12: =IFERROR(IF(Portafolio_Proyectos!$AQ5="","",Portafolio_Proyectos!$C5),"") | E12: =IFERROR(IF(Portafolio_Proyectos!$AQ5="","",Portafolio_Proyectos!$B5),"") | F12: =IFERROR(IF(Portafolio_Proyectos!$AQ5="","",Portafolio_Proyectos!$D5),"") | G12: =IFERROR(IF(Portafolio_Proyectos!$AQ5="","",Portafolio_Proyectos!$A5),"") | H12: =IFERROR(IF(Portafolio_Proyectos!$AQ5="","",Portafolio_Proyectos!$E5),"")
A13: =IFERROR(IF(Portafolio_Proyectos!$AR5="","","CAP-"&ROW()-1),"") | B13: =IFERROR(IF(Portafolio_Proyectos!$AR5="","",Portafolio_Proyectos!$AR5),"") | C13: =IFERROR(IF(Portafolio_Proyectos!$AR5="","","Distintiva"),"") | D13: =IFERROR(IF(Portafolio_Proyectos!$AR5="","",Portafolio_Proyectos!$C5),"") | E13: =IFERROR(IF(Portafolio_Proyectos!$AR5="","",Portafolio_Proyectos!$B5),"") | F13: =IFERROR(IF(Portafolio_Proyectos!$AR5="","",Portafolio_Proyectos!$D5),"") | G13: =IFERROR(IF(Portafolio_Proyectos!$AR5="","",Portafolio_Proyectos!$A5),"") | H13: =IFERROR(IF(Portafolio_Proyectos!$AR5="","",Portafolio_Proyectos!$E5),"")
A14: =IFERROR(IF(Portafolio_Proyectos!#REF!="","","CAP-"&ROW()-1),"") | B14: =IFERROR(IF(Portafolio_Proyectos!#REF!="","",Portafolio_Proyectos!#REF!),"") | C14: =IFERROR(IF(Portafolio_Proyectos!#REF!="","","Emergente"),"") | D14: =IFERROR(IF(Portafolio_Proyectos!#REF!="","",Portafolio_Proyectos!#REF!),"") | E14: =IFERROR(IF(Portafolio_Proyectos!#REF!="","",Portafolio_Proyectos!#REF!),"") | F14: =IFERROR(IF(Portafolio_Proyectos!#REF!="","",Portafolio_Proyectos!#REF!),"") | G14: =IFERROR(IF(Portafolio_Proyectos!#REF!="","",Portafolio_Proyectos!#REF!),"") | H14: =IFERROR(IF(Portafolio_Proyectos!#REF!="","",Portafolio_Proyectos!#REF!),"")
A15: =IFERROR(IF(Portafolio_Proyectos!#REF!="","","CAP-"&ROW()-1),"") | B15: =IFERROR(IF(Portafolio_Proyectos!#REF!="","",Portafolio_Proyectos!#REF!),"") | C15: =IFERROR(IF(Portafolio_Proyectos!#REF!="","","Consolidada"),"") | D15: =IFERROR(IF(Portafolio_Proyectos!#REF!="","",Portafolio_Proyectos!#REF!),"") | E15: =IFERROR(IF(Portafolio_Proyectos!#REF!="","",Portafolio_Proyectos!#REF!),"") | F15: =IFERROR(IF(Portafolio_Proyectos!#REF!="","",Portafolio_Proyectos!#REF!),"") | G15: =IFERROR(IF(Portafolio_Proyectos!#REF!="","",Portafolio_Proyectos!#REF!),"") | H15: =IFERROR(IF(Portafolio_Proyectos!#REF!="","",Portafolio_Proyectos!#REF!),"")
A16: =IFERROR(IF(Portafolio_Proyectos!#REF!="","","CAP-"&ROW()-1),"") | B16: =IFERROR(IF(Portafolio_Proyectos!#REF!="","",Portafolio_Proyectos!#REF!),"") | C16: =IFERROR(IF(Portafolio_Proyectos!#REF!="","","Distintiva"),"") | D16: =IFERROR(IF(Portafolio_Proyectos!#REF!="","",Portafolio_Proyectos!#REF!),"") | E16: =IFERROR(IF(Portafolio_Proyectos!#REF!="","",Portafolio_Proyectos!#REF!),"") | F16: =IFERROR(IF(Portafolio_Proyectos!#REF!="","",Portafolio_Proyectos!#REF!),"") | G16: =IFERROR(IF(Portafolio_Proyectos!#REF!="","",Portafolio_Proyectos!#REF!),"") | H16: =IFERROR(IF(Portafolio_Proyectos!#REF!="","",Portafolio_Proyectos!#REF!),"")
A17: =IFERROR(IF(Portafolio_Proyectos!$AP6="","","CAP-"&ROW()-1),"") -> CAP-16 | B17: =IFERROR(IF(Portafolio_Proyectos!$AP6="","",Portafolio_Proyectos!$AP6),"") -> Indicadores de sostenibilidad ambiental | C17: =IFERROR(IF(Portafolio_Proyectos!$AP6="","","Emergente"),"") -> Emergente | D17: =IFERROR(IF(Portafolio_Proyectos!$AP6="","",Portafolio_Proyectos!$C6),"") -> Fisiología vegetal y nutrición | E17: =IFERROR(IF(Portafolio_Proyectos!$AP6="","",Portafolio_Proyectos!$B6),"") -> Aguacate Hass | F17: =IFERROR(IF(Portafolio_Proyectos!$AP6="","",Portafolio_Proyectos!$D6),"") -> Convenio 1929. Desarrollo y validación de tecnologías para incrementar la productividad del cultivo | G17: =IFERROR(IF(Portafolio_Proyectos!$AP6="","",Portafolio_Proyectos!$A6),"") -> ACI:Productividad agrícola agroambientalmente eficiente e integralmente sostenible | H17: =IFERROR(IF(Portafolio_Proyectos!$AP6="","",Portafolio_Proyectos!$E6),"") -> Alexander Rebolledo Roa
A18: =IFERROR(IF(Portafolio_Proyectos!$AQ6="","","CAP-"&ROW()-1),"") -> CAP-17 | B18: =IFERROR(IF(Portafolio_Proyectos!$AQ6="","",Portafolio_Proyectos!$AQ6),"") -> Fertilización por sitio específico | C18: =IFERROR(IF(Portafolio_Proyectos!$AQ6="","","Consolidada"),"") -> Consolidada | D18: =IFERROR(IF(Portafolio_Proyectos!$AQ6="","",Portafolio_Proyectos!$C6),"") -> Fisiología vegetal y nutrición | E18: =IFERROR(IF(Portafolio_Proyectos!$AQ6="","",Portafolio_Proyectos!$B6),"") -> Aguacate Hass | F18: =IFERROR(IF(Portafolio_Proyectos!$AQ6="","",Portafolio_Proyectos!$D6),"") -> Convenio 1929. Desarrollo y validación de tecnologías para incrementar la productividad del cultivo | G18: =IFERROR(IF(Portafolio_Proyectos!$AQ6="","",Portafolio_Proyectos!$A6),"") -> ACI:Productividad agrícola agroambientalmente eficiente e integralmente sostenible | H18: =IFERROR(IF(Portafolio_Proyectos!$AQ6="","",Portafolio_Proyectos!$E6),"") -> Alexander Rebolledo Roa
A19: =IFERROR(IF(Portafolio_Proyectos!$AR6="","","CAP-"&ROW()-1),"") | B19: =IFERROR(IF(Portafolio_Proyectos!$AR6="","",Portafolio_Proyectos!$AR6),"") | C19: =IFERROR(IF(Portafolio_Proyectos!$AR6="","","Distintiva"),"") | D19: =IFERROR(IF(Portafolio_Proyectos!$AR6="","",Portafolio_Proyectos!$C6),"") | E19: =IFERROR(IF(Portafolio_Proyectos!$AR6="","",Portafolio_Proyectos!$B6),"") | F19: =IFERROR(IF(Portafolio_Proyectos!$AR6="","",Portafolio_Proyectos!$D6),"") | G19: =IFERROR(IF(Portafolio_Proyectos!$AR6="","",Portafolio_Proyectos!$A6),"") | H19: =IFERROR(IF(Portafolio_Proyectos!$AR6="","",Portafolio_Proyectos!$E6),"")
A20: =IFERROR(IF(Portafolio_Proyectos!$AP7="","","CAP-"&ROW()-1),"") -> CAP-19 | B20: =IFERROR(IF(Portafolio_Proyectos!$AP7="","",Portafolio_Proyectos!$AP7),"") -> Nutrición y riego para aguacate de consumo interno (Lorena) | C20: =IFERROR(IF(Portafolio_Proyectos!$AP7="","","Emergente"),"") -> Emergente | D20: =IFERROR(IF(Portafolio_Proyectos!$AP7="","",Portafolio_Proyectos!$C7),"") -> Fisiología vegetal y nutrición | E20: =IFERROR(IF(Portafolio_Proyectos!$AP7="","",Portafolio_Proyectos!$B7),"") -> Aguacate Hass | F20: =IFERROR(IF(Portafolio_Proyectos!$AP7="","",Portafolio_Proyectos!$D7),"") -> Portafolio. Fortalecimiento cadena de valor de aguacate. Convocatoria 42. SGR-Región Pacífico | G20: =IFERROR(IF(Portafolio_Proyectos!$AP7="","",Portafolio_Proyectos!$A7),"") -> ACI:Productividad agrícola agroambientalmente eficiente e integralmente sostenible | H20: =IFERROR(IF(Portafolio_Proyectos!$AP7="","",Portafolio_Proyectos!$E7),"") -> Alexander Rebolledo Roa
A21: =IFERROR(IF(Portafolio_Proyectos!$AQ7="","","CAP-"&ROW()-1),"") -> CAP-20 | B21: =IFERROR(IF(Portafolio_Proyectos!$AQ7="","",Portafolio_Proyectos!$AQ7),"") -> Fertilización por sitio específico (IBN) y riego por balance hídrico | C21: =IFERROR(IF(Portafolio_Proyectos!$AQ7="","","Consolidada"),"") -> Consolidada | D21: =IFERROR(IF(Portafolio_Proyectos!$AQ7="","",Portafolio_Proyectos!$C7),"") -> Fisiología vegetal y nutrición | E21: =IFERROR(IF(Portafolio_Proyectos!$AQ7="","",Portafolio_Proyectos!$B7),"") -> Aguacate Hass | F21: =IFERROR(IF(Portafolio_Proyectos!$AQ7="","",Portafolio_Proyectos!$D7),"") -> Portafolio. Fortalecimiento cadena de valor de aguacate. Convocatoria 42. SGR-Región Pacífico | G21: =IFERROR(IF(Portafolio_Proyectos!$AQ7="","",Portafolio_Proyectos!$A7),"") -> ACI:Productividad agrícola agroambientalmente eficiente e integralmente sostenible | H21: =IFERROR(IF(Portafolio_Proyectos!$AQ7="","",Portafolio_Proyectos!$E7),"") -> Alexander Rebolledo Roa
A22: =IFERROR(IF(Portafolio_Proyectos!$AR7="","","CAP-"&ROW()-1),"") | B22: =IFERROR(IF(Portafolio_Proyectos!$AR7="","",Portafolio_Proyectos!$AR7),"") | C22: =IFERROR(IF(Portafolio_Proyectos!$AR7="","","Distintiva"),"") | D22: =IFERROR(IF(Portafolio_Proyectos!$AR7="","",Portafolio_Proyectos!$C7),"") | E22: =IFERROR(IF(Portafolio_Proyectos!$AR7="","",Portafolio_Proyectos!$B7),"") | F22: =IFERROR(IF(Portafolio_Proyectos!$AR7="","",Portafolio_Proyectos!$D7),"") | G22: =IFERROR(IF(Portafolio_Proyectos!$AR7="","",Portafolio_Proyectos!$A7),"") | H22: =IFERROR(IF(Portafolio_Proyectos!$AR7="","",Portafolio_Proyectos!$E7),"")
A23: =IFERROR(IF(Portafolio_Proyectos!$AP8="","","CAP-"&ROW()-1),"") -> CAP-22 | B23: =IFERROR(IF(Portafolio_Proyectos!$AP8="","",Portafolio_Proyectos!$AP8),"") -> Modelación fenológica con acumulación térmica (GDD) en sistemas frutícolas altoandinos | C23: =IFERROR(IF(Portafolio_Proyectos!$AP8="","","Emergente"),"") -> Emergente | D23: =IFERROR(IF(Portafolio_Proyectos!$AP8="","",Portafolio_Proyectos!$C8),"") -> Fisiología vegetal y nutrición | E23: =IFERROR(IF(Portafolio_Proyectos!$AP8="","",Portafolio_Proyectos!$B8),"") -> Aguacate Hass | F23: =IFERROR(IF(Portafolio_Proyectos!$AP8="","",Portafolio_Proyectos!$D8),"") -> Convenio 2207. Desarrollo de modelo fenológico aguacate Hass Pijao – Quindío (Fase 1) | G23: =IFERROR(IF(Portafolio_Proyectos!$AP8="","",Portafolio_Proyectos!$A8),"") -> Bioeconomía: Prácticas de agricultura sostenible | H23: =IFERROR(IF(Portafolio_Proyectos!$AP8="","",Portafolio_Proyectos!$E8),"") -> Alexander Rebolledo Roa
A24: =IFERROR(IF(Portafolio_Proyectos!$AQ8="","","CAP-"&ROW()-1),"") -> CAP-23 | B24: =IFERROR(IF(Portafolio_Proyectos!$AQ8="","",Portafolio_Proyectos!$AQ8),"") -> Fertilización por sitio específico | C24: =IFERROR(IF(Portafolio_Proyectos!$AQ8="","","Consolidada"),"") -> Consolidada | D24: =IFERROR(IF(Portafolio_Proyectos!$AQ8="","",Portafolio_Proyectos!$C8),"") -> Fisiología vegetal y nutrición | E24: =IFERROR(IF(Portafolio_Proyectos!$AQ8="","",Portafolio_Proyectos!$B8),"") -> Aguacate Hass | F24: =IFERROR(IF(Portafolio_Proyectos!$AQ8="","",Portafolio_Proyectos!$D8),"") -> Convenio 2207. Desarrollo de modelo fenológico aguacate Hass Pijao – Quindío (Fase 1) | G24: =IFERROR(IF(Portafolio_Proyectos!$AQ8="","",Portafolio_Proyectos!$A8),"") -> Bioeconomía: Prácticas de agricultura sostenible | H24: =IFERROR(IF(Portafolio_Proyectos!$AQ8="","",Portafolio_Proyectos!$E8),"") -> Alexander Rebolledo Roa
A25: =IFERROR(IF(Portafolio_Proyectos!$AR8="","","CAP-"&ROW()-1),"") | B25: =IFERROR(IF(Portafolio_Proyectos!$AR8="","",Portafolio_Proyectos!$AR8),"") | C25: =IFERROR(IF(Portafolio_Proyectos!$AR8="","","Distintiva"),"") | D25: =IFERROR(IF(Portafolio_Proyectos!$AR8="","",Portafolio_Proyectos!$C8),"") | E25: =IFERROR(IF(Portafolio_Proyectos!$AR8="","",Portafolio_Proyectos!$B8),"") | F25: =IFERROR(IF(Portafolio_Proyectos!$AR8="","",Portafolio_Proyectos!$D8),"") | G25: =IFERROR(IF(Portafolio_Proyectos!$AR8="","",Portafolio_Proyectos!$A8),"") | H25: =IFERROR(IF(Portafolio_Proyectos!$AR8="","",Portafolio_Proyectos!$E8),"")
A26: =IFERROR(IF(Portafolio_Proyectos!$AP9="","","CAP-"&ROW()-1),"") | B26: =IFERROR(IF(Portafolio_Proyectos!$AP9="","",Portafolio_Proyectos!$AP9),"") | C26: =IFERROR(IF(Portafolio_Proyectos!$AP9="","","Emergente"),"") | D26: =IFERROR(IF(Portafolio_Proyectos!$AP9="","",Portafolio_Proyectos!$C9),"") | E26: =IFERROR(IF(Portafolio_Proyectos!$AP9="","",Portafolio_Proyectos!$B9),"") | F26: =IFERROR(IF(Portafolio_Proyectos!$AP9="","",Portafolio_Proyectos!$D9),"") | G26: =IFERROR(IF(Portafolio_Proyectos!$AP9="","",Portafolio_Proyectos!$A9),"") | H26: =IFERROR(IF(Portafolio_Proyectos!$AP9="","",Portafolio_Proyectos!$E9),"")
A27: =IFERROR(IF(Portafolio_Proyectos!$AQ9="","","CAP-"&ROW()-1),"") | B27: =IFERROR(IF(Portafolio_Proyectos!$AQ9="","",Portafolio_Proyectos!$AQ9),"") | C27: =IFERROR(IF(Portafolio_Proyectos!$AQ9="","","Consolidada"),"") | D27: =IFERROR(IF(Portafolio_Proyectos!$AQ9="","",Portafolio_Proyectos!$C9),"") | E27: =IFERROR(IF(Portafolio_Proyectos!$AQ9="","",Portafolio_Proyectos!$B9),"") | F27: =IFERROR(IF(Portafolio_Proyectos!$AQ9="","",Portafolio_Proyectos!$D9),"") | G27: =IFERROR(IF(Portafolio_Proyectos!$AQ9="","",Portafolio_Proyectos!$A9),"") | H27: =IFERROR(IF(Portafolio_Proyectos!$AQ9="","",Portafolio_Proyectos!$E9),"")
A28: =IFERROR(IF(Portafolio_Proyectos!$AR9="","","CAP-"&ROW()-1),"") | B28: =IFERROR(IF(Portafolio_Proyectos!$AR9="","",Portafolio_Proyectos!$AR9),"") | C28: =IFERROR(IF(Portafolio_Proyectos!$AR9="","","Distintiva"),"") | D28: =IFERROR(IF(Portafolio_Proyectos!$AR9="","",Portafolio_Proyectos!$C9),"") | E28: =IFERROR(IF(Portafolio_Proyectos!$AR9="","",Portafolio_Proyectos!$B9),"") | F28: =IFERROR(IF(Portafolio_Proyectos!$AR9="","",Portafolio_Proyectos!$D9),"") | G28: =IFERROR(IF(Portafolio_Proyectos!$AR9="","",Portafolio_Proyectos!$A9),"") | H28: =IFERROR(IF(Portafolio_Proyectos!$AR9="","",Portafolio_Proyectos!$E9),"")
A29: =IFERROR(IF(Portafolio_Proyectos!$AP10="","","CAP-"&ROW()-1),"") | B29: =IFERROR(IF(Portafolio_Proyectos!$AP10="","",Portafolio_Proyectos!$AP10),"") | C29: =IFERROR(IF(Portafolio_Proyectos!$AP10="","","Emergente"),"") | D29: =IFERROR(IF(Portafolio_Proyectos!$AP10="","",Portafolio_Proyectos!$C10),"") | E29: =IFERROR(IF(Portafolio_Proyectos!$AP10="","",Portafolio_Proyectos!$B10),"") | F29: =IFERROR(IF(Portafolio_Proyectos!$AP10="","",Portafolio_Proyectos!$D10),"") | G29: =IFERROR(IF(Portafolio_Proyectos!$AP10="","",Portafolio_Proyectos!$A10),"") | H29: =IFERROR(IF(Portafolio_Proyectos!$AP10="","",Portafolio_Proyectos!$E10),"")
A30: =IFERROR(IF(Portafolio_Proyectos!$AQ10="","","CAP-"&ROW()-1),"") | B30: =IFERROR(IF(Portafolio_Proyectos!$AQ10="","",Portafolio_Proyectos!$AQ10),"") | C30: =IFERROR(IF(Portafolio_Proyectos!$AQ10="","","Consolidada"),"") | D30: =IFERROR(IF(Portafolio_Proyectos!$AQ10="","",Portafolio_Proyectos!$C10),"") | E30: =IFERROR(IF(Portafolio_Proyectos!$AQ10="","",Portafolio_Proyectos!$B10),"") | F30: =IFERROR(IF(Portafolio_Proyectos!$AQ10="","",Portafolio_Proyectos!$D10),"") | G30: =IFERROR(IF(Portafolio_Proyectos!$AQ10="","",Portafolio_Proyectos!$A10),"") | H30: =IFERROR(IF(Portafolio_Proyectos!$AQ10="","",Portafolio_Proyectos!$E10),"")
A31: =IFERROR(IF(Portafolio_Proyectos!$AR10="","","CAP-"&ROW()-1),"") | B31: =IFERROR(IF(Portafolio_Proyectos!$AR10="","",Portafolio_Proyectos!$AR10),"") | C31: =IFERROR(IF(Portafolio_Proyectos!$AR10="","","Distintiva"),"") | D31: =IFERROR(IF(Portafolio_Proyectos!$AR10="","",Portafolio_Proyectos!$C10),"") | E31: =IFERROR(IF(Portafolio_Proyectos!$AR10="","",Portafolio_Proyectos!$B10),"") | F31: =IFERROR(IF(Portafolio_Proyectos!$AR10="","",Portafolio_Proyectos!$D10),"") | G31: =IFERROR(IF(Portafolio_Proyectos!$AR10="","",Portafolio_Proyectos!$A10),"") | H31: =IFERROR(IF(Portafolio_Proyectos!$AR10="","",Portafolio_Proyectos!$E10),"")
A32: =IFERROR(IF(Portafolio_Proyectos!$AP11="","","CAP-"&ROW()-1),"") | B32: =IFERROR(IF(Portafolio_Proyectos!$AP11="","",Portafolio_Proyectos!$AP11),"") | C32: =IFERROR(IF(Portafolio_Proyectos!$AP11="","","Emergente"),"") | D32: =IFERROR(IF(Portafolio_Proyectos!$AP11="","",Portafolio_Proyectos!$C11),"") | E32: =IFERROR(IF(Portafolio_Proyectos!$AP11="","",Portafolio_Proyectos!$B11),"") | F32: =IFERROR(IF(Portafolio_Proyectos!$AP11="","",Portafolio_Proyectos!$D11),"") | G32: =IFERROR(IF(Portafolio_Proyectos!$AP11="","",Portafolio_Proyectos!$A11),"") | H32: =IFERROR(IF(Portafolio_Proyectos!$AP11="","",Portafolio_Proyectos!$E11),"")
A33: =IFERROR(IF(Portafolio_Proyectos!$AQ11="","","CAP-"&ROW()-1),"") | B33: =IFERROR(IF(Portafolio_Proyectos!$AQ11="","",Portafolio_Proyectos!$AQ11),"") | C33: =IFERROR(IF(Portafolio_Proyectos!$AQ11="","","Consolidada"),"") | D33: =IFERROR(IF(Portafolio_Proyectos!$AQ11="","",Portafolio_Proyectos!$C11),"") | E33: =IFERROR(IF(Portafolio_Proyectos!$AQ11="","",Portafolio_Proyectos!$B11),"") | F33: =IFERROR(IF(Portafolio_Proyectos!$AQ11="","",Portafolio_Proyectos!$D11),"") | G33: =IFERROR(IF(Portafolio_Proyectos!$AQ11="","",Portafolio_Proyectos!$A11),"") | H33: =IFERROR(IF(Portafolio_Proyectos!$AQ11="","",Portafolio_Proyectos!$E11),"")
A34: =IFERROR(IF(Portafolio_Proyectos!$AR11="","","CAP-"&ROW()-1),"") | B34: =IFERROR(IF(Portafolio_Proyectos!$AR11="","",Portafolio_Proyectos!$AR11),"") | C34: =IFERROR(IF(Portafolio_Proyectos!$AR11="","","Distintiva"),"") | D34: =IFERROR(IF(Portafolio_Proyectos!$AR11="","",Portafolio_Proyectos!$C11),"") | E34: =IFERROR(IF(Portafolio_Proyectos!$AR11="","",Portafolio_Proyectos!$B11),"") | F34: =IFERROR(IF(Portafolio_Proyectos!$AR11="","",Portafolio_Proyectos!$D11),"") | G34: =IFERROR(IF(Portafolio_Proyectos!$AR11="","",Portafolio_Proyectos!$A11),"") | H34: =IFERROR(IF(Portafolio_Proyectos!$AR11="","",Portafolio_Proyectos!$E11),"")
A35: =IFERROR(IF(Portafolio_Proyectos!$AP12="","","CAP-"&ROW()-1),"") | B35: =IFERROR(IF(Portafolio_Proyectos!$AP12="","",Portafolio_Proyectos!$AP12),"") | C35: =IFERROR(IF(Portafolio_Proyectos!$AP12="","","Emergente"),"") | D35: =IFERROR(IF(Portafolio_Proyectos!$AP12="","",Portafolio_Proyectos!$C12),"") | E35: =IFERROR(IF(Portafolio_Proyectos!$AP12="","",Portafolio_Proyectos!$B12),"") | F35: =IFERROR(IF(Portafolio_Proyectos!$AP12="","",Portafolio_Proyectos!$D12),"") | G35: =IFERROR(IF(Portafolio_Proyectos!$AP12="","",Portafolio_Proyectos!$A12),"") | H35: =IFERROR(IF(Portafolio_Proyectos!$AP12="","",Portafolio_Proyectos!$E12),"")
A36: =IFERROR(IF(Portafolio_Proyectos!$AQ12="","","CAP-"&ROW()-1),"") | B36: =IFERROR(IF(Portafolio_Proyectos!$AQ12="","",Portafolio_Proyectos!$AQ12),"") | C36: =IFERROR(IF(Portafolio_Proyectos!$AQ12="","","Consolidada"),"") | D36: =IFERROR(IF(Portafolio_Proyectos!$AQ12="","",Portafolio_Proyectos!$C12),"") | E36: =IFERROR(IF(Portafolio_Proyectos!$AQ12="","",Portafolio_Proyectos!$B12),"") | F36: =IFERROR(IF(Portafolio_Proyectos!$AQ12="","",Portafolio_Proyectos!$D12),"") | G36: =IFERROR(IF(Portafolio_Proyectos!$AQ12="","",Portafolio_Proyectos!$A12),"") | H36: =IFERROR(IF(Portafolio_Proyectos!$AQ12="","",Portafolio_Proyectos!$E12),"")
A37: =IFERROR(IF(Portafolio_Proyectos!$AR12="","","CAP-"&ROW()-1),"") | B37: =IFERROR(IF(Portafolio_Proyectos!$AR12="","",Portafolio_Proyectos!$AR12),"") | C37: =IFERROR(IF(Portafolio_Proyectos!$AR12="","","Distintiva"),"") | D37: =IFERROR(IF(Portafolio_Proyectos!$AR12="","",Portafolio_Proyectos!$C12),"") | E37: =IFERROR(IF(Portafolio_Proyectos!$AR12="","",Portafolio_Proyectos!$B12),"") | F37: =IFERROR(IF(Portafolio_Proyectos!$AR12="","",Portafolio_Proyectos!$D12),"") | G37: =IFERROR(IF(Portafolio_Proyectos!$AR12="","",Portafolio_Proyectos!$A12),"") | H37: =IFERROR(IF(Portafolio_Proyectos!$AR12="","",Portafolio_Proyectos!$E12),"")
A38: =IFERROR(IF(Portafolio_Proyectos!$AP13="","","CAP-"&ROW()-1),"") | B38: =IFERROR(IF(Portafolio_Proyectos!$AP13="","",Portafolio_Proyectos!$AP13),"") | C38: =IFERROR(IF(Portafolio_Proyectos!$AP13="","","Emergente"),"") | D38: =IFERROR(IF(Portafolio_Proyectos!$AP13="","",Portafolio_Proyectos!$C13),"") | E38: =IFERROR(IF(Portafolio_Proyectos!$AP13="","",Portafolio_Proyectos!$B13),"") | F38: =IFERROR(IF(Portafolio_Proyectos!$AP13="","",Portafolio_Proyectos!$D13),"") | G38: =IFERROR(IF(Portafolio_Proyectos!$AP13="","",Portafolio_Proyectos!$A13),"") | H38: =IFERROR(IF(Portafolio_Proyectos!$AP13="","",Portafolio_Proyectos!$E13),"")
A39: =IFERROR(IF(Portafolio_Proyectos!$AQ13="","","CAP-"&ROW()-1),"") | B39: =IFERROR(IF(Portafolio_Proyectos!$AQ13="","",Portafolio_Proyectos!$AQ13),"") | C39: =IFERROR(IF(Portafolio_Proyectos!$AQ13="","","Consolidada"),"") | D39: =IFERROR(IF(Portafolio_Proyectos!$AQ13="","",Portafolio_Proyectos!$C13),"") | E39: =IFERROR(IF(Portafolio_Proyectos!$AQ13="","",Portafolio_Proyectos!$B13),"") | F39: =IFERROR(IF(Portafolio_Proyectos!$AQ13="","",Portafolio_Proyectos!$D13),"") | G39: =IFERROR(IF(Portafolio_Proyectos!$AQ13="","",Portafolio_Proyectos!$A13),"") | H39: =IFERROR(IF(Portafolio_Proyectos!$AQ13="","",Portafolio_Proyectos!$E13),"")
A40: =IFERROR(IF(Portafolio_Proyectos!$AR13="","","CAP-"&ROW()-1),"") | B40: =IFERROR(IF(Portafolio_Proyectos!$AR13="","",Portafolio_Proyectos!$AR13),"") | C40: =IFERROR(IF(Portafolio_Proyectos!$AR13="","","Distintiva"),"") | D40: =IFERROR(IF(Portafolio_Proyectos!$AR13="","",Portafolio_Proyectos!$C13),"") | E40: =IFERROR(IF(Portafolio_Proyectos!$AR13="","",Portafolio_Proyectos!$B13),"") | F40: =IFERROR(IF(Portafolio_Proyectos!$AR13="","",Portafolio_Proyectos!$D13),"") | G40: =IFERROR(IF(Portafolio_Proyectos!$AR13="","",Portafolio_Proyectos!$A13),"") | H40: =IFERROR(IF(Portafolio_Proyectos!$AR13="","",Portafolio_Proyectos!$E13),"")
A41: =IFERROR(IF(Portafolio_Proyectos!$AP14="","","CAP-"&ROW()-1),"") | B41: =IFERROR(IF(Portafolio_Proyectos!$AP14="","",Portafolio_Proyectos!$AP14),"") | C41: =IFERROR(IF(Portafolio_Proyectos!$AP14="","","Emergente"),"") | D41: =IFERROR(IF(Portafolio_Proyectos!$AP14="","",Portafolio_Proyectos!$C14),"") | E41: =IFERROR(IF(Portafolio_Proyectos!$AP14="","",Portafolio_Proyectos!$B14),"") | F41: =IFERROR(IF(Portafolio_Proyectos!$AP14="","",Portafolio_Proyectos!$D14),"") | G41: =IFERROR(IF(Portafolio_Proyectos!$AP14="","",Portafolio_Proyectos!$A14),"") | H41: =IFERROR(IF(Portafolio_Proyectos!$AP14="","",Portafolio_Proyectos!$E14),"")
A42: =IFERROR(IF(Portafolio_Proyectos!$AQ14="","","CAP-"&ROW()-1),"") | B42: =IFERROR(IF(Portafolio_Proyectos!$AQ14="","",Portafolio_Proyectos!$AQ14),"") | C42: =IFERROR(IF(Portafolio_Proyectos!$AQ14="","","Consolidada"),"") | D42: =IFERROR(IF(Portafolio_Proyectos!$AQ14="","",Portafolio_Proyectos!$C14),"") | E42: =IFERROR(IF(Portafolio_Proyectos!$AQ14="","",Portafolio_Proyectos!$B14),"") | F42: =IFERROR(IF(Portafolio_Proyectos!$AQ14="","",Portafolio_Proyectos!$D14),"") | G42: =IFERROR(IF(Portafolio_Proyectos!$AQ14="","",Portafolio_Proyectos!$A14),"") | H42: =IFERROR(IF(Portafolio_Proyectos!$AQ14="","",Portafolio_Proyectos!$E14),"")
A43: =IFERROR(IF(Portafolio_Proyectos!$AR14="","","CAP-"&ROW()-1),"") | B43: =IFERROR(IF(Portafolio_Proyectos!$AR14="","",Portafolio_Proyectos!$AR14),"") | C43: =IFERROR(IF(Portafolio_Proyectos!$AR14="","","Distintiva"),"") | D43: =IFERROR(IF(Portafolio_Proyectos!$AR14="","",Portafolio_Proyectos!$C14),"") | E43: =IFERROR(IF(Portafolio_Proyectos!$AR14="","",Portafolio_Proyectos!$B14),"") | F43: =IFERROR(IF(Portafolio_Proyectos!$AR14="","",Portafolio_Proyectos!$D14),"") | G43: =IFERROR(IF(Portafolio_Proyectos!$AR14="","",Portafolio_Proyectos!$A14),"") | H43: =IFERROR(IF(Portafolio_Proyectos!$AR14="","",Portafolio_Proyectos!$E14),"")
A44: =IFERROR(IF(Portafolio_Proyectos!$AP15="","","CAP-"&ROW()-1),"") | B44: =IFERROR(IF(Portafolio_Proyectos!$AP15="","",Portafolio_Proyectos!$AP15),"") | C44: =IFERROR(IF(Portafolio_Proyectos!$AP15="","","Emergente"),"") | D44: =IFERROR(IF(Portafolio_Proyectos!$AP15="","",Portafolio_Proyectos!$C15),"") | E44: =IFERROR(IF(Portafolio_Proyectos!$AP15="","",Portafolio_Proyectos!$B15),"") | F44: =IFERROR(IF(Portafolio_Proyectos!$AP15="","",Portafolio_Proyectos!$D15),"") | G44: =IFERROR(IF(Portafolio_Proyectos!$AP15="","",Portafolio_Proyectos!$A15),"") | H44: =IFERROR(IF(Portafolio_Proyectos!$AP15="","",Portafolio_Proyectos!$E15),"")
A45: =IFERROR(IF(Portafolio_Proyectos!$AQ15="","","CAP-"&ROW()-1),"") | B45: =IFERROR(IF(Portafolio_Proyectos!$AQ15="","",Portafolio_Proyectos!$AQ15),"") | C45: =IFERROR(IF(Portafolio_Proyectos!$AQ15="","","Consolidada"),"") | D45: =IFERROR(IF(Portafolio_Proyectos!$AQ15="","",Portafolio_Proyectos!$C15),"") | E45: =IFERROR(IF(Portafolio_Proyectos!$AQ15="","",Portafolio_Proyectos!$B15),"") | F45: =IFERROR(IF(Portafolio_Proyectos!$AQ15="","",Portafolio_Proyectos!$D15),"") | G45: =IFERROR(IF(Portafolio_Proyectos!$AQ15="","",Portafolio_Proyectos!$A15),"") | H45: =IFERROR(IF(Portafolio_Proyectos!$AQ15="","",Portafolio_Proyectos!$E15),"")
A46: =IFERROR(IF(Portafolio_Proyectos!$AR15="","","CAP-"&ROW()-1),"") | B46: =IFERROR(IF(Portafolio_Proyectos!$AR15="","",Portafolio_Proyectos!$AR15),"") | C46: =IFERROR(IF(Portafolio_Proyectos!$AR15="","","Distintiva"),"") | D46: =IFERROR(IF(Portafolio_Proyectos!$AR15="","",Portafolio_Proyectos!$C15),"") | E46: =IFERROR(IF(Portafolio_Proyectos!$AR15="","",Portafolio_Proyectos!$B15),"") | F46: =IFERROR(IF(Portafolio_Proyectos!$AR15="","",Portafolio_Proyectos!$D15),"") | G46: =IFERROR(IF(Portafolio_Proyectos!$AR15="","",Portafolio_Proyectos!$A15),"") | H46: =IFERROR(IF(Portafolio_Proyectos!$AR15="","",Portafolio_Proyectos!$E15),"")
A47: =IFERROR(IF(Portafolio_Proyectos!$AP16="","","CAP-"&ROW()-1),"") | B47: =IFERROR(IF(Portafolio_Proyectos!$AP16="","",Portafolio_Proyectos!$AP16),"") | C47: =IFERROR(IF(Portafolio_Proyectos!$AP16="","","Emergente"),"") | D47: =IFERROR(IF(Portafolio_Proyectos!$AP16="","",Portafolio_Proyectos!$C16),"") | E47: =IFERROR(IF(Portafolio_Proyectos!$AP16="","",Portafolio_Proyectos!$B16),"") | F47: =IFERROR(IF(Portafolio_Proyectos!$AP16="","",Portafolio_Proyectos!$D16),"") | G47: =IFERROR(IF(Portafolio_Proyectos!$AP16="","",Portafolio_Proyectos!$A16),"") | H47: =IFERROR(IF(Portafolio_Proyectos!$AP16="","",Portafolio_Proyectos!$E16),"")
A48: =IFERROR(IF(Portafolio_Proyectos!$AQ16="","","CAP-"&ROW()-1),"") | B48: =IFERROR(IF(Portafolio_Proyectos!$AQ16="","",Portafolio_Proyectos!$AQ16),"") | C48: =IFERROR(IF(Portafolio_Proyectos!$AQ16="","","Consolidada"),"") | D48: =IFERROR(IF(Portafolio_Proyectos!$AQ16="","",Portafolio_Proyectos!$C16),"") | E48: =IFERROR(IF(Portafolio_Proyectos!$AQ16="","",Portafolio_Proyectos!$B16),"") | F48: =IFERROR(IF(Portafolio_Proyectos!$AQ16="","",Portafolio_Proyectos!$D16),"") | G48: =IFERROR(IF(Portafolio_Proyectos!$AQ16="","",Portafolio_Proyectos!$A16),"") | H48: =IFERROR(IF(Portafolio_Proyectos!$AQ16="","",Portafolio_Proyectos!$E16),"")
A49: =IFERROR(IF(Portafolio_Proyectos!$AR16="","","CAP-"&ROW()-1),"") | B49: =IFERROR(IF(Portafolio_Proyectos!$AR16="","",Portafolio_Proyectos!$AR16),"") | C49: =IFERROR(IF(Portafolio_Proyectos!$AR16="","","Distintiva"),"") | D49: =IFERROR(IF(Portafolio_Proyectos!$AR16="","",Portafolio_Proyectos!$C16),"") | E49: =IFERROR(IF(Portafolio_Proyectos!$AR16="","",Portafolio_Proyectos!$B16),"") | F49: =IFERROR(IF(Portafolio_Proyectos!$AR16="","",Portafolio_Proyectos!$D16),"") | G49: =IFERROR(IF(Portafolio_Proyectos!$AR16="","",Portafolio_Proyectos!$A16),"") | H49: =IFERROR(IF(Portafolio_Proyectos!$AR16="","",Portafolio_Proyectos!$E16),"")
A50: =IFERROR(IF(Portafolio_Proyectos!$AP17="","","CAP-"&ROW()-1),"") | B50: =IFERROR(IF(Portafolio_Proyectos!$AP17="","",Portafolio_Proyectos!$AP17),"") | C50: =IFERROR(IF(Portafolio_Proyectos!$AP17="","","Emergente"),"") | D50: =IFERROR(IF(Portafolio_Proyectos!$AP17="","",Portafolio_Proyectos!$C17),"") | E50: =IFERROR(IF(Portafolio_Proyectos!$AP17="","",Portafolio_Proyectos!$B17),"") | F50: =IFERROR(IF(Portafolio_Proyectos!$AP17="","",Portafolio_Proyectos!$D17),"") | G50: =IFERROR(IF(Portafolio_Proyectos!$AP17="","",Portafolio_Proyectos!$A17),"") | H50: =IFERROR(IF(Portafolio_Proyectos!$AP17="","",Portafolio_Proyectos!$E17),"")
A51: =IFERROR(IF(Portafolio_Proyectos!$AQ17="","","CAP-"&ROW()-1),"") | B51: =IFERROR(IF(Portafolio_Proyectos!$AQ17="","",Portafolio_Proyectos!$AQ17),"") | C51: =IFERROR(IF(Portafolio_Proyectos!$AQ17="","","Consolidada"),"") | D51: =IFERROR(IF(Portafolio_Proyectos!$AQ17="","",Portafolio_Proyectos!$C17),"") | E51: =IFERROR(IF(Portafolio_Proyectos!$AQ17="","",Portafolio_Proyectos!$B17),"") | F51: =IFERROR(IF(Portafolio_Proyectos!$AQ17="","",Portafolio_Proyectos!$D17),"") | G51: =IFERROR(IF(Portafolio_Proyectos!$AQ17="","",Portafolio_Proyectos!$A17),"") | H51: =IFERROR(IF(Portafolio_Proyectos!$AQ17="","",Portafolio_Proyectos!$E17),"")
A52: =IFERROR(IF(Portafolio_Proyectos!$AR17="","","CAP-"&ROW()-1),"") | B52: =IFERROR(IF(Portafolio_Proyectos!$AR17="","",Portafolio_Proyectos!$AR17),"") | C52: =IFERROR(IF(Portafolio_Proyectos!$AR17="","","Distintiva"),"") | D52: =IFERROR(IF(Portafolio_Proyectos!$AR17="","",Portafolio_Proyectos!$C17),"") | E52: =IFERROR(IF(Portafolio_Proyectos!$AR17="","",Portafolio_Proyectos!$B17),"") | F52: =IFERROR(IF(Portafolio_Proyectos!$AR17="","",Portafolio_Proyectos!$D17),"") | G52: =IFERROR(IF(Portafolio_Proyectos!$AR17="","",Portafolio_Proyectos!$A17),"") | H52: =IFERROR(IF(Portafolio_Proyectos!$AR17="","",Portafolio_Proyectos!$E17),"")
A53: =IFERROR(IF(Portafolio_Proyectos!$AP18="","","CAP-"&ROW()-1),"") | B53: =IFERROR(IF(Portafolio_Proyectos!$AP18="","",Portafolio_Proyectos!$AP18),"") | C53: =IFERROR(IF(Portafolio_Proyectos!$AP18="","","Emergente"),"") | D53: =IFERROR(IF(Portafolio_Proyectos!$AP18="","",Portafolio_Proyectos!$C18),"") | E53: =IFERROR(IF(Portafolio_Proyectos!$AP18="","",Portafolio_Proyectos!$B18),"") | F53: =IFERROR(IF(Portafolio_Proyectos!$AP18="","",Portafolio_Proyectos!$D18),"") | G53: =IFERROR(IF(Portafolio_Proyectos!$AP18="","",Portafolio_Proyectos!$A18),"") | H53: =IFERROR(IF(Portafolio_Proyectos!$AP18="","",Portafolio_Proyectos!$E18),"")
A54: =IFERROR(IF(Portafolio_Proyectos!$AQ18="","","CAP-"&ROW()-1),"") | B54: =IFERROR(IF(Portafolio_Proyectos!$AQ18="","",Portafolio_Proyectos!$AQ18),"") | C54: =IFERROR(IF(Portafolio_Proyectos!$AQ18="","","Consolidada"),"") | D54: =IFERROR(IF(Portafolio_Proyectos!$AQ18="","",Portafolio_Proyectos!$C18),"") | E54: =IFERROR(IF(Portafolio_Proyectos!$AQ18="","",Portafolio_Proyectos!$B18),"") | F54: =IFERROR(IF(Portafolio_Proyectos!$AQ18="","",Portafolio_Proyectos!$D18),"") | G54: =IFERROR(IF(Portafolio_Proyectos!$AQ18="","",Portafolio_Proyectos!$A18),"") | H54: =IFERROR(IF(Portafolio_Proyectos!$AQ18="","",Portafolio_Proyectos!$E18),"")
A55: =IFERROR(IF(Portafolio_Proyectos!$AR18="","","CAP-"&ROW()-1),"") | B55: =IFERROR(IF(Portafolio_Proyectos!$AR18="","",Portafolio_Proyectos!$AR18),"") | C55: =IFERROR(IF(Portafolio_Proyectos!$AR18="","","Distintiva"),"") | D55: =IFERROR(IF(Portafolio_Proyectos!$AR18="","",Portafolio_Proyectos!$C18),"") | E55: =IFERROR(IF(Portafolio_Proyectos!$AR18="","",Portafolio_Proyectos!$B18),"") | F55: =IFERROR(IF(Portafolio_Proyectos!$AR18="","",Portafolio_Proyectos!$D18),"") | G55: =IFERROR(IF(Portafolio_Proyectos!$AR18="","",Portafolio_Proyectos!$A18),"") | H55: =IFERROR(IF(Portafolio_Proyectos!$AR18="","",Portafolio_Proyectos!$E18),"")
A56: =IFERROR(IF(Portafolio_Proyectos!$AP19="","","CAP-"&ROW()-1),"") | B56: =IFERROR(IF(Portafolio_Proyectos!$AP19="","",Portafolio_Proyectos!$AP19),"") | C56: =IFERROR(IF(Portafolio_Proyectos!$AP19="","","Emergente"),"") | D56: =IFERROR(IF(Portafolio_Proyectos!$AP19="","",Portafolio_Proyectos!$C19),"") | E56: =IFERROR(IF(Portafolio_Proyectos!$AP19="","",Portafolio_Proyectos!$B19),"") | F56: =IFERROR(IF(Portafolio_Proyectos!$AP19="","",Portafolio_Proyectos!$D19),"") | G56: =IFERROR(IF(Portafolio_Proyectos!$AP19="","",Portafolio_Proyectos!$A19),"") | H56: =IFERROR(IF(Portafolio_Proyectos!$AP19="","",Portafolio_Proyectos!$E19),"")
A57: =IFERROR(IF(Portafolio_Proyectos!$AQ19="","","CAP-"&ROW()-1),"") | B57: =IFERROR(IF(Portafolio_Proyectos!$AQ19="","",Portafolio_Proyectos!$AQ19),"") | C57: =IFERROR(IF(Portafolio_Proyectos!$AQ19="","","Consolidada"),"") | D57: =IFERROR(IF(Portafolio_Proyectos!$AQ19="","",Portafolio_Proyectos!$C19),"") | E57: =IFERROR(IF(Portafolio_Proyectos!$AQ19="","",Portafolio_Proyectos!$B19),"") | F57: =IFERROR(IF(Portafolio_Proyectos!$AQ19="","",Portafolio_Proyectos!$D19),"") | G57: =IFERROR(IF(Portafolio_Proyectos!$AQ19="","",Portafolio_Proyectos!$A19),"") | H57: =IFERROR(IF(Portafolio_Proyectos!$AQ19="","",Portafolio_Proyectos!$E19),"")
A58: =IFERROR(IF(Portafolio_Proyectos!$AR19="","","CAP-"&ROW()-1),"") | B58: =IFERROR(IF(Portafolio_Proyectos!$AR19="","",Portafolio_Proyectos!$AR19),"") | C58: =IFERROR(IF(Portafolio_Proyectos!$AR19="","","Distintiva"),"") | D58: =IFERROR(IF(Portafolio_Proyectos!$AR19="","",Portafolio_Proyectos!$C19),"") | E58: =IFERROR(IF(Portafolio_Proyectos!$AR19="","",Portafolio_Proyectos!$B19),"") | F58: =IFERROR(IF(Portafolio_Proyectos!$AR19="","",Portafolio_Proyectos!$D19),"") | G58: =IFERROR(IF(Portafolio_Proyectos!$AR19="","",Portafolio_Proyectos!$A19),"") | H58: =IFERROR(IF(Portafolio_Proyectos!$AR19="","",Portafolio_Proyectos!$E19),"")
A59: =IFERROR(IF(Portafolio_Proyectos!$AP20="","","CAP-"&ROW()-1),"") | B59: =IFERROR(IF(Portafolio_Proyectos!$AP20="","",Portafolio_Proyectos!$AP20),"") | C59: =IFERROR(IF(Portafolio_Proyectos!$AP20="","","Emergente"),"") | D59: =IFERROR(IF(Portafolio_Proyectos!$AP20="","",Portafolio_Proyectos!$C20),"") | E59: =IFERROR(IF(Portafolio_Proyectos!$AP20="","",Portafolio_Proyectos!$B20),"") | F59: =IFERROR(IF(Portafolio_Proyectos!$AP20="","",Portafolio_Proyectos!$D20),"") | G59: =IFERROR(IF(Portafolio_Proyectos!$AP20="","",Portafolio_Proyectos!$A20),"") | H59: =IFERROR(IF(Portafolio_Proyectos!$AP20="","",Portafolio_Proyectos!$E20),"")
A60: =IFERROR(IF(Portafolio_Proyectos!$AQ20="","","CAP-"&ROW()-1),"") | B60: =IFERROR(IF(Portafolio_Proyectos!$AQ20="","",Portafolio_Proyectos!$AQ20),"") | C60: =IFERROR(IF(Portafolio_Proyectos!$AQ20="","","Consolidada"),"") | D60: =IFERROR(IF(Portafolio_Proyectos!$AQ20="","",Portafolio_Proyectos!$C20),"") | E60: =IFERROR(IF(Portafolio_Proyectos!$AQ20="","",Portafolio_Proyectos!$B20),"") | F60: =IFERROR(IF(Portafolio_Proyectos!$AQ20="","",Portafolio_Proyectos!$D20),"") | G60: =IFERROR(IF(Portafolio_Proyectos!$AQ20="","",Portafolio_Proyectos!$A20),"") | H60: =IFERROR(IF(Portafolio_Proyectos!$AQ20="","",Portafolio_Proyectos!$E20),"")
A61: =IFERROR(IF(Portafolio_Proyectos!$AR20="","","CAP-"&ROW()-1),"") | B61: =IFERROR(IF(Portafolio_Proyectos!$AR20="","",Portafolio_Proyectos!$AR20),"") | C61: =IFERROR(IF(Portafolio_Proyectos!$AR20="","","Distintiva"),"") | D61: =IFERROR(IF(Portafolio_Proyectos!$AR20="","",Portafolio_Proyectos!$C20),"") | E61: =IFERROR(IF(Portafolio_Proyectos!$AR20="","",Portafolio_Proyectos!$B20),"") | F61: =IFERROR(IF(Portafolio_Proyectos!$AR20="","",Portafolio_Proyectos!$D20),"") | G61: =IFERROR(IF(Portafolio_Proyectos!$AR20="","",Portafolio_Proyectos!$A20),"") | H61: =IFERROR(IF(Portafolio_Proyectos!$AR20="","",Portafolio_Proyectos!$E20),"")
A62: =IFERROR(IF(Portafolio_Proyectos!$AP21="","","CAP-"&ROW()-1),"") | B62: =IFERROR(IF(Portafolio_Proyectos!$AP21="","",Portafolio_Proyectos!$AP21),"") | C62: =IFERROR(IF(Portafolio_Proyectos!$AP21="","","Emergente"),"") | D62: =IFERROR(IF(Portafolio_Proyectos!$AP21="","",Portafolio_Proyectos!$C21),"") | E62: =IFERROR(IF(Portafolio_Proyectos!$AP21="","",Portafolio_Proyectos!$B21),"") | F62: =IFERROR(IF(Portafolio_Proyectos!$AP21="","",Portafolio_Proyectos!$D21),"") | G62: =IFERROR(IF(Portafolio_Proyectos!$AP21="","",Portafolio_Proyectos!$A21),"") | H62: =IFERROR(IF(Portafolio_Proyectos!$AP21="","",Portafolio_Proyectos!$E21),"")
A63: =IFERROR(IF(Portafolio_Proyectos!$AQ21="","","CAP-"&ROW()-1),"") | B63: =IFERROR(IF(Portafolio_Proyectos!$AQ21="","",Portafolio_Proyectos!$AQ21),"") | C63: =IFERROR(IF(Portafolio_Proyectos!$AQ21="","","Consolidada"),"") | D63: =IFERROR(IF(Portafolio_Proyectos!$AQ21="","",Portafolio_Proyectos!$C21),"") | E63: =IFERROR(IF(Portafolio_Proyectos!$AQ21="","",Portafolio_Proyectos!$B21),"") | F63: =IFERROR(IF(Portafolio_Proyectos!$AQ21="","",Portafolio_Proyectos!$D21),"") | G63: =IFERROR(IF(Portafolio_Proyectos!$AQ21="","",Portafolio_Proyectos!$A21),"") | H63: =IFERROR(IF(Portafolio_Proyectos!$AQ21="","",Portafolio_Proyectos!$E21),"")
A64: =IFERROR(IF(Portafolio_Proyectos!$AR21="","","CAP-"&ROW()-1),"") | B64: =IFERROR(IF(Portafolio_Proyectos!$AR21="","",Portafolio_Proyectos!$AR21),"") | C64: =IFERROR(IF(Portafolio_Proyectos!$AR21="","","Distintiva"),"") | D64: =IFERROR(IF(Portafolio_Proyectos!$AR21="","",Portafolio_Proyectos!$C21),"") | E64: =IFERROR(IF(Portafolio_Proyectos!$AR21="","",Portafolio_Proyectos!$B21),"") | F64: =IFERROR(IF(Portafolio_Proyectos!$AR21="","",Portafolio_Proyectos!$D21),"") | G64: =IFERROR(IF(Portafolio_Proyectos!$AR21="","",Portafolio_Proyectos!$A21),"") | H64: =IFERROR(IF(Portafolio_Proyectos!$AR21="","",Portafolio_Proyectos!$E21),"")
A65: =IFERROR(IF(Portafolio_Proyectos!$AP22="","","CAP-"&ROW()-1),"") | B65: =IFERROR(IF(Portafolio_Proyectos!$AP22="","",Portafolio_Proyectos!$AP22),"") | C65: =IFERROR(IF(Portafolio_Proyectos!$AP22="","","Emergente"),"") | D65: =IFERROR(IF(Portafolio_Proyectos!$AP22="","",Portafolio_Proyectos!$C22),"") | E65: =IFERROR(IF(Portafolio_Proyectos!$AP22="","",Portafolio_Proyectos!$B22),"") | F65: =IFERROR(IF(Portafolio_Proyectos!$AP22="","",Portafolio_Proyectos!$D22),"") | G65: =IFERROR(IF(Portafolio_Proyectos!$AP22="","",Portafolio_Proyectos!$A22),"") | H65: =IFERROR(IF(Portafolio_Proyectos!$AP22="","",Portafolio_Proyectos!$E22),"")
A66: =IFERROR(IF(Portafolio_Proyectos!$AQ22="","","CAP-"&ROW()-1),"") | B66: =IFERROR(IF(Portafolio_Proyectos!$AQ22="","",Portafolio_Proyectos!$AQ22),"") | C66: =IFERROR(IF(Portafolio_Proyectos!$AQ22="","","Consolidada"),"") | D66: =IFERROR(IF(Portafolio_Proyectos!$AQ22="","",Portafolio_Proyectos!$C22),"") | E66: =IFERROR(IF(Portafolio_Proyectos!$AQ22="","",Portafolio_Proyectos!$B22),"") | F66: =IFERROR(IF(Portafolio_Proyectos!$AQ22="","",Portafolio_Proyectos!$D22),"") | G66: =IFERROR(IF(Portafolio_Proyectos!$AQ22="","",Portafolio_Proyectos!$A22),"") | H66: =IFERROR(IF(Portafolio_Proyectos!$AQ22="","",Portafolio_Proyectos!$E22),"")
A67: =IFERROR(IF(Portafolio_Proyectos!$AR22="","","CAP-"&ROW()-1),"") | B67: =IFERROR(IF(Portafolio_Proyectos!$AR22="","",Portafolio_Proyectos!$AR22),"") | C67: =IFERROR(IF(Portafolio_Proyectos!$AR22="","","Distintiva"),"") | D67: =IFERROR(IF(Portafolio_Proyectos!$AR22="","",Portafolio_Proyectos!$C22),"") | E67: =IFERROR(IF(Portafolio_Proyectos!$AR22="","",Portafolio_Proyectos!$B22),"") | F67: =IFERROR(IF(Portafolio_Proyectos!$AR22="","",Portafolio_Proyectos!$D22),"") | G67: =IFERROR(IF(Portafolio_Proyectos!$AR22="","",Portafolio_Proyectos!$A22),"") | H67: =IFERROR(IF(Portafolio_Proyectos!$AR22="","",Portafolio_Proyectos!$E22),"")
A68: =IFERROR(IF(Portafolio_Proyectos!$AP23="","","CAP-"&ROW()-1),"") | B68: =IFERROR(IF(Portafolio_Proyectos!$AP23="","",Portafolio_Proyectos!$AP23),"") | C68: =IFERROR(IF(Portafolio_Proyectos!$AP23="","","Emergente"),"") | D68: =IFERROR(IF(Portafolio_Proyectos!$AP23="","",Portafolio_Proyectos!$C23),"") | E68: =IFERROR(IF(Portafolio_Proyectos!$AP23="","",Portafolio_Proyectos!$B23),"") | F68: =IFERROR(IF(Portafolio_Proyectos!$AP23="","",Portafolio_Proyectos!$D23),"") | G68: =IFERROR(IF(Portafolio_Proyectos!$AP23="","",Portafolio_Proyectos!$A23),"") | H68: =IFERROR(IF(Portafolio_Proyectos!$AP23="","",Portafolio_Proyectos!$E23),"")
A69: =IFERROR(IF(Portafolio_Proyectos!$AQ23="","","CAP-"&ROW()-1),"") | B69: =IFERROR(IF(Portafolio_Proyectos!$AQ23="","",Portafolio_Proyectos!$AQ23),"") | C69: =IFERROR(IF(Portafolio_Proyectos!$AQ23="","","Consolidada"),"") | D69: =IFERROR(IF(Portafolio_Proyectos!$AQ23="","",Portafolio_Proyectos!$C23),"") | E69: =IFERROR(IF(Portafolio_Proyectos!$AQ23="","",Portafolio_Proyectos!$B23),"") | F69: =IFERROR(IF(Portafolio_Proyectos!$AQ23="","",Portafolio_Proyectos!$D23),"") | G69: =IFERROR(IF(Portafolio_Proyectos!$AQ23="","",Portafolio_Proyectos!$A23),"") | H69: =IFERROR(IF(Portafolio_Proyectos!$AQ23="","",Portafolio_Proyectos!$E23),"")
A70: =IFERROR(IF(Portafolio_Proyectos!$AR23="","","CAP-"&ROW()-1),"") | B70: =IFERROR(IF(Portafolio_Proyectos!$AR23="","",Portafolio_Proyectos!$AR23),"") | C70: =IFERROR(IF(Portafolio_Proyectos!$AR23="","","Distintiva"),"") | D70: =IFERROR(IF(Portafolio_Proyectos!$AR23="","",Portafolio_Proyectos!$C23),"") | E70: =IFERROR(IF(Portafolio_Proyectos!$AR23="","",Portafolio_Proyectos!$B23),"") | F70: =IFERROR(IF(Portafolio_Proyectos!$AR23="","",Portafolio_Proyectos!$D23),"") | G70: =IFERROR(IF(Portafolio_Proyectos!$AR23="","",Portafolio_Proyectos!$A23),"") | H70: =IFERROR(IF(Portafolio_Proyectos!$AR23="","",Portafolio_Proyectos!$E23),"")
A71: =IFERROR(IF(Portafolio_Proyectos!$AP24="","","CAP-"&ROW()-1),"") | B71: =IFERROR(IF(Portafolio_Proyectos!$AP24="","",Portafolio_Proyectos!$AP24),"") | C71: =IFERROR(IF(Portafolio_Proyectos!$AP24="","","Emergente"),"") | D71: =IFERROR(IF(Portafolio_Proyectos!$AP24="","",Portafolio_Proyectos!$C24),"") | E71: =IFERROR(IF(Portafolio_Proyectos!$AP24="","",Portafolio_Proyectos!$B24),"") | F71: =IFERROR(IF(Portafolio_Proyectos!$AP24="","",Portafolio_Proyectos!$D24),"") | G71: =IFERROR(IF(Portafolio_Proyectos!$AP24="","",Portafolio_Proyectos!$A24),"") | H71: =IFERROR(IF(Portafolio_Proyectos!$AP24="","",Portafolio_Proyectos!$E24),"")
A72: =IFERROR(IF(Portafolio_Proyectos!$AQ24="","","CAP-"&ROW()-1),"") | B72: =IFERROR(IF(Portafolio_Proyectos!$AQ24="","",Portafolio_Proyectos!$AQ24),"") | C72: =IFERROR(IF(Portafolio_Proyectos!$AQ24="","","Consolidada"),"") | D72: =IFERROR(IF(Portafolio_Proyectos!$AQ24="","",Portafolio_Proyectos!$C24),"") | E72: =IFERROR(IF(Portafolio_Proyectos!$AQ24="","",Portafolio_Proyectos!$B24),"") | F72: =IFERROR(IF(Portafolio_Proyectos!$AQ24="","",Portafolio_Proyectos!$D24),"") | G72: =IFERROR(IF(Portafolio_Proyectos!$AQ24="","",Portafolio_Proyectos!$A24),"") | H72: =IFERROR(IF(Portafolio_Proyectos!$AQ24="","",Portafolio_Proyectos!$E24),"")
A73: =IFERROR(IF(Portafolio_Proyectos!$AR24="","","CAP-"&ROW()-1),"") | B73: =IFERROR(IF(Portafolio_Proyectos!$AR24="","",Portafolio_Proyectos!$AR24),"") | C73: =IFERROR(IF(Portafolio_Proyectos!$AR24="","","Distintiva"),"") | D73: =IFERROR(IF(Portafolio_Proyectos!$AR24="","",Portafolio_Proyectos!$C24),"") | E73: =IFERROR(IF(Portafolio_Proyectos!$AR24="","",Portafolio_Proyectos!$B24),"") | F73: =IFERROR(IF(Portafolio_Proyectos!$AR24="","",Portafolio_Proyectos!$D24),"") | G73: =IFERROR(IF(Portafolio_Proyectos!$AR24="","",Portafolio_Proyectos!$A24),"") | H73: =IFERROR(IF(Portafolio_Proyectos!$AR24="","",Portafolio_Proyectos!$E24),"")
A74: =IFERROR(IF(Portafolio_Proyectos!$AP25="","","CAP-"&ROW()-1),"") | B74: =IFERROR(IF(Portafolio_Proyectos!$AP25="","",Portafolio_Proyectos!$AP25),"") | C74: =IFERROR(IF(Portafolio_Proyectos!$AP25="","","Emergente"),"") | D74: =IFERROR(IF(Portafolio_Proyectos!$AP25="","",Portafolio_Proyectos!$C25),"") | E74: =IFERROR(IF(Portafolio_Proyectos!$AP25="","",Portafolio_Proyectos!$B25),"") | F74: =IFERROR(IF(Portafolio_Proyectos!$AP25="","",Portafolio_Proyectos!$D25),"") | G74: =IFERROR(IF(Portafolio_Proyectos!$AP25="","",Portafolio_Proyectos!$A25),"") | H74: =IFERROR(IF(Portafolio_Proyectos!$AP25="","",Portafolio_Proyectos!$E25),"")
A75: =IFERROR(IF(Portafolio_Proyectos!$AQ25="","","CAP-"&ROW()-1),"") | B75: =IFERROR(IF(Portafolio_Proyectos!$AQ25="","",Portafolio_Proyectos!$AQ25),"") | C75: =IFERROR(IF(Portafolio_Proyectos!$AQ25="","","Consolidada"),"") | D75: =IFERROR(IF(Portafolio_Proyectos!$AQ25="","",Portafolio_Proyectos!$C25),"") | E75: =IFERROR(IF(Portafolio_Proyectos!$AQ25="","",Portafolio_Proyectos!$B25),"") | F75: =IFERROR(IF(Portafolio_Proyectos!$AQ25="","",Portafolio_Proyectos!$D25),"") | G75: =IFERROR(IF(Portafolio_Proyectos!$AQ25="","",Portafolio_Proyectos!$A25),"") | H75: =IFERROR(IF(Portafolio_Proyectos!$AQ25="","",Portafolio_Proyectos!$E25),"")
A76: =IFERROR(IF(Portafolio_Proyectos!$AR25="","","CAP-"&ROW()-1),"") | B76: =IFERROR(IF(Portafolio_Proyectos!$AR25="","",Portafolio_Proyectos!$AR25),"") | C76: =IFERROR(IF(Portafolio_Proyectos!$AR25="","","Distintiva"),"") | D76: =IFERROR(IF(Portafolio_Proyectos!$AR25="","",Portafolio_Proyectos!$C25),"") | E76: =IFERROR(IF(Portafolio_Proyectos!$AR25="","",Portafolio_Proyectos!$B25),"") | F76: =IFERROR(IF(Portafolio_Proyectos!$AR25="","",Portafolio_Proyectos!$D25),"") | G76: =IFERROR(IF(Portafolio_Proyectos!$AR25="","",Portafolio_Proyectos!$A25),"") | H76: =IFERROR(IF(Portafolio_Proyectos!$AR25="","",Portafolio_Proyectos!$E25),"")
A77: =IFERROR(IF(Portafolio_Proyectos!$AP26="","","CAP-"&ROW()-1),"") | B77: =IFERROR(IF(Portafolio_Proyectos!$AP26="","",Portafolio_Proyectos!$AP26),"") | C77: =IFERROR(IF(Portafolio_Proyectos!$AP26="","","Emergente"),"") | D77: =IFERROR(IF(Portafolio_Proyectos!$AP26="","",Portafolio_Proyectos!$C26),"") | E77: =IFERROR(IF(Portafolio_Proyectos!$AP26="","",Portafolio_Proyectos!$B26),"") | F77: =IFERROR(IF(Portafolio_Proyectos!$AP26="","",Portafolio_Proyectos!$D26),"") | G77: =IFERROR(IF(Portafolio_Proyectos!$AP26="","",Portafolio_Proyectos!$A26),"") | H77: =IFERROR(IF(Portafolio_Proyectos!$AP26="","",Portafolio_Proyectos!$E26),"")
A78: =IFERROR(IF(Portafolio_Proyectos!$AQ26="","","CAP-"&ROW()-1),"") | B78: =IFERROR(IF(Portafolio_Proyectos!$AQ26="","",Portafolio_Proyectos!$AQ26),"") | C78: =IFERROR(IF(Portafolio_Proyectos!$AQ26="","","Consolidada"),"") | D78: =IFERROR(IF(Portafolio_Proyectos!$AQ26="","",Portafolio_Proyectos!$C26),"") | E78: =IFERROR(IF(Portafolio_Proyectos!$AQ26="","",Portafolio_Proyectos!$B26),"") | F78: =IFERROR(IF(Portafolio_Proyectos!$AQ26="","",Portafolio_Proyectos!$D26),"") | G78: =IFERROR(IF(Portafolio_Proyectos!$AQ26="","",Portafolio_Proyectos!$A26),"") | H78: =IFERROR(IF(Portafolio_Proyectos!$AQ26="","",Portafolio_Proyectos!$E26),"")
A79: =IFERROR(IF(Portafolio_Proyectos!$AR26="","","CAP-"&ROW()-1),"") | B79: =IFERROR(IF(Portafolio_Proyectos!$AR26="","",Portafolio_Proyectos!$AR26),"") | C79: =IFERROR(IF(Portafolio_Proyectos!$AR26="","","Distintiva"),"") | D79: =IFERROR(IF(Portafolio_Proyectos!$AR26="","",Portafolio_Proyectos!$C26),"") | E79: =IFERROR(IF(Portafolio_Proyectos!$AR26="","",Portafolio_Proyectos!$B26),"") | F79: =IFERROR(IF(Portafolio_Proyectos!$AR26="","",Portafolio_Proyectos!$D26),"") | G79: =IFERROR(IF(Portafolio_Proyectos!$AR26="","",Portafolio_Proyectos!$A26),"") | H79: =IFERROR(IF(Portafolio_Proyectos!$AR26="","",Portafolio_Proyectos!$E26),"")
A80: =IFERROR(IF(Portafolio_Proyectos!$AP27="","","CAP-"&ROW()-1),"") | B80: =IFERROR(IF(Portafolio_Proyectos!$AP27="","",Portafolio_Proyectos!$AP27),"") | C80: =IFERROR(IF(Portafolio_Proyectos!$AP27="","","Emergente"),"") | D80: =IFERROR(IF(Portafolio_Proyectos!$AP27="","",Portafolio_Proyectos!$C27),"") | E80: =IFERROR(IF(Portafolio_Proyectos!$AP27="","",Portafolio_Proyectos!$B27),"") | F80: =IFERROR(IF(Portafolio_Proyectos!$AP27="","",Portafolio_Proyectos!$D27),"") | G80: =IFERROR(IF(Portafolio_Proyectos!$AP27="","",Portafolio_Proyectos!$A27),"") | H80: =IFERROR(IF(Portafolio_Proyectos!$AP27="","",Portafolio_Proyectos!$E27),"")
A81: =IFERROR(IF(Portafolio_Proyectos!$AQ27="","","CAP-"&ROW()-1),"") | B81: =IFERROR(IF(Portafolio_Proyectos!$AQ27="","",Portafolio_Proyectos!$AQ27),"") | C81: =IFERROR(IF(Portafolio_Proyectos!$AQ27="","","Consolidada"),"") | D81: =IFERROR(IF(Portafolio_Proyectos!$AQ27="","",Portafolio_Proyectos!$C27),"") | E81: =IFERROR(IF(Portafolio_Proyectos!$AQ27="","",Portafolio_Proyectos!$B27),"") | F81: =IFERROR(IF(Portafolio_Proyectos!$AQ27="","",Portafolio_Proyectos!$D27),"") | G81: =IFERROR(IF(Portafolio_Proyectos!$AQ27="","",Portafolio_Proyectos!$A27),"") | H81: =IFERROR(IF(Portafolio_Proyectos!$AQ27="","",Portafolio_Proyectos!$E27),"")
A82: =IFERROR(IF(Portafolio_Proyectos!$AR27="","","CAP-"&ROW()-1),"") | B82: =IFERROR(IF(Portafolio_Proyectos!$AR27="","",Portafolio_Proyectos!$AR27),"") | C82: =IFERROR(IF(Portafolio_Proyectos!$AR27="","","Distintiva"),"") | D82: =IFERROR(IF(Portafolio_Proyectos!$AR27="","",Portafolio_Proyectos!$C27),"") | E82: =IFERROR(IF(Portafolio_Proyectos!$AR27="","",Portafolio_Proyectos!$B27),"") | F82: =IFERROR(IF(Portafolio_Proyectos!$AR27="","",Portafolio_Proyectos!$D27),"") | G82: =IFERROR(IF(Portafolio_Proyectos!$AR27="","",Portafolio_Proyectos!$A27),"") | H82: =IFERROR(IF(Portafolio_Proyectos!$AR27="","",Portafolio_Proyectos!$E27),"")
A83: =IFERROR(IF(Portafolio_Proyectos!$AP28="","","CAP-"&ROW()-1),"") | B83: =IFERROR(IF(Portafolio_Proyectos!$AP28="","",Portafolio_Proyectos!$AP28),"") | C83: =IFERROR(IF(Portafolio_Proyectos!$AP28="","","Emergente"),"") | D83: =IFERROR(IF(Portafolio_Proyectos!$AP28="","",Portafolio_Proyectos!$C28),"") | E83: =IFERROR(IF(Portafolio_Proyectos!$AP28="","",Portafolio_Proyectos!$B28),"") | F83: =IFERROR(IF(Portafolio_Proyectos!$AP28="","",Portafolio_Proyectos!$D28),"") | G83: =IFERROR(IF(Portafolio_Proyectos!$AP28="","",Portafolio_Proyectos!$A28),"") | H83: =IFERROR(IF(Portafolio_Proyectos!$AP28="","",Portafolio_Proyectos!$E28),"")
A84: =IFERROR(IF(Portafolio_Proyectos!$AQ28="","","CAP-"&ROW()-1),"") | B84: =IFERROR(IF(Portafolio_Proyectos!$AQ28="","",Portafolio_Proyectos!$AQ28),"") | C84: =IFERROR(IF(Portafolio_Proyectos!$AQ28="","","Consolidada"),"") | D84: =IFERROR(IF(Portafolio_Proyectos!$AQ28="","",Portafolio_Proyectos!$C28),"") | E84: =IFERROR(IF(Portafolio_Proyectos!$AQ28="","",Portafolio_Proyectos!$B28),"") | F84: =IFERROR(IF(Portafolio_Proyectos!$AQ28="","",Portafolio_Proyectos!$D28),"") | G84: =IFERROR(IF(Portafolio_Proyectos!$AQ28="","",Portafolio_Proyectos!$A28),"") | H84: =IFERROR(IF(Portafolio_Proyectos!$AQ28="","",Portafolio_Proyectos!$E28),"")
A85: =IFERROR(IF(Portafolio_Proyectos!$AR28="","","CAP-"&ROW()-1),"") | B85: =IFERROR(IF(Portafolio_Proyectos!$AR28="","",Portafolio_Proyectos!$AR28),"") | C85: =IFERROR(IF(Portafolio_Proyectos!$AR28="","","Distintiva"),"") | D85: =IFERROR(IF(Portafolio_Proyectos!$AR28="","",Portafolio_Proyectos!$C28),"") | E85: =IFERROR(IF(Portafolio_Proyectos!$AR28="","",Portafolio_Proyectos!$B28),"") | F85: =IFERROR(IF(Portafolio_Proyectos!$AR28="","",Portafolio_Proyectos!$D28),"") | G85: =IFERROR(IF(Portafolio_Proyectos!$AR28="","",Portafolio_Proyectos!$A28),"") | H85: =IFERROR(IF(Portafolio_Proyectos!$AR28="","",Portafolio_Proyectos!$E28),"")
A86: =IFERROR(IF(Portafolio_Proyectos!$AP29="","","CAP-"&ROW()-1),"") | B86: =IFERROR(IF(Portafolio_Proyectos!$AP29="","",Portafolio_Proyectos!$AP29),"") | C86: =IFERROR(IF(Portafolio_Proyectos!$AP29="","","Emergente"),"") | D86: =IFERROR(IF(Portafolio_Proyectos!$AP29="","",Portafolio_Proyectos!$C29),"") | E86: =IFERROR(IF(Portafolio_Proyectos!$AP29="","",Portafolio_Proyectos!$B29),"") | F86: =IFERROR(IF(Portafolio_Proyectos!$AP29="","",Portafolio_Proyectos!$D29),"") | G86: =IFERROR(IF(Portafolio_Proyectos!$AP29="","",Portafolio_Proyectos!$A29),"") | H86: =IFERROR(IF(Portafolio_Proyectos!$AP29="","",Portafolio_Proyectos!$E29),"")
A87: =IFERROR(IF(Portafolio_Proyectos!$AQ29="","","CAP-"&ROW()-1),"") | B87: =IFERROR(IF(Portafolio_Proyectos!$AQ29="","",Portafolio_Proyectos!$AQ29),"") | C87: =IFERROR(IF(Portafolio_Proyectos!$AQ29="","","Consolidada"),"") | D87: =IFERROR(IF(Portafolio_Proyectos!$AQ29="","",Portafolio_Proyectos!$C29),"") | E87: =IFERROR(IF(Portafolio_Proyectos!$AQ29="","",Portafolio_Proyectos!$B29),"") | F87: =IFERROR(IF(Portafolio_Proyectos!$AQ29="","",Portafolio_Proyectos!$D29),"") | G87: =IFERROR(IF(Portafolio_Proyectos!$AQ29="","",Portafolio_Proyectos!$A29),"") | H87: =IFERROR(IF(Portafolio_Proyectos!$AQ29="","",Portafolio_Proyectos!$E29),"")
A88: =IFERROR(IF(Portafolio_Proyectos!$AR29="","","CAP-"&ROW()-1),"") | B88: =IFERROR(IF(Portafolio_Proyectos!$AR29="","",Portafolio_Proyectos!$AR29),"") | C88: =IFERROR(IF(Portafolio_Proyectos!$AR29="","","Distintiva"),"") | D88: =IFERROR(IF(Portafolio_Proyectos!$AR29="","",Portafolio_Proyectos!$C29),"") | E88: =IFERROR(IF(Portafolio_Proyectos!$AR29="","",Portafolio_Proyectos!$B29),"") | F88: =IFERROR(IF(Portafolio_Proyectos!$AR29="","",Portafolio_Proyectos!$D29),"") | G88: =IFERROR(IF(Portafolio_Proyectos!$AR29="","",Portafolio_Proyectos!$A29),"") | H88: =IFERROR(IF(Portafolio_Proyectos!$AR29="","",Portafolio_Proyectos!$E29),"")
A89: =IFERROR(IF(Portafolio_Proyectos!$AP30="","","CAP-"&ROW()-1),"") | B89: =IFERROR(IF(Portafolio_Proyectos!$AP30="","",Portafolio_Proyectos!$AP30),"") | C89: =IFERROR(IF(Portafolio_Proyectos!$AP30="","","Emergente"),"") | D89: =IFERROR(IF(Portafolio_Proyectos!$AP30="","",Portafolio_Proyectos!$C30),"") | E89: =IFERROR(IF(Portafolio_Proyectos!$AP30="","",Portafolio_Proyectos!$B30),"") | F89: =IFERROR(IF(Portafolio_Proyectos!$AP30="","",Portafolio_Proyectos!$D30),"") | G89: =IFERROR(IF(Portafolio_Proyectos!$AP30="","",Portafolio_Proyectos!$A30),"") | H89: =IFERROR(IF(Portafolio_Proyectos!$AP30="","",Portafolio_Proyectos!$E30),"")
A90: =IFERROR(IF(Portafolio_Proyectos!$AQ30="","","CAP-"&ROW()-1),"") | B90: =IFERROR(IF(Portafolio_Proyectos!$AQ30="","",Portafolio_Proyectos!$AQ30),"") | C90: =IFERROR(IF(Portafolio_Proyectos!$AQ30="","","Consolidada"),"") | D90: =IFERROR(IF(Portafolio_Proyectos!$AQ30="","",Portafolio_Proyectos!$C30),"") | E90: =IFERROR(IF(Portafolio_Proyectos!$AQ30="","",Portafolio_Proyectos!$B30),"") | F90: =IFERROR(IF(Portafolio_Proyectos!$AQ30="","",Portafolio_Proyectos!$D30),"") | G90: =IFERROR(IF(Portafolio_Proyectos!$AQ30="","",Portafolio_Proyectos!$A30),"") | H90: =IFERROR(IF(Portafolio_Proyectos!$AQ30="","",Portafolio_Proyectos!$E30),"")
A91: =IFERROR(IF(Portafolio_Proyectos!$AR30="","","CAP-"&ROW()-1),"") -> CAP-90 | B91: =IFERROR(IF(Portafolio_Proyectos!$AR30="","",Portafolio_Proyectos!$AR30),"") -> Desarrollo de oferta tecnológica transferible Capacidad de convertir ciencia en productos de valor | C91: =IFERROR(IF(Portafolio_Proyectos!$AR30="","","Distintiva"),"") -> Distintiva | D91: =IFERROR(IF(Portafolio_Proyectos!$AR30="","",Portafolio_Proyectos!$C30),"") -> Manejo cosecha, poscosecha y transformación | E91: =IFERROR(IF(Portafolio_Proyectos!$AR30="","",Portafolio_Proyectos!$B30),"") -> Cacao | F91: =IFERROR(IF(Portafolio_Proyectos!$AR30="","",Portafolio_Proyectos!$D30),"") -> 1002666: Viabilidad centros de fermentación en las regiones cacaoteras de Caldas, Huila y Tolima. | G91: =IFERROR(IF(Portafolio_Proyectos!$AR30="","",Portafolio_Proyectos!$A30),"") -> Bioeconomía: Economía circular | H91: =IFERROR(IF(Portafolio_Proyectos!$AR30="","",Portafolio_Proyectos!$E30),"") -> Jader Rodríguez Cortina
A92: =IFERROR(IF(Portafolio_Proyectos!$AP31="","","CAP-"&ROW()-1),"") | B92: =IFERROR(IF(Portafolio_Proyectos!$AP31="","",Portafolio_Proyectos!$AP31),"") | C92: =IFERROR(IF(Portafolio_Proyectos!$AP31="","","Emergente"),"") | D92: =IFERROR(IF(Portafolio_Proyectos!$AP31="","",Portafolio_Proyectos!$C31),"") | E92: =IFERROR(IF(Portafolio_Proyectos!$AP31="","",Portafolio_Proyectos!$B31),"") | F92: =IFERROR(IF(Portafolio_Proyectos!$AP31="","",Portafolio_Proyectos!$D31),"") | G92: =IFERROR(IF(Portafolio_Proyectos!$AP31="","",Portafolio_Proyectos!$A31),"") | H92: =IFERROR(IF(Portafolio_Proyectos!$AP31="","",Portafolio_Proyectos!$E31),"")
A93: =IFERROR(IF(Portafolio_Proyectos!$AQ31="","","CAP-"&ROW()-1),"") -> CAP-92 | B93: =IFERROR(IF(Portafolio_Proyectos!$AQ31="","",Portafolio_Proyectos!$AQ31),"") -> Calidad sensorial de cacao Protocolos de fermentación y secado | C93: =IFERROR(IF(Portafolio_Proyectos!$AQ31="","","Consolidada"),"") -> Consolidada | D93: =IFERROR(IF(Portafolio_Proyectos!$AQ31="","",Portafolio_Proyectos!$C31),"") -> Manejo cosecha, poscosecha y transformación | E93: =IFERROR(IF(Portafolio_Proyectos!$AQ31="","",Portafolio_Proyectos!$B31),"") -> Cacao | F93: =IFERROR(IF(Portafolio_Proyectos!$AQ31="","",Portafolio_Proyectos!$D31),"") -> ID: 1002667. Establecimiento de protocolos apropiados de fermentación basados en perfiles sensoriales del cacao en Caldas, Huila y Tolima. | G93: =IFERROR(IF(Portafolio_Proyectos!$AQ31="","",Portafolio_Proyectos!$A31),"") -> Bioeconomía: Economía circular | H93: =IFERROR(IF(Portafolio_Proyectos!$AQ31="","",Portafolio_Proyectos!$E31),"") -> Jader Rodríguez Cortina
A94: =IFERROR(IF(Portafolio_Proyectos!$AR31="","","CAP-"&ROW()-1),"") | B94: =IFERROR(IF(Portafolio_Proyectos!$AR31="","",Portafolio_Proyectos!$AR31),"") | C94: =IFERROR(IF(Portafolio_Proyectos!$AR31="","","Distintiva"),"") | D94: =IFERROR(IF(Portafolio_Proyectos!$AR31="","",Portafolio_Proyectos!$C31),"") | E94: =IFERROR(IF(Portafolio_Proyectos!$AR31="","",Portafolio_Proyectos!$B31),"") | F94: =IFERROR(IF(Portafolio_Proyectos!$AR31="","",Portafolio_Proyectos!$D31),"") | G94: =IFERROR(IF(Portafolio_Proyectos!$AR31="","",Portafolio_Proyectos!$A31),"") | H94: =IFERROR(IF(Portafolio_Proyectos!$AR31="","",Portafolio_Proyectos!$E31),"")
A95: =IFERROR(IF(Portafolio_Proyectos!$AP32="","","CAP-"&ROW()-1),"") | B95: =IFERROR(IF(Portafolio_Proyectos!$AP32="","",Portafolio_Proyectos!$AP32),"") | C95: =IFERROR(IF(Portafolio_Proyectos!$AP32="","","Emergente"),"") | D95: =IFERROR(IF(Portafolio_Proyectos!$AP32="","",Portafolio_Proyectos!$C32),"") | E95: =IFERROR(IF(Portafolio_Proyectos!$AP32="","",Portafolio_Proyectos!$B32),"") | F95: =IFERROR(IF(Portafolio_Proyectos!$AP32="","",Portafolio_Proyectos!$D32),"") | G95: =IFERROR(IF(Portafolio_Proyectos!$AP32="","",Portafolio_Proyectos!$A32),"") | H95: =IFERROR(IF(Portafolio_Proyectos!$AP32="","",Portafolio_Proyectos!$E32),"")
A96: =IFERROR(IF(Portafolio_Proyectos!$AQ32="","","CAP-"&ROW()-1),"") -> CAP-95 | B96: =IFERROR(IF(Portafolio_Proyectos!$AQ32="","",Portafolio_Proyectos!$AQ32),"") -> Valorización de subproductos Diseño de equipos de poscosecha Escalamiento de tecnologías en cacao | C96: =IFERROR(IF(Portafolio_Proyectos!$AQ32="","","Consolidada"),"") -> Consolidada | D96: =IFERROR(IF(Portafolio_Proyectos!$AQ32="","",Portafolio_Proyectos!$C32),"") -> Manejo cosecha, poscosecha y transformación | E96: =IFERROR(IF(Portafolio_Proyectos!$AQ32="","",Portafolio_Proyectos!$B32),"") -> Cacao | F96: =IFERROR(IF(Portafolio_Proyectos!$AQ32="","",Portafolio_Proyectos!$D32),"") -> ID: 1002841. Implementación de un modelo para el aprovechamiento integral de las mazorcas de cacao para la generación de productos de valor agregado por medio de alternativas biotecnológicas | G96: =IFERROR(IF(Portafolio_Proyectos!$AQ32="","",Portafolio_Proyectos!$A32),"") -> Bioeconomía: Economía circular | H96: =IFERROR(IF(Portafolio_Proyectos!$AQ32="","",Portafolio_Proyectos!$E32),"") -> Jader Rodríguez Cortina
A97: =IFERROR(IF(Portafolio_Proyectos!$AR32="","","CAP-"&ROW()-1),"") -> CAP-96 | B97: =IFERROR(IF(Portafolio_Proyectos!$AR32="","",Portafolio_Proyectos!$AR32),"") -> Enfoque de bioeconomía en cacao Desarrollo de oferta tecnológica transferible Capacidad de convertir ciencia en productos de valor | C97: =IFERROR(IF(Portafolio_Proyectos!$AR32="","","Distintiva"),"") -> Distintiva | D97: =IFERROR(IF(Portafolio_Proyectos!$AR32="","",Portafolio_Proyectos!$C32),"") -> Manejo cosecha, poscosecha y transformación | E97: =IFERROR(IF(Portafolio_Proyectos!$AR32="","",Portafolio_Proyectos!$B32),"") -> Cacao | F97: =IFERROR(IF(Portafolio_Proyectos!$AR32="","",Portafolio_Proyectos!$D32),"") -> ID: 1002841. Implementación de un modelo para el aprovechamiento integral de las mazorcas de cacao para la generación de productos de valor agregado por medio de alternativas biotecnológicas | G97: =IFERROR(IF(Portafolio_Proyectos!$AR32="","",Portafolio_Proyectos!$A32),"") -> Bioeconomía: Economía circular | H97: =IFERROR(IF(Portafolio_Proyectos!$AR32="","",Portafolio_Proyectos!$E32),"") -> Jader Rodríguez Cortina
A98: =IFERROR(IF(Portafolio_Proyectos!$AP33="","","CAP-"&ROW()-1),"") | B98: =IFERROR(IF(Portafolio_Proyectos!$AP33="","",Portafolio_Proyectos!$AP33),"") | C98: =IFERROR(IF(Portafolio_Proyectos!$AP33="","","Emergente"),"") | D98: =IFERROR(IF(Portafolio_Proyectos!$AP33="","",Portafolio_Proyectos!$C33),"") | E98: =IFERROR(IF(Portafolio_Proyectos!$AP33="","",Portafolio_Proyectos!$B33),"") | F98: =IFERROR(IF(Portafolio_Proyectos!$AP33="","",Portafolio_Proyectos!$D33),"") | G98: =IFERROR(IF(Portafolio_Proyectos!$AP33="","",Portafolio_Proyectos!$A33),"") | H98: =IFERROR(IF(Portafolio_Proyectos!$AP33="","",Portafolio_Proyectos!$E33),"")
A99: =IFERROR(IF(Portafolio_Proyectos!$AQ33="","","CAP-"&ROW()-1),"") | B99: =IFERROR(IF(Portafolio_Proyectos!$AQ33="","",Portafolio_Proyectos!$AQ33),"") | C99: =IFERROR(IF(Portafolio_Proyectos!$AQ33="","","Consolidada"),"") | D99: =IFERROR(IF(Portafolio_Proyectos!$AQ33="","",Portafolio_Proyectos!$C33),"") | E99: =IFERROR(IF(Portafolio_Proyectos!$AQ33="","",Portafolio_Proyectos!$B33),"") | F99: =IFERROR(IF(Portafolio_Proyectos!$AQ33="","",Portafolio_Proyectos!$D33),"") | G99: =IFERROR(IF(Portafolio_Proyectos!$AQ33="","",Portafolio_Proyectos!$A33),"") | H99: =IFERROR(IF(Portafolio_Proyectos!$AQ33="","",Portafolio_Proyectos!$E33),"")
A100: =IFERROR(IF(Portafolio_Proyectos!$AR33="","","CAP-"&ROW()-1),"") | B100: =IFERROR(IF(Portafolio_Proyectos!$AR33="","",Portafolio_Proyectos!$AR33),"") | C100: =IFERROR(IF(Portafolio_Proyectos!$AR33="","","Distintiva"),"") | D100: =IFERROR(IF(Portafolio_Proyectos!$AR33="","",Portafolio_Proyectos!$C33),"") | E100: =IFERROR(IF(Portafolio_Proyectos!$AR33="","",Portafolio_Proyectos!$B33),"") | F100: =IFERROR(IF(Portafolio_Proyectos!$AR33="","",Portafolio_Proyectos!$D33),"") | G100: =IFERROR(IF(Portafolio_Proyectos!$AR33="","",Portafolio_Proyectos!$A33),"") | H100: =IFERROR(IF(Portafolio_Proyectos!$AR33="","",Portafolio_Proyectos!$E33),"")
...

Sheet Dashboard_Gerencial
A1: C.I. Palmira — Dashboard Gerencial del Portafolio de I+D+i
A2: Resumen ejecutivo automático. Todos los indicadores se actualizan al diligenciar Portafolio_Proyectos. Para análisis detallado, consulte las Vistas V1 a V8.
A4: Indicadores clave del portafolio
A5: Total proyectos | B5: Sistemas productivos | C5: Proyectos activos | D5: Con impacto social | E5: Depts. cubiertos | F5: Con TRL registrado
A6: =COUNTA(Tabla_Proyectos[Nombre del proyecto]) -> 132 | B6: =SUMPRODUCT((Tabla_Proyectos[Sistema productivo]<>"")/COUNTIF(Tabla_Proyectos[Sistema productivo],Tabla_Proyectos[Sistema productivo]&"")) -> 26 | C6: =COUNTIF(Tabla_Proyectos[Estado del proyecto],"En ejecución") -> 4 | D6: =COUNTIF(Tabla_Proyectos[Impacto social],"<>") -> 8 | E6: =COUNTIF(Tabla_Proyectos[Departamentos],"<>") -> 28 | F6: =COUNTIFS(Tabla_Proyectos[TRL final],"<>",Tabla_Proyectos[TRL final],"<>No definido") -> 7
A8: Top 10 — sistemas con más proyectos | E8: Completitud del portafolio (%)
A9: Sistema productivo | B9: Total proyectos | C9: En ejecución | E9: Campo crítico | F9: % diligenciado
A10: Aguacate Hass | B10: =COUNTIF(Tabla_Proyectos[Sistema productivo],"Aguacate Hass") -> 17 | C10: =COUNTIFS(Tabla_Proyectos[Sistema productivo],"Aguacate Hass",Tabla_Proyectos[Estado del proyecto],"En ejecución") -> 2 | E10: Investigador líder | F10: =IFERROR(COUNTA(Tabla_Proyectos[Investigador líder])/COUNTA(Tabla_Proyectos[Nombre del proyecto]),0) -> 0.075757576
A11: Guayaba | B11: =COUNTIF(Tabla_Proyectos[Sistema productivo],"Guayaba") -> 18 | C11: =COUNTIFS(Tabla_Proyectos[Sistema productivo],"Guayaba",Tabla_Proyectos[Estado del proyecto],"En ejecución") -> 0 | E11: Estado del proyecto | F11: =IFERROR(COUNTA(Tabla_Proyectos[Estado del proyecto])/COUNTA(Tabla_Proyectos[Nombre del proyecto]),0) -> 0.060606061
A12: Cacao | B12: =COUNTIF(Tabla_Proyectos[Sistema productivo],"Cacao") -> 15 | C12: =COUNTIFS(Tabla_Proyectos[Sistema productivo],"Cacao",Tabla_Proyectos[Estado del proyecto],"En ejecución") -> 2 | E12: TRL final | F12: =IFERROR(COUNTA(Tabla_Proyectos[TRL final])/COUNTA(Tabla_Proyectos[Nombre del proyecto]),0) -> 0.060606061
A13: Forestal | B13: =COUNTIF(Tabla_Proyectos[Sistema productivo],"Forestal") -> 11 | C13: =COUNTIFS(Tabla_Proyectos[Sistema productivo],"Forestal",Tabla_Proyectos[Estado del proyecto],"En ejecución") -> 0 | E13: Departamentos | F13: =IFERROR(COUNTA(Tabla_Proyectos[Departamentos])/COUNTA(Tabla_Proyectos[Nombre del proyecto]),0) -> 0.21212121
A14: Lima Acida Tahití | B14: =COUNTIF(Tabla_Proyectos[Sistema productivo],"Lima Acida Tahití") -> 11 | C14: =COUNTIFS(Tabla_Proyectos[Sistema productivo],"Lima Acida Tahití",Tabla_Proyectos[Estado del proyecto],"En ejecución") -> 0 | E14: Beneficiarios directos | F14: =IFERROR(COUNTA(Tabla_Proyectos[Beneficiarios directos])/COUNTA(Tabla_Proyectos[Nombre del proyecto]),0) -> 0.075757576
A15: Naranjas | B15: =COUNTIF(Tabla_Proyectos[Sistema productivo],"Naranjas") -> 8 | C15: =COUNTIFS(Tabla_Proyectos[Sistema productivo],"Naranjas",Tabla_Proyectos[Estado del proyecto],"En ejecución") -> 0 | E15: Impacto social | F15: =IFERROR(COUNTA(Tabla_Proyectos[Impacto social])/COUNTA(Tabla_Proyectos[Nombre del proyecto]),0) -> 0.060606061
A16: Quinua | B16: =COUNTIF(Tabla_Proyectos[Sistema productivo],"Quinua") -> 6 | C16: =COUNTIFS(Tabla_Proyectos[Sistema productivo],"Quinua",Tabla_Proyectos[Estado del proyecto],"En ejecución") -> 0 | E16: Impacto económico | F16: =IFERROR(COUNTA(Tabla_Proyectos[Impacto económico])/COUNTA(Tabla_Proyectos[Nombre del proyecto]),0) -> 0.060606061
A17: Otro | B17: =COUNTIF(Tabla_Proyectos[Sistema productivo],"Otro") -> 6 | C17: =COUNTIFS(Tabla_Proyectos[Sistema productivo],"Otro",Tabla_Proyectos[Estado del proyecto],"En ejecución") -> 0 | E17: Aliados estratégicos | F17: =IFERROR(COUNTA(Tabla_Proyectos[Aliados estratégicos])/COUNTA(Tabla_Proyectos[Nombre del proyecto]),0) -> 0.14393939
A18: Chontaduro | B18: =COUNTIF(Tabla_Proyectos[Sistema productivo],"Chontaduro") -> 4 | C18: =COUNTIFS(Tabla_Proyectos[Sistema productivo],"Chontaduro",Tabla_Proyectos[Estado del proyecto],"En ejecución") -> 0 | E18: Monto del proyecto | F18: =IFERROR(COUNTA(Tabla_Proyectos[Monto del proyecto])/COUNTA(Tabla_Proyectos[Nombre del proyecto]),0) -> 0.053030303
A19: Palma de aceite Africana | B19: =COUNTIF(Tabla_Proyectos[Sistema productivo],"Palma de aceite Africana") -> 4 | C19: =COUNTIFS(Tabla_Proyectos[Sistema productivo],"Palma de aceite Africana",Tabla_Proyectos[Estado del proyecto],"En ejecución") -> 0 | E19: Publicaciones | F19: =IFERROR(COUNTA(Tabla_Proyectos[Publicaciones])/COUNTA(Tabla_Proyectos[Nombre del proyecto]),0) -> 0.045454545
A22: Guía de navegación — Vistas del portafolio
A23: V1_Impacto_Territorial | C23: Cobertura geográfica y beneficiarios por departamento
A24: V2_Impacto_Demostrado | C24: Impactos técnicos, económicos, sociales y ambientales
A25: V3_Trayectoria_TRL | C25: Niveles de madurez tecnológica por sistema productivo
A26: V4_Red_Alianzas | C26: Aliados, financiadores y rol institucional
A27: V5_Portafolio_Activo | C27: Estado del portafolio: activo, finalizado, pipeline
A28: V6_Capacidades_Cientificas | C28: Mapa de capacidades emergentes, consolidadas y distintivas
A29: V7_Productividad_Cientifica | C29: Publicaciones, productos tecnológicos y propiedad intelectual
A30: V8_Ficha_Proyecto | C30: Ficha ejecutiva completa de un proyecto (seleccionable)

Sheet V1_Impacto_Territorial
A1: Vista 1 — Cobertura territorial del portafolio
A2: Muestra cuántos proyectos operan en cada departamento. Se actualiza automáticamente. NOTA: el campo Departamentos permite múltiples valores; se contabilizan proyectos que mencionen el departamento.
A4: A. Proyectos por departamento | E4: B. Proyectos por tipo de beneficiario
A5: Departamento | B5: N° proyectos | C5: % del total | E5: Tipo de beneficiario | F5: N° proyectos | G5: Beneficiarios directos (suma)
A6: AMAZONAS | B6: =COUNTIF(Tabla_Proyectos[Departamentos],"*AMAZONAS*") -> 0 | C6: =IFERROR(B6/COUNTIF(Tabla_Proyectos[Departamentos],"<>"),0) -> 0 | E6: Asociación de productores | F6: =COUNTIF(Tabla_Proyectos[Tipo de beneficiarios],"Asociación de productores") -> 9 | G6: =SUMIF(Tabla_Proyectos[Tipo de beneficiarios],"Asociación de productores",Tabla_Proyectos[Beneficiarios directos]) -> 2329
A7: ANTIOQUIA | B7: =COUNTIF(Tabla_Proyectos[Departamentos],"*ANTIOQUIA*") -> 2 | C7: =IFERROR(B7/COUNTIF(Tabla_Proyectos[Departamentos],"<>"),0) -> 0.071428571 | E7: Comunidad campesina | F7: =COUNTIF(Tabla_Proyectos[Tipo de beneficiarios],"Comunidad campesina") -> 2 | G7: =SUMIF(Tabla_Proyectos[Tipo de beneficiarios],"Comunidad campesina",Tabla_Proyectos[Beneficiarios directos]) -> 0
A8: ARAUCA | B8: =COUNTIF(Tabla_Proyectos[Departamentos],"*ARAUCA*") -> 1 | C8: =IFERROR(B8/COUNTIF(Tabla_Proyectos[Departamentos],"<>"),0) -> 0.035714286 | E8: Comunidad Indígena | F8: =COUNTIF(Tabla_Proyectos[Tipo de beneficiarios],"Comunidad Indígena") -> 1 | G8: =SUMIF(Tabla_Proyectos[Tipo de beneficiarios],"Comunidad Indígena",Tabla_Proyectos[Beneficiarios directos]) -> 0
A9: ARCHIPIELAGO DE SAN ANDRES | B9: =COUNTIF(Tabla_Proyectos[Departamentos],"*ARCHIPIELAGO DE SAN ANDRES*") -> 0 | C9: =IFERROR(B9/COUNTIF(Tabla_Proyectos[Departamentos],"<>"),0) -> 0 | E9: Comunidad Afrocolombiana | F9: =COUNTIF(Tabla_Proyectos[Tipo de beneficiarios],"Comunidad Afrocolombiana") -> 3 | G9: =SUMIF(Tabla_Proyectos[Tipo de beneficiarios],"Comunidad Afrocolombiana",Tabla_Proyectos[Beneficiarios directos]) -> 300
A10: ATLÁNTICO | B10: =COUNTIF(Tabla_Proyectos[Departamentos],"*ATLÁNTICO*") -> 0 | C10: =IFERROR(B10/COUNTIF(Tabla_Proyectos[Departamentos],"<>"),0) -> 0 | E10: Comunidad científica | F10: =COUNTIF(Tabla_Proyectos[Tipo de beneficiarios],"Comunidad científica") -> 0 | G10: =SUMIF(Tabla_Proyectos[Tipo de beneficiarios],"Comunidad científica",Tabla_Proyectos[Beneficiarios directos]) -> 0
A11: BOGOTÁ D.C. | B11: =COUNTIF(Tabla_Proyectos[Departamentos],"*BOGOTÁ D.C.*") -> 0 | C11: =IFERROR(B11/COUNTIF(Tabla_Proyectos[Departamentos],"<>"),0) -> 0 | E11: Otro | F11: =COUNTIF(Tabla_Proyectos[Tipo de beneficiarios],"Otro") -> 1 | G11: =SUMIF(Tabla_Proyectos[Tipo de beneficiarios],"Otro",Tabla_Proyectos[Beneficiarios directos]) -> 115
A12: BOLIVAR | B12: =COUNTIF(Tabla_Proyectos[Departamentos],"*BOLIVAR*") -> 0 | C12: =IFERROR(B12/COUNTIF(Tabla_Proyectos[Departamentos],"<>"),0) -> 0 | E12: TOTAL | F12: =SUM(F6:F11) -> 16 | G12: =SUM(G6:G11) -> 2744
A13: BOYACÁ | B13: =COUNTIF(Tabla_Proyectos[Departamentos],"*BOYACÁ*") -> 0 | C13: =IFERROR(B13/COUNTIF(Tabla_Proyectos[Departamentos],"<>"),0) -> 0
A14: C. Presencia territorial — top 10 sistemas productivos × departamento (proyectos)
A15: Departamento | B15: Aguacate Hass | C15: Lima Acida Tahití | D15: Cacao | E15: Piña | F15: Platano | G15: Chontaduro | H15: Guanábana | I15: Guayaba | J15: Naranjas | K15: Banano
A16: AMAZONAS | B16: =COUNTIFS(Tabla_Proyectos[Departamentos],"*AMAZONAS*",Tabla_Proyectos[Sistema productivo],"Aguacate Hass") -> 0 | C16: =COUNTIFS(Tabla_Proyectos[Departamentos],"*AMAZONAS*",Tabla_Proyectos[Sistema productivo],"Lima Acida Tahití") -> 0 | D16: =COUNTIFS(Tabla_Proyectos[Departamentos],"*AMAZONAS*",Tabla_Proyectos[Sistema productivo],"Cacao") -> 0 | E16: =COUNTIFS(Tabla_Proyectos[Departamentos],"*AMAZONAS*",Tabla_Proyectos[Sistema productivo],"Piña") -> 0 | F16: =COUNTIFS(Tabla_Proyectos[Departamentos],"*AMAZONAS*",Tabla_Proyectos[Sistema productivo],"Platano") -> 0 | G16: =COUNTIFS(Tabla_Proyectos[Departamentos],"*AMAZONAS*",Tabla_Proyectos[Sistema productivo],"Chontaduro") -> 0 | H16: =COUNTIFS(Tabla_Proyectos[Departamentos],"*AMAZONAS*",Tabla_Proyectos[Sistema productivo],"Guanábana") -> 0 | I16: =COUNTIFS(Tabla_Proyectos[Departamentos],"*AMAZONAS*",Tabla_Proyectos[Sistema productivo],"Guayaba") -> 0 | J16: =COUNTIFS(Tabla_Proyectos[Departamentos],"*AMAZONAS*",Tabla_Proyectos[Sistema productivo],"Naranjas") -> 0 | K16: =COUNTIFS(Tabla_Proyectos[Departamentos],"*AMAZONAS*",Tabla_Proyectos[Sistema productivo],"Banano") -> 0
A17: ANTIOQUIA | B17: =COUNTIFS(Tabla_Proyectos[Departamentos],"*ANTIOQUIA*",Tabla_Proyectos[Sistema productivo],"Aguacate Hass") -> 1 | C17: =COUNTIFS(Tabla_Proyectos[Departamentos],"*ANTIOQUIA*",Tabla_Proyectos[Sistema productivo],"Lima Acida Tahití") -> 0 | D17: =COUNTIFS(Tabla_Proyectos[Departamentos],"*ANTIOQUIA*",Tabla_Proyectos[Sistema productivo],"Cacao") -> 0 | E17: =COUNTIFS(Tabla_Proyectos[Departamentos],"*ANTIOQUIA*",Tabla_Proyectos[Sistema productivo],"Piña") -> 0 | F17: =COUNTIFS(Tabla_Proyectos[Departamentos],"*ANTIOQUIA*",Tabla_Proyectos[Sistema productivo],"Platano") -> 0 | G17: =COUNTIFS(Tabla_Proyectos[Departamentos],"*ANTIOQUIA*",Tabla_Proyectos[Sistema productivo],"Chontaduro") -> 0 | H17: =COUNTIFS(Tabla_Proyectos[Departamentos],"*ANTIOQUIA*",Tabla_Proyectos[Sistema productivo],"Guanábana") -> 0 | I17: =COUNTIFS(Tabla_Proyectos[Departamentos],"*ANTIOQUIA*",Tabla_Proyectos[Sistema productivo],"Guayaba") -> 0 | J17: =COUNTIFS(Tabla_Proyectos[Departamentos],"*ANTIOQUIA*",Tabla_Proyectos[Sistema productivo],"Naranjas") -> 0 | K17: =COUNTIFS(Tabla_Proyectos[Departamentos],"*ANTIOQUIA*",Tabla_Proyectos[Sistema productivo],"Banano") -> 0
A18: ARAUCA | B18: =COUNTIFS(Tabla_Proyectos[Departamentos],"*ARAUCA*",Tabla_Proyectos[Sistema productivo],"Aguacate Hass") -> 0 | C18: =COUNTIFS(Tabla_Proyectos[Departamentos],"*ARAUCA*",Tabla_Proyectos[Sistema productivo],"Lima Acida Tahití") -> 0 | D18: =COUNTIFS(Tabla_Proyectos[Departamentos],"*ARAUCA*",Tabla_Proyectos[Sistema productivo],"Cacao") -> 1 | E18: =COUNTIFS(Tabla_Proyectos[Departamentos],"*ARAUCA*",Tabla_Proyectos[Sistema productivo],"Piña") -> 0 | F18: =COUNTIFS(Tabla_Proyectos[Departamentos],"*ARAUCA*",Tabla_Proyectos[Sistema productivo],"Platano") -> 0 | G18: =COUNTIFS(Tabla_Proyectos[Departamentos],"*ARAUCA*",Tabla_Proyectos[Sistema productivo],"Chontaduro") -> 0 | H18: =COUNTIFS(Tabla_Proyectos[Departamentos],"*ARAUCA*",Tabla_Proyectos[Sistema productivo],"Guanábana") -> 0 | I18: =COUNTIFS(Tabla_Proyectos[Departamentos],"*ARAUCA*",Tabla_Proyectos[Sistema productivo],"Guayaba") -> 0 | J18: =COUNTIFS(Tabla_Proyectos[Departamentos],"*ARAUCA*",Tabla_Proyectos[Sistema productivo],"Naranjas") -> 0 | K18: =COUNTIFS(Tabla_Proyectos[Departamentos],"*ARAUCA*",Tabla_Proyectos[Sistema productivo],"Banano") -> 0
A19: ARCHIPIELAGO DE SAN ANDRES | B19: =COUNTIFS(Tabla_Proyectos[Departamentos],"*ARCHIPIELAGO DE SAN ANDRES*",Tabla_Proyectos[Sistema productivo],"Aguacate Hass") -> 0 | C19: =COUNTIFS(Tabla_Proyectos[Departamentos],"*ARCHIPIELAGO DE SAN ANDRES*",Tabla_Proyectos[Sistema productivo],"Lima Acida Tahití") -> 0 | D19: =COUNTIFS(Tabla_Proyectos[Departamentos],"*ARCHIPIELAGO DE SAN ANDRES*",Tabla_Proyectos[Sistema productivo],"Cacao") -> 0 | E19: =COUNTIFS(Tabla_Proyectos[Departamentos],"*ARCHIPIELAGO DE SAN ANDRES*",Tabla_Proyectos[Sistema productivo],"Piña") -> 0 | F19: =COUNTIFS(Tabla_Proyectos[Departamentos],"*ARCHIPIELAGO DE SAN ANDRES*",Tabla_Proyectos[Sistema productivo],"Platano") -> 0 | G19: =COUNTIFS(Tabla_Proyectos[Departamentos],"*ARCHIPIELAGO DE SAN ANDRES*",Tabla_Proyectos[Sistema productivo],"Chontaduro") -> 0 | H19: =COUNTIFS(Tabla_Proyectos[Departamentos],"*ARCHIPIELAGO DE SAN ANDRES*",Tabla_Proyectos[Sistema productivo],"Guanábana") -> 0 | I19: =COUNTIFS(Tabla_Proyectos[Departamentos],"*ARCHIPIELAGO DE SAN ANDRES*",Tabla_Proyectos[Sistema productivo],"Guayaba") -> 0 | J19: =COUNTIFS(Tabla_Proyectos[Departamentos],"*ARCHIPIELAGO DE SAN ANDRES*",Tabla_Proyectos[Sistema productivo],"Naranjas") -> 0 | K19: =COUNTIFS(Tabla_Proyectos[Departamentos],"*ARCHIPIELAGO DE SAN ANDRES*",Tabla_Proyectos[Sistema productivo],"Banano") -> 0
A20: ATLÁNTICO | B20: =COUNTIFS(Tabla_Proyectos[Departamentos],"*ATLÁNTICO*",Tabla_Proyectos[Sistema productivo],"Aguacate Hass") -> 0 | C20: =COUNTIFS(Tabla_Proyectos[Departamentos],"*ATLÁNTICO*",Tabla_Proyectos[Sistema productivo],"Lima Acida Tahití") -> 0 | D20: =COUNTIFS(Tabla_Proyectos[Departamentos],"*ATLÁNTICO*",Tabla_Proyectos[Sistema productivo],"Cacao") -> 0 | E20: =COUNTIFS(Tabla_Proyectos[Departamentos],"*ATLÁNTICO*",Tabla_Proyectos[Sistema productivo],"Piña") -> 0 | F20: =COUNTIFS(Tabla_Proyectos[Departamentos],"*ATLÁNTICO*",Tabla_Proyectos[Sistema productivo],"Platano") -> 0 | G20: =COUNTIFS(Tabla_Proyectos[Departamentos],"*ATLÁNTICO*",Tabla_Proyectos[Sistema productivo],"Chontaduro") -> 0 | H20: =COUNTIFS(Tabla_Proyectos[Departamentos],"*ATLÁNTICO*",Tabla_Proyectos[Sistema productivo],"Guanábana") -> 0 | I20: =COUNTIFS(Tabla_Proyectos[Departamentos],"*ATLÁNTICO*",Tabla_Proyectos[Sistema productivo],"Guayaba") -> 0 | J20: =COUNTIFS(Tabla_Proyectos[Departamentos],"*ATLÁNTICO*",Tabla_Proyectos[Sistema productivo],"Naranjas") -> 0 | K20: =COUNTIFS(Tabla_Proyectos[Departamentos],"*ATLÁNTICO*",Tabla_Proyectos[Sistema productivo],"Banano") -> 0
A21: BOGOTÁ D.C. | B21: =COUNTIFS(Tabla_Proyectos[Departamentos],"*BOGOTÁ D.C.*",Tabla_Proyectos[Sistema productivo],"Aguacate Hass") -> 0 | C21: =COUNTIFS(Tabla_Proyectos[Departamentos],"*BOGOTÁ D.C.*",Tabla_Proyectos[Sistema productivo],"Lima Acida Tahití") -> 0 | D21: =COUNTIFS(Tabla_Proyectos[Departamentos],"*BOGOTÁ D.C.*",Tabla_Proyectos[Sistema productivo],"Cacao") -> 0 | E21: =COUNTIFS(Tabla_Proyectos[Departamentos],"*BOGOTÁ D.C.*",Tabla_Proyectos[Sistema productivo],"Piña") -> 0 | F21: =COUNTIFS(Tabla_Proyectos[Departamentos],"*BOGOTÁ D.C.*",Tabla_Proyectos[Sistema productivo],"Platano") -> 0 | G21: =COUNTIFS(Tabla_Proyectos[Departamentos],"*BOGOTÁ D.C.*",Tabla_Proyectos[Sistema productivo],"Chontaduro") -> 0 | H21: =COUNTIFS(Tabla_Proyectos[Departamentos],"*BOGOTÁ D.C.*",Tabla_Proyectos[Sistema productivo],"Guanábana") -> 0 | I21: =COUNTIFS(Tabla_Proyectos[Departamentos],"*BOGOTÁ D.C.*",Tabla_Proyectos[Sistema productivo],"Guayaba") -> 0 | J21: =COUNTIFS(Tabla_Proyectos[Departamentos],"*BOGOTÁ D.C.*",Tabla_Proyectos[Sistema productivo],"Naranjas") -> 0 | K21: =COUNTIFS(Tabla_Proyectos[Departamentos],"*BOGOTÁ D.C.*",Tabla_Proyectos[Sistema productivo],"Banano") -> 0
A22: BOLIVAR | B22: =COUNTIFS(Tabla_Proyectos[Departamentos],"*BOLIVAR*",Tabla_Proyectos[Sistema productivo],"Aguacate Hass") -> 0 | C22: =COUNTIFS(Tabla_Proyectos[Departamentos],"*BOLIVAR*",Tabla_Proyectos[Sistema productivo],"Lima Acida Tahití") -> 0 | D22: =COUNTIFS(Tabla_Proyectos[Departamentos],"*BOLIVAR*",Tabla_Proyectos[Sistema productivo],"Cacao") -> 0 | E22: =COUNTIFS(Tabla_Proyectos[Departamentos],"*BOLIVAR*",Tabla_Proyectos[Sistema productivo],"Piña") -> 0 | F22: =COUNTIFS(Tabla_Proyectos[Departamentos],"*BOLIVAR*",Tabla_Proyectos[Sistema productivo],"Platano") -> 0 | G22: =COUNTIFS(Tabla_Proyectos[Departamentos],"*BOLIVAR*",Tabla_Proyectos[Sistema productivo],"Chontaduro") -> 0 | H22: =COUNTIFS(Tabla_Proyectos[Departamentos],"*BOLIVAR*",Tabla_Proyectos[Sistema productivo],"Guanábana") -> 0 | I22: =COUNTIFS(Tabla_Proyectos[Departamentos],"*BOLIVAR*",Tabla_Proyectos[Sistema productivo],"Guayaba") -> 0 | J22: =COUNTIFS(Tabla_Proyectos[Departamentos],"*BOLIVAR*",Tabla_Proyectos[Sistema productivo],"Naranjas") -> 0 | K22: =COUNTIFS(Tabla_Proyectos[Departamentos],"*BOLIVAR*",Tabla_Proyectos[Sistema productivo],"Banano") -> 0
A23: BOYACÁ | B23: =COUNTIFS(Tabla_Proyectos[Departamentos],"*BOYACÁ*",Tabla_Proyectos[Sistema productivo],"Aguacate Hass") -> 0 | C23: =COUNTIFS(Tabla_Proyectos[Departamentos],"*BOYACÁ*",Tabla_Proyectos[Sistema productivo],"Lima Acida Tahití") -> 0 | D23: =COUNTIFS(Tabla_Proyectos[Departamentos],"*BOYACÁ*",Tabla_Proyectos[Sistema productivo],"Cacao") -> 0 | E23: =COUNTIFS(Tabla_Proyectos[Departamentos],"*BOYACÁ*",Tabla_Proyectos[Sistema productivo],"Piña") -> 0 | F23: =COUNTIFS(Tabla_Proyectos[Departamentos],"*BOYACÁ*",Tabla_Proyectos[Sistema productivo],"Platano") -> 0 | G23: =COUNTIFS(Tabla_Proyectos[Departamentos],"*BOYACÁ*",Tabla_Proyectos[Sistema productivo],"Chontaduro") -> 0 | H23: =COUNTIFS(Tabla_Proyectos[Departamentos],"*BOYACÁ*",Tabla_Proyectos[Sistema productivo],"Guanábana") -> 0 | I23: =COUNTIFS(Tabla_Proyectos[Departamentos],"*BOYACÁ*",Tabla_Proyectos[Sistema productivo],"Guayaba") -> 0 | J23: =COUNTIFS(Tabla_Proyectos[Departamentos],"*BOYACÁ*",Tabla_Proyectos[Sistema productivo],"Naranjas") -> 0 | K23: =COUNTIFS(Tabla_Proyectos[Departamentos],"*BOYACÁ*",Tabla_Proyectos[Sistema productivo],"Banano") -> 0
A24: CALDAS | B24: =COUNTIFS(Tabla_Proyectos[Departamentos],"*CALDAS*",Tabla_Proyectos[Sistema productivo],"Aguacate Hass") -> 0 | C24: =COUNTIFS(Tabla_Proyectos[Departamentos],"*CALDAS*",Tabla_Proyectos[Sistema productivo],"Lima Acida Tahití") -> 0 | D24: =COUNTIFS(Tabla_Proyectos[Departamentos],"*CALDAS*",Tabla_Proyectos[Sistema productivo],"Cacao") -> 2 | E24: =COUNTIFS(Tabla_Proyectos[Departamentos],"*CALDAS*",Tabla_Proyectos[Sistema productivo],"Piña") -> 0 | F24: =COUNTIFS(Tabla_Proyectos[Departamentos],"*CALDAS*",Tabla_Proyectos[Sistema productivo],"Platano") -> 1 | G24: =COUNTIFS(Tabla_Proyectos[Departamentos],"*CALDAS*",Tabla_Proyectos[Sistema productivo],"Chontaduro") -> 0 | H24: =COUNTIFS(Tabla_Proyectos[Departamentos],"*CALDAS*",Tabla_Proyectos[Sistema productivo],"Guanábana") -> 0 | I24: =COUNTIFS(Tabla_Proyectos[Departamentos],"*CALDAS*",Tabla_Proyectos[Sistema productivo],"Guayaba") -> 0 | J24: =COUNTIFS(Tabla_Proyectos[Departamentos],"*CALDAS*",Tabla_Proyectos[Sistema productivo],"Naranjas") -> 0 | K24: =COUNTIFS(Tabla_Proyectos[Departamentos],"*CALDAS*",Tabla_Proyectos[Sistema productivo],"Banano") -> 0
A25: CAQUETA | B25: =COUNTIFS(Tabla_Proyectos[Departamentos],"*CAQUETA*",Tabla_Proyectos[Sistema productivo],"Aguacate Hass") -> 0 | C25: =COUNTIFS(Tabla_Proyectos[Departamentos],"*CAQUETA*",Tabla_Proyectos[Sistema productivo],"Lima Acida Tahití") -> 0 | D25: =COUNTIFS(Tabla_Proyectos[Departamentos],"*CAQUETA*",Tabla_Proyectos[Sistema productivo],"Cacao") -> 0 | E25: =COUNTIFS(Tabla_Proyectos[Departamentos],"*CAQUETA*",Tabla_Proyectos[Sistema productivo],"Piña") -> 0 | F25: =COUNTIFS(Tabla_Proyectos[Departamentos],"*CAQUETA*",Tabla_Proyectos[Sistema productivo],"Platano") -> 0 | G25: =COUNTIFS(Tabla_Proyectos[Departamentos],"*CAQUETA*",Tabla_Proyectos[Sistema productivo],"Chontaduro") -> 0 | H25: =COUNTIFS(Tabla_Proyectos[Departamentos],"*CAQUETA*",Tabla_Proyectos[Sistema productivo],"Guanábana") -> 0 | I25: =COUNTIFS(Tabla_Proyectos[Departamentos],"*CAQUETA*",Tabla_Proyectos[Sistema productivo],"Guayaba") -> 0 | J25: =COUNTIFS(Tabla_Proyectos[Departamentos],"*CAQUETA*",Tabla_Proyectos[Sistema productivo],"Naranjas") -> 0 | K25: =COUNTIFS(Tabla_Proyectos[Departamentos],"*CAQUETA*",Tabla_Proyectos[Sistema productivo],"Banano") -> 0
A26: CASANARE | B26: =COUNTIFS(Tabla_Proyectos[Departamentos],"*CASANARE*",Tabla_Proyectos[Sistema productivo],"Aguacate Hass") -> 0 | C26: =COUNTIFS(Tabla_Proyectos[Departamentos],"*CASANARE*",Tabla_Proyectos[Sistema productivo],"Lima Acida Tahití") -> 0 | D26: =COUNTIFS(Tabla_Proyectos[Departamentos],"*CASANARE*",Tabla_Proyectos[Sistema productivo],"Cacao") -> 0 | E26: =COUNTIFS(Tabla_Proyectos[Departamentos],"*CASANARE*",Tabla_Proyectos[Sistema productivo],"Piña") -> 0 | F26: =COUNTIFS(Tabla_Proyectos[Departamentos],"*CASANARE*",Tabla_Proyectos[Sistema productivo],"Platano") -> 0 | G26: =COUNTIFS(Tabla_Proyectos[Departamentos],"*CASANARE*",Tabla_Proyectos[Sistema productivo],"Chontaduro") -> 0 | H26: =COUNTIFS(Tabla_Proyectos[Departamentos],"*CASANARE*",Tabla_Proyectos[Sistema productivo],"Guanábana") -> 0 | I26: =COUNTIFS(Tabla_Proyectos[Departamentos],"*CASANARE*",Tabla_Proyectos[Sistema productivo],"Guayaba") -> 0 | J26: =COUNTIFS(Tabla_Proyectos[Departamentos],"*CASANARE*",Tabla_Proyectos[Sistema productivo],"Naranjas") -> 0 | K26: =COUNTIFS(Tabla_Proyectos[Departamentos],"*CASANARE*",Tabla_Proyectos[Sistema productivo],"Banano") -> 0
A27: CAUCA | B27: =COUNTIFS(Tabla_Proyectos[Departamentos],"*CAUCA*",Tabla_Proyectos[Sistema productivo],"Aguacate Hass") -> 4 | C27: =COUNTIFS(Tabla_Proyectos[Departamentos],"*CAUCA*",Tabla_Proyectos[Sistema productivo],"Lima Acida Tahití") -> 0 | D27: =COUNTIFS(Tabla_Proyectos[Departamentos],"*CAUCA*",Tabla_Proyectos[Sistema productivo],"Cacao") -> 1 | E27: =COUNTIFS(Tabla_Proyectos[Departamentos],"*CAUCA*",Tabla_Proyectos[Sistema productivo],"Piña") -> 1 | F27: =COUNTIFS(Tabla_Proyectos[Departamentos],"*CAUCA*",Tabla_Proyectos[Sistema productivo],"Platano") -> 1 | G27: =COUNTIFS(Tabla_Proyectos[Departamentos],"*CAUCA*",Tabla_Proyectos[Sistema productivo],"Chontaduro") -> 0 | H27: =COUNTIFS(Tabla_Proyectos[Departamentos],"*CAUCA*",Tabla_Proyectos[Sistema productivo],"Guanábana") -> 0 | I27: =COUNTIFS(Tabla_Proyectos[Departamentos],"*CAUCA*",Tabla_Proyectos[Sistema productivo],"Guayaba") -> 0 | J27: =COUNTIFS(Tabla_Proyectos[Departamentos],"*CAUCA*",Tabla_Proyectos[Sistema productivo],"Naranjas") -> 0 | K27: =COUNTIFS(Tabla_Proyectos[Departamentos],"*CAUCA*",Tabla_Proyectos[Sistema productivo],"Banano") -> 0
A28: CESAR | B28: =COUNTIFS(Tabla_Proyectos[Departamentos],"*CESAR*",Tabla_Proyectos[Sistema productivo],"Aguacate Hass") -> 0 | C28: =COUNTIFS(Tabla_Proyectos[Departamentos],"*CESAR*",Tabla_Proyectos[Sistema productivo],"Lima Acida Tahití") -> 0 | D28: =COUNTIFS(Tabla_Proyectos[Departamentos],"*CESAR*",Tabla_Proyectos[Sistema productivo],"Cacao") -> 0 | E28: =COUNTIFS(Tabla_Proyectos[Departamentos],"*CESAR*",Tabla_Proyectos[Sistema productivo],"Piña") -> 0 | F28: =COUNTIFS(Tabla_Proyectos[Departamentos],"*CESAR*",Tabla_Proyectos[Sistema productivo],"Platano") -> 0 | G28: =COUNTIFS(Tabla_Proyectos[Departamentos],"*CESAR*",Tabla_Proyectos[Sistema productivo],"Chontaduro") -> 0 | H28: =COUNTIFS(Tabla_Proyectos[Departamentos],"*CESAR*",Tabla_Proyectos[Sistema productivo],"Guanábana") -> 0 | I28: =COUNTIFS(Tabla_Proyectos[Departamentos],"*CESAR*",Tabla_Proyectos[Sistema productivo],"Guayaba") -> 0 | J28: =COUNTIFS(Tabla_Proyectos[Departamentos],"*CESAR*",Tabla_Proyectos[Sistema productivo],"Naranjas") -> 0 | K28: =COUNTIFS(Tabla_Proyectos[Departamentos],"*CESAR*",Tabla_Proyectos[Sistema productivo],"Banano") -> 0
A29: CHOCO | B29: =COUNTIFS(Tabla_Proyectos[Departamentos],"*CHOCO*",Tabla_Proyectos[Sistema productivo],"Aguacate Hass") -> 0 | C29: =COUNTIFS(Tabla_Proyectos[Departamentos],"*CHOCO*",Tabla_Proyectos[Sistema productivo],"Lima Acida Tahití") -> 0 | D29: =COUNTIFS(Tabla_Proyectos[Departamentos],"*CHOCO*",Tabla_Proyectos[Sistema productivo],"Cacao") -> 0 | E29: =COUNTIFS(Tabla_Proyectos[Departamentos],"*CHOCO*",Tabla_Proyectos[Sistema productivo],"Piña") -> 0 | F29: =COUNTIFS(Tabla_Proyectos[Departamentos],"*CHOCO*",Tabla_Proyectos[Sistema productivo],"Platano") -> 0 | G29: =COUNTIFS(Tabla_Proyectos[Departamentos],"*CHOCO*",Tabla_Proyectos[Sistema productivo],"Chontaduro") -> 0 | H29: =COUNTIFS(Tabla_Proyectos[Departamentos],"*CHOCO*",Tabla_Proyectos[Sistema productivo],"Guanábana") -> 0 | I29: =COUNTIFS(Tabla_Proyectos[Departamentos],"*CHOCO*",Tabla_Proyectos[Sistema productivo],"Guayaba") -> 0 | J29: =COUNTIFS(Tabla_Proyectos[Departamentos],"*CHOCO*",Tabla_Proyectos[Sistema productivo],"Naranjas") -> 0 | K29: =COUNTIFS(Tabla_Proyectos[Departamentos],"*CHOCO*",Tabla_Proyectos[Sistema productivo],"Banano") -> 0
A30: CORDOBA | B30: =COUNTIFS(Tabla_Proyectos[Departamentos],"*CORDOBA*",Tabla_Proyectos[Sistema productivo],"Aguacate Hass") -> 0 | C30: =COUNTIFS(Tabla_Proyectos[Departamentos],"*CORDOBA*",Tabla_Proyectos[Sistema productivo],"Lima Acida Tahití") -> 0 | D30: =COUNTIFS(Tabla_Proyectos[Departamentos],"*CORDOBA*",Tabla_Proyectos[Sistema productivo],"Cacao") -> 0 | E30: =COUNTIFS(Tabla_Proyectos[Departamentos],"*CORDOBA*",Tabla_Proyectos[Sistema productivo],"Piña") -> 0 | F30: =COUNTIFS(Tabla_Proyectos[Departamentos],"*CORDOBA*",Tabla_Proyectos[Sistema productivo],"Platano") -> 0 | G30: =COUNTIFS(Tabla_Proyectos[Departamentos],"*CORDOBA*",Tabla_Proyectos[Sistema productivo],"Chontaduro") -> 0 | H30: =COUNTIFS(Tabla_Proyectos[Departamentos],"*CORDOBA*",Tabla_Proyectos[Sistema productivo],"Guanábana") -> 0 | I30: =COUNTIFS(Tabla_Proyectos[Departamentos],"*CORDOBA*",Tabla_Proyectos[Sistema productivo],"Guayaba") -> 0 | J30: =COUNTIFS(Tabla_Proyectos[Departamentos],"*CORDOBA*",Tabla_Proyectos[Sistema productivo],"Naranjas") -> 0 | K30: =COUNTIFS(Tabla_Proyectos[Departamentos],"*CORDOBA*",Tabla_Proyectos[Sistema productivo],"Banano") -> 0
A31: CUNDINAMARCA | B31: =COUNTIFS(Tabla_Proyectos[Departamentos],"*CUNDINAMARCA*",Tabla_Proyectos[Sistema productivo],"Aguacate Hass") -> 0 | C31: =COUNTIFS(Tabla_Proyectos[Departamentos],"*CUNDINAMARCA*",Tabla_Proyectos[Sistema productivo],"Lima Acida Tahití") -> 0 | D31: =COUNTIFS(Tabla_Proyectos[Departamentos],"*CUNDINAMARCA*",Tabla_Proyectos[Sistema productivo],"Cacao") -> 0 | E31: =COUNTIFS(Tabla_Proyectos[Departamentos],"*CUNDINAMARCA*",Tabla_Proyectos[Sistema productivo],"Piña") -> 0 | F31: =COUNTIFS(Tabla_Proyectos[Departamentos],"*CUNDINAMARCA*",Tabla_Proyectos[Sistema productivo],"Platano") -> 0 | G31: =COUNTIFS(Tabla_Proyectos[Departamentos],"*CUNDINAMARCA*",Tabla_Proyectos[Sistema productivo],"Chontaduro") -> 0 | H31: =COUNTIFS(Tabla_Proyectos[Departamentos],"*CUNDINAMARCA*",Tabla_Proyectos[Sistema productivo],"Guanábana") -> 0 | I31: =COUNTIFS(Tabla_Proyectos[Departamentos],"*CUNDINAMARCA*",Tabla_Proyectos[Sistema productivo],"Guayaba") -> 0 | J31: =COUNTIFS(Tabla_Proyectos[Departamentos],"*CUNDINAMARCA*",Tabla_Proyectos[Sistema productivo],"Naranjas") -> 0 | K31: =COUNTIFS(Tabla_Proyectos[Departamentos],"*CUNDINAMARCA*",Tabla_Proyectos[Sistema productivo],"Banano") -> 0
A32: GUAINIA | B32: =COUNTIFS(Tabla_Proyectos[Departamentos],"*GUAINIA*",Tabla_Proyectos[Sistema productivo],"Aguacate Hass") -> 0 | C32: =COUNTIFS(Tabla_Proyectos[Departamentos],"*GUAINIA*",Tabla_Proyectos[Sistema productivo],"Lima Acida Tahití") -> 0 | D32: =COUNTIFS(Tabla_Proyectos[Departamentos],"*GUAINIA*",Tabla_Proyectos[Sistema productivo],"Cacao") -> 0 | E32: =COUNTIFS(Tabla_Proyectos[Departamentos],"*GUAINIA*",Tabla_Proyectos[Sistema productivo],"Piña") -> 0 | F32: =COUNTIFS(Tabla_Proyectos[Departamentos],"*GUAINIA*",Tabla_Proyectos[Sistema productivo],"Platano") -> 0 | G32: =COUNTIFS(Tabla_Proyectos[Departamentos],"*GUAINIA*",Tabla_Proyectos[Sistema productivo],"Chontaduro") -> 0 | H32: =COUNTIFS(Tabla_Proyectos[Departamentos],"*GUAINIA*",Tabla_Proyectos[Sistema productivo],"Guanábana") -> 0 | I32: =COUNTIFS(Tabla_Proyectos[Departamentos],"*GUAINIA*",Tabla_Proyectos[Sistema productivo],"Guayaba") -> 0 | J32: =COUNTIFS(Tabla_Proyectos[Departamentos],"*GUAINIA*",Tabla_Proyectos[Sistema productivo],"Naranjas") -> 0 | K32: =COUNTIFS(Tabla_Proyectos[Departamentos],"*GUAINIA*",Tabla_Proyectos[Sistema productivo],"Banano") -> 0
A33: GUAVÍARE | B33: =COUNTIFS(Tabla_Proyectos[Departamentos],"*GUAVÍARE*",Tabla_Proyectos[Sistema productivo],"Aguacate Hass") -> 0 | C33: =COUNTIFS(Tabla_Proyectos[Departamentos],"*GUAVÍARE*",Tabla_Proyectos[Sistema productivo],"Lima Acida Tahití") -> 0 | D33: =COUNTIFS(Tabla_Proyectos[Departamentos],"*GUAVÍARE*",Tabla_Proyectos[Sistema productivo],"Cacao") -> 0 | E33: =COUNTIFS(Tabla_Proyectos[Departamentos],"*GUAVÍARE*",Tabla_Proyectos[Sistema productivo],"Piña") -> 0 | F33: =COUNTIFS(Tabla_Proyectos[Departamentos],"*GUAVÍARE*",Tabla_Proyectos[Sistema productivo],"Platano") -> 0 | G33: =COUNTIFS(Tabla_Proyectos[Departamentos],"*GUAVÍARE*",Tabla_Proyectos[Sistema productivo],"Chontaduro") -> 0 | H33: =COUNTIFS(Tabla_Proyectos[Departamentos],"*GUAVÍARE*",Tabla_Proyectos[Sistema productivo],"Guanábana") -> 0 | I33: =COUNTIFS(Tabla_Proyectos[Departamentos],"*GUAVÍARE*",Tabla_Proyectos[Sistema productivo],"Guayaba") -> 0 | J33: =COUNTIFS(Tabla_Proyectos[Departamentos],"*GUAVÍARE*",Tabla_Proyectos[Sistema productivo],"Naranjas") -> 0 | K33: =COUNTIFS(Tabla_Proyectos[Departamentos],"*GUAVÍARE*",Tabla_Proyectos[Sistema productivo],"Banano") -> 0
A34: HUILA | B34: =COUNTIFS(Tabla_Proyectos[Departamentos],"*HUILA*",Tabla_Proyectos[Sistema productivo],"Aguacate Hass") -> 0 | C34: =COUNTIFS(Tabla_Proyectos[Departamentos],"*HUILA*",Tabla_Proyectos[Sistema productivo],"Lima Acida Tahití") -> 0 | D34: =COUNTIFS(Tabla_Proyectos[Departamentos],"*HUILA*",Tabla_Proyectos[Sistema productivo],"Cacao") -> 2 | E34: =COUNTIFS(Tabla_Proyectos[Departamentos],"*HUILA*",Tabla_Proyectos[Sistema productivo],"Piña") -> 0 | F34: =COUNTIFS(Tabla_Proyectos[Departamentos],"*HUILA*",Tabla_Proyectos[Sistema productivo],"Platano") -> 0 | G34: =COUNTIFS(Tabla_Proyectos[Departamentos],"*HUILA*",Tabla_Proyectos[Sistema productivo],"Chontaduro") -> 0 | H34: =COUNTIFS(Tabla_Proyectos[Departamentos],"*HUILA*",Tabla_Proyectos[Sistema productivo],"Guanábana") -> 0 | I34: =COUNTIFS(Tabla_Proyectos[Departamentos],"*HUILA*",Tabla_Proyectos[Sistema productivo],"Guayaba") -> 0 | J34: =COUNTIFS(Tabla_Proyectos[Departamentos],"*HUILA*",Tabla_Proyectos[Sistema productivo],"Naranjas") -> 0 | K34: =COUNTIFS(Tabla_Proyectos[Departamentos],"*HUILA*",Tabla_Proyectos[Sistema productivo],"Banano") -> 0
A35: LA GUAJIRA | B35: =COUNTIFS(Tabla_Proyectos[Departamentos],"*LA GUAJIRA*",Tabla_Proyectos[Sistema productivo],"Aguacate Hass") -> 0 | C35: =COUNTIFS(Tabla_Proyectos[Departamentos],"*LA GUAJIRA*",Tabla_Proyectos[Sistema productivo],"Lima Acida Tahití") -> 0 | D35: =COUNTIFS(Tabla_Proyectos[Departamentos],"*LA GUAJIRA*",Tabla_Proyectos[Sistema productivo],"Cacao") -> 0 | E35: =COUNTIFS(Tabla_Proyectos[Departamentos],"*LA GUAJIRA*",Tabla_Proyectos[Sistema productivo],"Piña") -> 0 | F35: =COUNTIFS(Tabla_Proyectos[Departamentos],"*LA GUAJIRA*",Tabla_Proyectos[Sistema productivo],"Platano") -> 0 | G35: =COUNTIFS(Tabla_Proyectos[Departamentos],"*LA GUAJIRA*",Tabla_Proyectos[Sistema productivo],"Chontaduro") -> 0 | H35: =COUNTIFS(Tabla_Proyectos[Departamentos],"*LA GUAJIRA*",Tabla_Proyectos[Sistema productivo],"Guanábana") -> 0 | I35: =COUNTIFS(Tabla_Proyectos[Departamentos],"*LA GUAJIRA*",Tabla_Proyectos[Sistema productivo],"Guayaba") -> 0 | J35: =COUNTIFS(Tabla_Proyectos[Departamentos],"*LA GUAJIRA*",Tabla_Proyectos[Sistema productivo],"Naranjas") -> 0 | K35: =COUNTIFS(Tabla_Proyectos[Departamentos],"*LA GUAJIRA*",Tabla_Proyectos[Sistema productivo],"Banano") -> 0
A36: MAGDALENA | B36: =COUNTIFS(Tabla_Proyectos[Departamentos],"*MAGDALENA*",Tabla_Proyectos[Sistema productivo],"Aguacate Hass") -> 0 | C36: =COUNTIFS(Tabla_Proyectos[Departamentos],"*MAGDALENA*",Tabla_Proyectos[Sistema productivo],"Lima Acida Tahití") -> 0 | D36: =COUNTIFS(Tabla_Proyectos[Departamentos],"*MAGDALENA*",Tabla_Proyectos[Sistema productivo],"Cacao") -> 0 | E36: =COUNTIFS(Tabla_Proyectos[Departamentos],"*MAGDALENA*",Tabla_Proyectos[Sistema productivo],"Piña") -> 0 | F36: =COUNTIFS(Tabla_Proyectos[Departamentos],"*MAGDALENA*",Tabla_Proyectos[Sistema productivo],"Platano") -> 0 | G36: =COUNTIFS(Tabla_Proyectos[Departamentos],"*MAGDALENA*",Tabla_Proyectos[Sistema productivo],"Chontaduro") -> 0 | H36: =COUNTIFS(Tabla_Proyectos[Departamentos],"*MAGDALENA*",Tabla_Proyectos[Sistema productivo],"Guanábana") -> 0 | I36: =COUNTIFS(Tabla_Proyectos[Departamentos],"*MAGDALENA*",Tabla_Proyectos[Sistema productivo],"Guayaba") -> 0 | J36: =COUNTIFS(Tabla_Proyectos[Departamentos],"*MAGDALENA*",Tabla_Proyectos[Sistema productivo],"Naranjas") -> 0 | K36: =COUNTIFS(Tabla_Proyectos[Departamentos],"*MAGDALENA*",Tabla_Proyectos[Sistema productivo],"Banano") -> 0
A37: META | B37: =COUNTIFS(Tabla_Proyectos[Departamentos],"*META*",Tabla_Proyectos[Sistema productivo],"Aguacate Hass") -> 0 | C37: =COUNTIFS(Tabla_Proyectos[Departamentos],"*META*",Tabla_Proyectos[Sistema productivo],"Lima Acida Tahití") -> 0 | D37: =COUNTIFS(Tabla_Proyectos[Departamentos],"*META*",Tabla_Proyectos[Sistema productivo],"Cacao") -> 0 | E37: =COUNTIFS(Tabla_Proyectos[Departamentos],"*META*",Tabla_Proyectos[Sistema productivo],"Piña") -> 0 | F37: =COUNTIFS(Tabla_Proyectos[Departamentos],"*META*",Tabla_Proyectos[Sistema productivo],"Platano") -> 0 | G37: =COUNTIFS(Tabla_Proyectos[Departamentos],"*META*",Tabla_Proyectos[Sistema productivo],"Chontaduro") -> 0 | H37: =COUNTIFS(Tabla_Proyectos[Departamentos],"*META*",Tabla_Proyectos[Sistema productivo],"Guanábana") -> 0 | I37: =COUNTIFS(Tabla_Proyectos[Departamentos],"*META*",Tabla_Proyectos[Sistema productivo],"Guayaba") -> 0 | J37: =COUNTIFS(Tabla_Proyectos[Departamentos],"*META*",Tabla_Proyectos[Sistema productivo],"Naranjas") -> 0 | K37: =COUNTIFS(Tabla_Proyectos[Departamentos],"*META*",Tabla_Proyectos[Sistema productivo],"Banano") -> 0
A38: NARIÑO | B38: =COUNTIFS(Tabla_Proyectos[Departamentos],"*NARIÑO*",Tabla_Proyectos[Sistema productivo],"Aguacate Hass") -> 0 | C38: =COUNTIFS(Tabla_Proyectos[Departamentos],"*NARIÑO*",Tabla_Proyectos[Sistema productivo],"Lima Acida Tahití") -> 0 | D38: =COUNTIFS(Tabla_Proyectos[Departamentos],"*NARIÑO*",Tabla_Proyectos[Sistema productivo],"Cacao") -> 0 | E38: =COUNTIFS(Tabla_Proyectos[Departamentos],"*NARIÑO*",Tabla_Proyectos[Sistema productivo],"Piña") -> 0 | F38: =COUNTIFS(Tabla_Proyectos[Departamentos],"*NARIÑO*",Tabla_Proyectos[Sistema productivo],"Platano") -> 0 | G38: =COUNTIFS(Tabla_Proyectos[Departamentos],"*NARIÑO*",Tabla_Proyectos[Sistema productivo],"Chontaduro") -> 0 | H38: =COUNTIFS(Tabla_Proyectos[Departamentos],"*NARIÑO*",Tabla_Proyectos[Sistema productivo],"Guanábana") -> 0 | I38: =COUNTIFS(Tabla_Proyectos[Departamentos],"*NARIÑO*",Tabla_Proyectos[Sistema productivo],"Guayaba") -> 0 | J38: =COUNTIFS(Tabla_Proyectos[Departamentos],"*NARIÑO*",Tabla_Proyectos[Sistema productivo],"Naranjas") -> 0 | K38: =COUNTIFS(Tabla_Proyectos[Departamentos],"*NARIÑO*",Tabla_Proyectos[Sistema productivo],"Banano") -> 0
A39: NORTE DE SANTANDER | B39: =COUNTIFS(Tabla_Proyectos[Departamentos],"*NORTE DE SANTANDER*",Tabla_Proyectos[Sistema productivo],"Aguacate Hass") -> 0 | C39: =COUNTIFS(Tabla_Proyectos[Departamentos],"*NORTE DE SANTANDER*",Tabla_Proyectos[Sistema productivo],"Lima Acida Tahití") -> 0 | D39: =COUNTIFS(Tabla_Proyectos[Departamentos],"*NORTE DE SANTANDER*",Tabla_Proyectos[Sistema productivo],"Cacao") -> 0 | E39: =COUNTIFS(Tabla_Proyectos[Departamentos],"*NORTE DE SANTANDER*",Tabla_Proyectos[Sistema productivo],"Piña") -> 0 | F39: =COUNTIFS(Tabla_Proyectos[Departamentos],"*NORTE DE SANTANDER*",Tabla_Proyectos[Sistema productivo],"Platano") -> 0 | G39: =COUNTIFS(Tabla_Proyectos[Departamentos],"*NORTE DE SANTANDER*",Tabla_Proyectos[Sistema productivo],"Chontaduro") -> 0 | H39: =COUNTIFS(Tabla_Proyectos[Departamentos],"*NORTE DE SANTANDER*",Tabla_Proyectos[Sistema productivo],"Guanábana") -> 0 | I39: =COUNTIFS(Tabla_Proyectos[Departamentos],"*NORTE DE SANTANDER*",Tabla_Proyectos[Sistema productivo],"Guayaba") -> 0 | J39: =COUNTIFS(Tabla_Proyectos[Departamentos],"*NORTE DE SANTANDER*",Tabla_Proyectos[Sistema productivo],"Naranjas") -> 0 | K39: =COUNTIFS(Tabla_Proyectos[Departamentos],"*NORTE DE SANTANDER*",Tabla_Proyectos[Sistema productivo],"Banano") -> 0
A40: PUTUMAYO | B40: =COUNTIFS(Tabla_Proyectos[Departamentos],"*PUTUMAYO*",Tabla_Proyectos[Sistema productivo],"Aguacate Hass") -> 0 | C40: =COUNTIFS(Tabla_Proyectos[Departamentos],"*PUTUMAYO*",Tabla_Proyectos[Sistema productivo],"Lima Acida Tahití") -> 0 | D40: =COUNTIFS(Tabla_Proyectos[Departamentos],"*PUTUMAYO*",Tabla_Proyectos[Sistema productivo],"Cacao") -> 0 | E40: =COUNTIFS(Tabla_Proyectos[Departamentos],"*PUTUMAYO*",Tabla_Proyectos[Sistema productivo],"Piña") -> 0 | F40: =COUNTIFS(Tabla_Proyectos[Departamentos],"*PUTUMAYO*",Tabla_Proyectos[Sistema productivo],"Platano") -> 0 | G40: =COUNTIFS(Tabla_Proyectos[Departamentos],"*PUTUMAYO*",Tabla_Proyectos[Sistema productivo],"Chontaduro") -> 0 | H40: =COUNTIFS(Tabla_Proyectos[Departamentos],"*PUTUMAYO*",Tabla_Proyectos[Sistema productivo],"Guanábana") -> 0 | I40: =COUNTIFS(Tabla_Proyectos[Departamentos],"*PUTUMAYO*",Tabla_Proyectos[Sistema productivo],"Guayaba") -> 0 | J40: =COUNTIFS(Tabla_Proyectos[Departamentos],"*PUTUMAYO*",Tabla_Proyectos[Sistema productivo],"Naranjas") -> 0 | K40: =COUNTIFS(Tabla_Proyectos[Departamentos],"*PUTUMAYO*",Tabla_Proyectos[Sistema productivo],"Banano") -> 0
A41: QUINDIO | B41: =COUNTIFS(Tabla_Proyectos[Departamentos],"*QUINDIO*",Tabla_Proyectos[Sistema productivo],"Aguacate Hass") -> 0 | C41: =COUNTIFS(Tabla_Proyectos[Departamentos],"*QUINDIO*",Tabla_Proyectos[Sistema productivo],"Lima Acida Tahití") -> 0 | D41: =COUNTIFS(Tabla_Proyectos[Departamentos],"*QUINDIO*",Tabla_Proyectos[Sistema productivo],"Cacao") -> 0 | E41: =COUNTIFS(Tabla_Proyectos[Departamentos],"*QUINDIO*",Tabla_Proyectos[Sistema productivo],"Piña") -> 0 | F41: =COUNTIFS(Tabla_Proyectos[Departamentos],"*QUINDIO*",Tabla_Proyectos[Sistema productivo],"Platano") -> 0 | G41: =COUNTIFS(Tabla_Proyectos[Departamentos],"*QUINDIO*",Tabla_Proyectos[Sistema productivo],"Chontaduro") -> 0 | H41: =COUNTIFS(Tabla_Proyectos[Departamentos],"*QUINDIO*",Tabla_Proyectos[Sistema productivo],"Guanábana") -> 0 | I41: =COUNTIFS(Tabla_Proyectos[Departamentos],"*QUINDIO*",Tabla_Proyectos[Sistema productivo],"Guayaba") -> 0 | J41: =COUNTIFS(Tabla_Proyectos[Departamentos],"*QUINDIO*",Tabla_Proyectos[Sistema productivo],"Naranjas") -> 0 | K41: =COUNTIFS(Tabla_Proyectos[Departamentos],"*QUINDIO*",Tabla_Proyectos[Sistema productivo],"Banano") -> 0
A42: RISARALDA | B42: =COUNTIFS(Tabla_Proyectos[Departamentos],"*RISARALDA*",Tabla_Proyectos[Sistema productivo],"Aguacate Hass") -> 1 | C42: =COUNTIFS(Tabla_Proyectos[Departamentos],"*RISARALDA*",Tabla_Proyectos[Sistema productivo],"Lima Acida Tahití") -> 0 | D42: =COUNTIFS(Tabla_Proyectos[Departamentos],"*RISARALDA*",Tabla_Proyectos[Sistema productivo],"Cacao") -> 0 | E42: =COUNTIFS(Tabla_Proyectos[Departamentos],"*RISARALDA*",Tabla_Proyectos[Sistema productivo],"Piña") -> 0 | F42: =COUNTIFS(Tabla_Proyectos[Departamentos],"*RISARALDA*",Tabla_Proyectos[Sistema productivo],"Platano") -> 1 | G42: =COUNTIFS(Tabla_Proyectos[Departamentos],"*RISARALDA*",Tabla_Proyectos[Sistema productivo],"Chontaduro") -> 0 | H42: =COUNTIFS(Tabla_Proyectos[Departamentos],"*RISARALDA*",Tabla_Proyectos[Sistema productivo],"Guanábana") -> 0 | I42: =COUNTIFS(Tabla_Proyectos[Departamentos],"*RISARALDA*",Tabla_Proyectos[Sistema productivo],"Guayaba") -> 0 | J42: =COUNTIFS(Tabla_Proyectos[Departamentos],"*RISARALDA*",Tabla_Proyectos[Sistema productivo],"Naranjas") -> 0 | K42: =COUNTIFS(Tabla_Proyectos[Departamentos],"*RISARALDA*",Tabla_Proyectos[Sistema productivo],"Banano") -> 0
A43: SANTANDER | B43: =COUNTIFS(Tabla_Proyectos[Departamentos],"*SANTANDER*",Tabla_Proyectos[Sistema productivo],"Aguacate Hass") -> 0 | C43: =COUNTIFS(Tabla_Proyectos[Departamentos],"*SANTANDER*",Tabla_Proyectos[Sistema productivo],"Lima Acida Tahití") -> 0 | D43: =COUNTIFS(Tabla_Proyectos[Departamentos],"*SANTANDER*",Tabla_Proyectos[Sistema productivo],"Cacao") -> 0 | E43: =COUNTIFS(Tabla_Proyectos[Departamentos],"*SANTANDER*",Tabla_Proyectos[Sistema productivo],"Piña") -> 0 | F43: =COUNTIFS(Tabla_Proyectos[Departamentos],"*SANTANDER*",Tabla_Proyectos[Sistema productivo],"Platano") -> 0 | G43: =COUNTIFS(Tabla_Proyectos[Departamentos],"*SANTANDER*",Tabla_Proyectos[Sistema productivo],"Chontaduro") -> 0 | H43: =COUNTIFS(Tabla_Proyectos[Departamentos],"*SANTANDER*",Tabla_Proyectos[Sistema productivo],"Guanábana") -> 0 | I43: =COUNTIFS(Tabla_Proyectos[Departamentos],"*SANTANDER*",Tabla_Proyectos[Sistema productivo],"Guayaba") -> 0 | J43: =COUNTIFS(Tabla_Proyectos[Departamentos],"*SANTANDER*",Tabla_Proyectos[Sistema productivo],"Naranjas") -> 0 | K43: =COUNTIFS(Tabla_Proyectos[Departamentos],"*SANTANDER*",Tabla_Proyectos[Sistema productivo],"Banano") -> 0
A44: SUCRE | B44: =COUNTIFS(Tabla_Proyectos[Departamentos],"*SUCRE*",Tabla_Proyectos[Sistema productivo],"Aguacate Hass") -> 0 | C44: =COUNTIFS(Tabla_Proyectos[Departamentos],"*SUCRE*",Tabla_Proyectos[Sistema productivo],"Lima Acida Tahití") -> 0 | D44: =COUNTIFS(Tabla_Proyectos[Departamentos],"*SUCRE*",Tabla_Proyectos[Sistema productivo],"Cacao") -> 0 | E44: =COUNTIFS(Tabla_Proyectos[Departamentos],"*SUCRE*",Tabla_Proyectos[Sistema productivo],"Piña") -> 0 | F44: =COUNTIFS(Tabla_Proyectos[Departamentos],"*SUCRE*",Tabla_Proyectos[Sistema productivo],"Platano") -> 0 | G44: =COUNTIFS(Tabla_Proyectos[Departamentos],"*SUCRE*",Tabla_Proyectos[Sistema productivo],"Chontaduro") -> 0 | H44: =COUNTIFS(Tabla_Proyectos[Departamentos],"*SUCRE*",Tabla_Proyectos[Sistema productivo],"Guanábana") -> 0 | I44: =COUNTIFS(Tabla_Proyectos[Departamentos],"*SUCRE*",Tabla_Proyectos[Sistema productivo],"Guayaba") -> 0 | J44: =COUNTIFS(Tabla_Proyectos[Departamentos],"*SUCRE*",Tabla_Proyectos[Sistema productivo],"Naranjas") -> 0 | K44: =COUNTIFS(Tabla_Proyectos[Departamentos],"*SUCRE*",Tabla_Proyectos[Sistema productivo],"Banano") -> 0
A45: TOLIMA | B45: =COUNTIFS(Tabla_Proyectos[Departamentos],"*TOLIMA*",Tabla_Proyectos[Sistema productivo],"Aguacate Hass") -> 4 | C45: =COUNTIFS(Tabla_Proyectos[Departamentos],"*TOLIMA*",Tabla_Proyectos[Sistema productivo],"Lima Acida Tahití") -> 0 | D45: =COUNTIFS(Tabla_Proyectos[Departamentos],"*TOLIMA*",Tabla_Proyectos[Sistema productivo],"Cacao") -> 2 | E45: =COUNTIFS(Tabla_Proyectos[Departamentos],"*TOLIMA*",Tabla_Proyectos[Sistema productivo],"Piña") -> 0 | F45: =COUNTIFS(Tabla_Proyectos[Departamentos],"*TOLIMA*",Tabla_Proyectos[Sistema productivo],"Platano") -> 0 | G45: =COUNTIFS(Tabla_Proyectos[Departamentos],"*TOLIMA*",Tabla_Proyectos[Sistema productivo],"Chontaduro") -> 0 | H45: =COUNTIFS(Tabla_Proyectos[Departamentos],"*TOLIMA*",Tabla_Proyectos[Sistema productivo],"Guanábana") -> 0 | I45: =COUNTIFS(Tabla_Proyectos[Departamentos],"*TOLIMA*",Tabla_Proyectos[Sistema productivo],"Guayaba") -> 0 | J45: =COUNTIFS(Tabla_Proyectos[Departamentos],"*TOLIMA*",Tabla_Proyectos[Sistema productivo],"Naranjas") -> 0 | K45: =COUNTIFS(Tabla_Proyectos[Departamentos],"*TOLIMA*",Tabla_Proyectos[Sistema productivo],"Banano") -> 0
A46: VALLE DEL CAUCA | B46: =COUNTIFS(Tabla_Proyectos[Departamentos],"*VALLE DEL CAUCA*",Tabla_Proyectos[Sistema productivo],"Aguacate Hass") -> 2 | C46: =COUNTIFS(Tabla_Proyectos[Departamentos],"*VALLE DEL CAUCA*",Tabla_Proyectos[Sistema productivo],"Lima Acida Tahití") -> 0 | D46: =COUNTIFS(Tabla_Proyectos[Departamentos],"*VALLE DEL CAUCA*",Tabla_Proyectos[Sistema productivo],"Cacao") -> 1 | E46: =COUNTIFS(Tabla_Proyectos[Departamentos],"*VALLE DEL CAUCA*",Tabla_Proyectos[Sistema productivo],"Piña") -> 0 | F46: =COUNTIFS(Tabla_Proyectos[Departamentos],"*VALLE DEL CAUCA*",Tabla_Proyectos[Sistema productivo],"Platano") -> 1 | G46: =COUNTIFS(Tabla_Proyectos[Departamentos],"*VALLE DEL CAUCA*",Tabla_Proyectos[Sistema productivo],"Chontaduro") -> 0 | H46: =COUNTIFS(Tabla_Proyectos[Departamentos],"*VALLE DEL CAUCA*",Tabla_Proyectos[Sistema productivo],"Guanábana") -> 0 | I46: =COUNTIFS(Tabla_Proyectos[Departamentos],"*VALLE DEL CAUCA*",Tabla_Proyectos[Sistema productivo],"Guayaba") -> 0 | J46: =COUNTIFS(Tabla_Proyectos[Departamentos],"*VALLE DEL CAUCA*",Tabla_Proyectos[Sistema productivo],"Naranjas") -> 0 | K46: =COUNTIFS(Tabla_Proyectos[Departamentos],"*VALLE DEL CAUCA*",Tabla_Proyectos[Sistema productivo],"Banano") -> 0
A47: VAUPÉS | B47: =COUNTIFS(Tabla_Proyectos[Departamentos],"*VAUPÉS*",Tabla_Proyectos[Sistema productivo],"Aguacate Hass") -> 0 | C47: =COUNTIFS(Tabla_Proyectos[Departamentos],"*VAUPÉS*",Tabla_Proyectos[Sistema productivo],"Lima Acida Tahití") -> 0 | D47: =COUNTIFS(Tabla_Proyectos[Departamentos],"*VAUPÉS*",Tabla_Proyectos[Sistema productivo],"Cacao") -> 0 | E47: =COUNTIFS(Tabla_Proyectos[Departamentos],"*VAUPÉS*",Tabla_Proyectos[Sistema productivo],"Piña") -> 0 | F47: =COUNTIFS(Tabla_Proyectos[Departamentos],"*VAUPÉS*",Tabla_Proyectos[Sistema productivo],"Platano") -> 0 | G47: =COUNTIFS(Tabla_Proyectos[Departamentos],"*VAUPÉS*",Tabla_Proyectos[Sistema productivo],"Chontaduro") -> 0 | H47: =COUNTIFS(Tabla_Proyectos[Departamentos],"*VAUPÉS*",Tabla_Proyectos[Sistema productivo],"Guanábana") -> 0 | I47: =COUNTIFS(Tabla_Proyectos[Departamentos],"*VAUPÉS*",Tabla_Proyectos[Sistema productivo],"Guayaba") -> 0 | J47: =COUNTIFS(Tabla_Proyectos[Departamentos],"*VAUPÉS*",Tabla_Proyectos[Sistema productivo],"Naranjas") -> 0 | K47: =COUNTIFS(Tabla_Proyectos[Departamentos],"*VAUPÉS*",Tabla_Proyectos[Sistema productivo],"Banano") -> 0
A48: VICHADA | B48: =COUNTIFS(Tabla_Proyectos[Departamentos],"*VICHADA*",Tabla_Proyectos[Sistema productivo],"Aguacate Hass") -> 0 | C48: =COUNTIFS(Tabla_Proyectos[Departamentos],"*VICHADA*",Tabla_Proyectos[Sistema productivo],"Lima Acida Tahití") -> 0 | D48: =COUNTIFS(Tabla_Proyectos[Departamentos],"*VICHADA*",Tabla_Proyectos[Sistema productivo],"Cacao") -> 0 | E48: =COUNTIFS(Tabla_Proyectos[Departamentos],"*VICHADA*",Tabla_Proyectos[Sistema productivo],"Piña") -> 0 | F48: =COUNTIFS(Tabla_Proyectos[Departamentos],"*VICHADA*",Tabla_Proyectos[Sistema productivo],"Platano") -> 0 | G48: =COUNTIFS(Tabla_Proyectos[Departamentos],"*VICHADA*",Tabla_Proyectos[Sistema productivo],"Chontaduro") -> 0 | H48: =COUNTIFS(Tabla_Proyectos[Departamentos],"*VICHADA*",Tabla_Proyectos[Sistema productivo],"Guanábana") -> 0 | I48: =COUNTIFS(Tabla_Proyectos[Departamentos],"*VICHADA*",Tabla_Proyectos[Sistema productivo],"Guayaba") -> 0 | J48: =COUNTIFS(Tabla_Proyectos[Departamentos],"*VICHADA*",Tabla_Proyectos[Sistema productivo],"Naranjas") -> 0 | K48: =COUNTIFS(Tabla_Proyectos[Departamentos],"*VICHADA*",Tabla_Proyectos[Sistema productivo],"Banano") -> 0

Sheet V2_Impacto_Demostrado
A1: Vista 2 — Impactos demostrados por el portafolio
A2: Esta vista consolida los proyectos que tienen impactos registrados (técnico, económico, social, ambiental). Se actualiza al completar la Capa 1.
A4: A. Proyectos con impactos registrados | E4: C. Proyectos con impacto social registrado × área temática
A5: Tipo de impacto | B5: Proyectos con dato | C5: % del portafolio | E5: Área temática | F5: Con impacto social
A6: Impacto técnico | B6: =COUNTA(Tabla_Proyectos[Impacto técnico]) -> 8 | C6: =IFERROR(B6/COUNTA(Tabla_Proyectos[Nombre del proyecto]),0) -> 0.060606061 | E6: Manejo sanitario y fitosanitario | F6: =COUNTIFS(Tabla_Proyectos[Área temática],"Manejo sanitario y fitosanitario",Tabla_Proyectos[Impacto social],"<>") -> 0
A7: Impacto económico | B7: =COUNTA(Tabla_Proyectos[Impacto económico]) -> 8 | C7: =IFERROR(B7/COUNTA(Tabla_Proyectos[Nombre del proyecto]),0) -> 0.060606061 | E7: Transf. de tecnologia, asist. técnica e innovación | F7: =COUNTIFS(Tabla_Proyectos[Área temática],"Transf. de tecnologia, asist. técnica e innovación",Tabla_Proyectos[Impacto social],"<>") -> 0
A8: Impacto social | B8: =COUNTA(Tabla_Proyectos[Impacto social]) -> 8 | C8: =IFERROR(B8/COUNTA(Tabla_Proyectos[Nombre del proyecto]),0) -> 0.060606061 | E8: Material de siembra y mejoramiento genético | F8: =COUNTIFS(Tabla_Proyectos[Área temática],"Material de siembra y mejoramiento genético",Tabla_Proyectos[Impacto social],"<>") -> 0
A9: Impacto ambiental | B9: =COUNTA(Tabla_Proyectos[Impacto ambiental]) -> 8 | C9: =IFERROR(B9/COUNTA(Tabla_Proyectos[Nombre del proyecto]),0) -> 0.060606061 | E9: Manejo ambiental y sostenibilidad | F9: =COUNTIFS(Tabla_Proyectos[Área temática],"Manejo ambiental y sostenibilidad",Tabla_Proyectos[Impacto social],"<>") -> 0
E10: Fisiología vegetal y nutrición | F10: =COUNTIFS(Tabla_Proyectos[Área temática],"Fisiología vegetal y nutrición",Tabla_Proyectos[Impacto social],"<>") -> 4
A11: B. Beneficiarios registrados por sistema productivo | E11: Manejo cosecha, poscosecha y transformación | F11: =COUNTIFS(Tabla_Proyectos[Área temática],"Manejo cosecha, poscosecha y transformación",Tabla_Proyectos[Impacto social],"<>") -> 4
A12: Sistema productivo | B12: Beneficiarios directos | C12: Beneficiarios indirectos | E12: Manejo de suelos y aguas | F12: =COUNTIFS(Tabla_Proyectos[Área temática],"Manejo de suelos y aguas",Tabla_Proyectos[Impacto social],"<>") -> 0
A13: Aguacate Hass | B13: =SUMIF(Tabla_Proyectos[Sistema productivo],"Aguacate Hass",Tabla_Proyectos[Beneficiarios directos]) -> 2444 | C13: =SUMIF(Tabla_Proyectos[Sistema productivo],"Aguacate Hass",Tabla_Proyectos[Beneficiarios indirectos]) -> 0 | E13: Manejo de sistemas productivos | F13: =COUNTIFS(Tabla_Proyectos[Área temática],"Manejo de sistemas productivos",Tabla_Proyectos[Impacto social],"<>") -> 0
A14: Lima Acida Tahití | B14: =SUMIF(Tabla_Proyectos[Sistema productivo],"Lima Acida Tahití",Tabla_Proyectos[Beneficiarios directos]) -> 0 | C14: =SUMIF(Tabla_Proyectos[Sistema productivo],"Lima Acida Tahití",Tabla_Proyectos[Beneficiarios indirectos]) -> 0 | E14: Calidad e inocuidad de insumos y productos | F14: =COUNTIFS(Tabla_Proyectos[Área temática],"Calidad e inocuidad de insumos y productos",Tabla_Proyectos[Impacto social],"<>") -> 0
A15: Cacao | B15: =SUMIF(Tabla_Proyectos[Sistema productivo],"Cacao",Tabla_Proyectos[Beneficiarios directos]) -> 0 | C15: =SUMIF(Tabla_Proyectos[Sistema productivo],"Cacao",Tabla_Proyectos[Beneficiarios indirectos]) -> 0
A16: Piña | B16: =SUMIF(Tabla_Proyectos[Sistema productivo],"Piña",Tabla_Proyectos[Beneficiarios directos]) -> 0 | C16: =SUMIF(Tabla_Proyectos[Sistema productivo],"Piña",Tabla_Proyectos[Beneficiarios indirectos]) -> 0
A17: Platano | B17: =SUMIF(Tabla_Proyectos[Sistema productivo],"Platano",Tabla_Proyectos[Beneficiarios directos]) -> 0 | C17: =SUMIF(Tabla_Proyectos[Sistema productivo],"Platano",Tabla_Proyectos[Beneficiarios indirectos]) -> 0
A18: Chontaduro | B18: =SUMIF(Tabla_Proyectos[Sistema productivo],"Chontaduro",Tabla_Proyectos[Beneficiarios directos]) -> 0 | C18: =SUMIF(Tabla_Proyectos[Sistema productivo],"Chontaduro",Tabla_Proyectos[Beneficiarios indirectos]) -> 0
A19: Guanábana | B19: =SUMIF(Tabla_Proyectos[Sistema productivo],"Guanábana",Tabla_Proyectos[Beneficiarios directos]) -> 0 | C19: =SUMIF(Tabla_Proyectos[Sistema productivo],"Guanábana",Tabla_Proyectos[Beneficiarios indirectos]) -> 0
A20: Guayaba | B20: =SUMIF(Tabla_Proyectos[Sistema productivo],"Guayaba",Tabla_Proyectos[Beneficiarios directos]) -> 0 | C20: =SUMIF(Tabla_Proyectos[Sistema productivo],"Guayaba",Tabla_Proyectos[Beneficiarios indirectos]) -> 0
A21: Naranjas | B21: =SUMIF(Tabla_Proyectos[Sistema productivo],"Naranjas",Tabla_Proyectos[Beneficiarios directos]) -> 0 | C21: =SUMIF(Tabla_Proyectos[Sistema productivo],"Naranjas",Tabla_Proyectos[Beneficiarios indirectos]) -> 0
A22: Banano | B22: =SUMIF(Tabla_Proyectos[Sistema productivo],"Banano",Tabla_Proyectos[Beneficiarios directos]) -> 0 | C22: =SUMIF(Tabla_Proyectos[Sistema productivo],"Banano",Tabla_Proyectos[Beneficiarios indirectos]) -> 0
A23: Maiz | B23: =SUMIF(Tabla_Proyectos[Sistema productivo],"Maiz",Tabla_Proyectos[Beneficiarios directos]) -> 0 | C23: =SUMIF(Tabla_Proyectos[Sistema productivo],"Maiz",Tabla_Proyectos[Beneficiarios indirectos]) -> 0
A24: Frijol | B24: =SUMIF(Tabla_Proyectos[Sistema productivo],"Frijol",Tabla_Proyectos[Beneficiarios directos]) -> 0 | C24: =SUMIF(Tabla_Proyectos[Sistema productivo],"Frijol",Tabla_Proyectos[Beneficiarios indirectos]) -> 0
A25: Cebolla | B25: =SUMIF(Tabla_Proyectos[Sistema productivo],"Cebolla",Tabla_Proyectos[Beneficiarios directos]) -> 0 | C25: =SUMIF(Tabla_Proyectos[Sistema productivo],"Cebolla",Tabla_Proyectos[Beneficiarios indirectos]) -> 0
A26: Yuca | B26: =SUMIF(Tabla_Proyectos[Sistema productivo],"Yuca",Tabla_Proyectos[Beneficiarios directos]) -> 300 | C26: =SUMIF(Tabla_Proyectos[Sistema productivo],"Yuca",Tabla_Proyectos[Beneficiarios indirectos]) -> 0
A27: Ganaderia | B27: =SUMIF(Tabla_Proyectos[Sistema productivo],"Ganaderia ",Tabla_Proyectos[Beneficiarios directos]) -> 0 | C27: =SUMIF(Tabla_Proyectos[Sistema productivo],"Ganaderia ",Tabla_Proyectos[Beneficiarios indirectos]) -> 0
A28: Apicola | B28: =SUMIF(Tabla_Proyectos[Sistema productivo],"Apicola",Tabla_Proyectos[Beneficiarios directos]) -> 0 | C28: =SUMIF(Tabla_Proyectos[Sistema productivo],"Apicola",Tabla_Proyectos[Beneficiarios indirectos]) -> 0
A29: Maracuya | B29: =SUMIF(Tabla_Proyectos[Sistema productivo],"Maracuya",Tabla_Proyectos[Beneficiarios directos]) -> 0 | C29: =SUMIF(Tabla_Proyectos[Sistema productivo],"Maracuya",Tabla_Proyectos[Beneficiarios indirectos]) -> 0
A30: Ají | B30: =SUMIF(Tabla_Proyectos[Sistema productivo],"Ají",Tabla_Proyectos[Beneficiarios directos]) -> 0 | C30: =SUMIF(Tabla_Proyectos[Sistema productivo],"Ají",Tabla_Proyectos[Beneficiarios indirectos]) -> 0
A31: Forestal | B31: =SUMIF(Tabla_Proyectos[Sistema productivo],"Forestal",Tabla_Proyectos[Beneficiarios directos]) -> 0 | C31: =SUMIF(Tabla_Proyectos[Sistema productivo],"Forestal",Tabla_Proyectos[Beneficiarios indirectos]) -> 0
A32: Quinua | B32: =SUMIF(Tabla_Proyectos[Sistema productivo],"Quinua",Tabla_Proyectos[Beneficiarios directos]) -> 0 | C32: =SUMIF(Tabla_Proyectos[Sistema productivo],"Quinua",Tabla_Proyectos[Beneficiarios indirectos]) -> 0
A33: Caña panelera | B33: =SUMIF(Tabla_Proyectos[Sistema productivo],"Caña panelera",Tabla_Proyectos[Beneficiarios directos]) -> 0 | C33: =SUMIF(Tabla_Proyectos[Sistema productivo],"Caña panelera",Tabla_Proyectos[Beneficiarios indirectos]) -> 0
A34: Fique | B34: =SUMIF(Tabla_Proyectos[Sistema productivo],"Fique",Tabla_Proyectos[Beneficiarios directos]) -> 0 | C34: =SUMIF(Tabla_Proyectos[Sistema productivo],"Fique",Tabla_Proyectos[Beneficiarios indirectos]) -> 0
A35: Limón Pajarito | B35: =SUMIF(Tabla_Proyectos[Sistema productivo],"Limón Pajarito",Tabla_Proyectos[Beneficiarios directos]) -> 0 | C35: =SUMIF(Tabla_Proyectos[Sistema productivo],"Limón Pajarito",Tabla_Proyectos[Beneficiarios indirectos]) -> 0
A36: Mora | B36: =SUMIF(Tabla_Proyectos[Sistema productivo],"Mora",Tabla_Proyectos[Beneficiarios directos]) -> 0 | C36: =SUMIF(Tabla_Proyectos[Sistema productivo],"Mora",Tabla_Proyectos[Beneficiarios indirectos]) -> 0
A37: Melón | B37: =SUMIF(Tabla_Proyectos[Sistema productivo],"Melón",Tabla_Proyectos[Beneficiarios directos]) -> 0 | C37: =SUMIF(Tabla_Proyectos[Sistema productivo],"Melón",Tabla_Proyectos[Beneficiarios indirectos]) -> 0
A38: Palma de aceite Americana | B38: =SUMIF(Tabla_Proyectos[Sistema productivo],"Palma de aceite Americana",Tabla_Proyectos[Beneficiarios directos]) -> 0 | C38: =SUMIF(Tabla_Proyectos[Sistema productivo],"Palma de aceite Americana",Tabla_Proyectos[Beneficiarios indirectos]) -> 0
A39: Palma de aceite Africana | B39: =SUMIF(Tabla_Proyectos[Sistema productivo],"Palma de aceite Africana",Tabla_Proyectos[Beneficiarios directos]) -> 0 | C39: =SUMIF(Tabla_Proyectos[Sistema productivo],"Palma de aceite Africana",Tabla_Proyectos[Beneficiarios indirectos]) -> 0
A40: Bancos de Germoplasma | B40: =SUMIF(Tabla_Proyectos[Sistema productivo],"Bancos de Germoplasma",Tabla_Proyectos[Beneficiarios directos]) -> 0 | C40: =SUMIF(Tabla_Proyectos[Sistema productivo],"Bancos de Germoplasma",Tabla_Proyectos[Beneficiarios indirectos]) -> 0
A41: Agraz | B41: =SUMIF(Tabla_Proyectos[Sistema productivo],"Agraz",Tabla_Proyectos[Beneficiarios directos]) -> 0 | C41: =SUMIF(Tabla_Proyectos[Sistema productivo],"Agraz",Tabla_Proyectos[Beneficiarios indirectos]) -> 0
A42: Pitaya Amarilla | B42: =SUMIF(Tabla_Proyectos[Sistema productivo],"Pitaya Amarilla",Tabla_Proyectos[Beneficiarios directos]) -> 0 | C42: =SUMIF(Tabla_Proyectos[Sistema productivo],"Pitaya Amarilla",Tabla_Proyectos[Beneficiarios indirectos]) -> 0
A43: Palmaceas | B43: =SUMIF(Tabla_Proyectos[Sistema productivo],"Palmaceas",Tabla_Proyectos[Beneficiarios directos]) -> 0 | C43: =SUMIF(Tabla_Proyectos[Sistema productivo],"Palmaceas",Tabla_Proyectos[Beneficiarios indirectos]) -> 0
A44: Coco | B44: =SUMIF(Tabla_Proyectos[Sistema productivo],"Coco",Tabla_Proyectos[Beneficiarios directos]) -> 0 | C44: =SUMIF(Tabla_Proyectos[Sistema productivo],"Coco",Tabla_Proyectos[Beneficiarios indirectos]) -> 0
A45: Otro | B45: =SUMIF(Tabla_Proyectos[Sistema productivo],"Otro",Tabla_Proyectos[Beneficiarios directos]) -> 0 | C45: =SUMIF(Tabla_Proyectos[Sistema productivo],"Otro",Tabla_Proyectos[Beneficiarios indirectos]) -> 0
A46: TOTAL | B46: =SUM(B13:B45) -> 2744 | C46: =SUM(C13:C45) -> 0
A48: D. Recursos movilizados (suma de montos registrados)
A49: Indicador | B49: Valor | C49: Nota
A50: Total proyectos con monto registrado | B50: =COUNTA(Tabla_Proyectos[Monto del proyecto]) -> 7 | C50: Proyectos
A51: Suma total de montos registrados (COP) | B51: =IFERROR(SUM(Tabla_Proyectos[Monto del proyecto]),0) -> 30093566725 | C51: Se completa al diligenciar campo Monto
A52: Monto promedio por proyecto (COP) | B52: =IFERROR(B51/B50,0) -> 4.299081e+09 | C52: Solo proyectos con monto registrado

Sheet V3_Trayectoria_TRL
A1: Vista 3 — Trayectoria tecnológica (niveles TRL)
A2: TRL: Technology Readiness Level (1=idea básica → 9=tecnología adoptada). Muestra dónde inician y terminan los proyectos. Se activa al completar TRL inicial y final en Capa 1.
A4: A. Escala TRL de referencia | E4: B. Distribución TRL final por sistema productivo
A5: Nivel TRL | B5: Categoría | C5: Descripción | E5: Sistema productivo | F5: TRL 1 | G5: TRL 2 | H5: TRL 3 | I5: TRL 4 | J5: TRL 5 | K5: TRL 6 | L5: TRL 7 | M5: TRL 8 | N5: TRL 9
A6: TRL 1 | B6: Investigación básica | C6: Principios científicos observados | E6: Aguacate Hass | F6: =COUNTIFS(Tabla_Proyectos[Sistema productivo],"Aguacate Hass",Tabla_Proyectos[TRL final],"1") -> 0 | G6: =COUNTIFS(Tabla_Proyectos[Sistema productivo],"Aguacate Hass",Tabla_Proyectos[TRL final],"2") -> 0 | H6: =COUNTIFS(Tabla_Proyectos[Sistema productivo],"Aguacate Hass",Tabla_Proyectos[TRL final],"3") -> 0 | I6: =COUNTIFS(Tabla_Proyectos[Sistema productivo],"Aguacate Hass",Tabla_Proyectos[TRL final],"4") -> 0 | J6: =COUNTIFS(Tabla_Proyectos[Sistema productivo],"Aguacate Hass",Tabla_Proyectos[TRL final],"5") -> 1 | K6: =COUNTIFS(Tabla_Proyectos[Sistema productivo],"Aguacate Hass",Tabla_Proyectos[TRL final],"6") -> 0 | L6: =COUNTIFS(Tabla_Proyectos[Sistema productivo],"Aguacate Hass",Tabla_Proyectos[TRL final],"7") -> 1 | M6: =COUNTIFS(Tabla_Proyectos[Sistema productivo],"Aguacate Hass",Tabla_Proyectos[TRL final],"8") -> 1 | N6: =COUNTIFS(Tabla_Proyectos[Sistema productivo],"Aguacate Hass",Tabla_Proyectos[TRL final],"9") -> 0
A7: TRL 2 | B7: Concepto formulado | C7: Concepto tecnológico formulado | E7: Lima Acida Tahití | F7: =COUNTIFS(Tabla_Proyectos[Sistema productivo],"Lima Acida Tahití",Tabla_Proyectos[TRL final],"1") -> 0 | G7: =COUNTIFS(Tabla_Proyectos[Sistema productivo],"Lima Acida Tahití",Tabla_Proyectos[TRL final],"2") -> 0 | H7: =COUNTIFS(Tabla_Proyectos[Sistema productivo],"Lima Acida Tahití",Tabla_Proyectos[TRL final],"3") -> 0 | I7: =COUNTIFS(Tabla_Proyectos[Sistema productivo],"Lima Acida Tahití",Tabla_Proyectos[TRL final],"4") -> 0 | J7: =COUNTIFS(Tabla_Proyectos[Sistema productivo],"Lima Acida Tahití",Tabla_Proyectos[TRL final],"5") -> 0 | K7: =COUNTIFS(Tabla_Proyectos[Sistema productivo],"Lima Acida Tahití",Tabla_Proyectos[TRL final],"6") -> 0 | L7: =COUNTIFS(Tabla_Proyectos[Sistema productivo],"Lima Acida Tahití",Tabla_Proyectos[TRL final],"7") -> 0 | M7: =COUNTIFS(Tabla_Proyectos[Sistema productivo],"Lima Acida Tahití",Tabla_Proyectos[TRL final],"8") -> 0 | N7: =COUNTIFS(Tabla_Proyectos[Sistema productivo],"Lima Acida Tahití",Tabla_Proyectos[TRL final],"9") -> 0
A8: TRL 3 | B8: Prueba de concepto | C8: Demostración experimental en laboratorio | E8: Cacao | F8: =COUNTIFS(Tabla_Proyectos[Sistema productivo],"Cacao",Tabla_Proyectos[TRL final],"1") -> 0 | G8: =COUNTIFS(Tabla_Proyectos[Sistema productivo],"Cacao",Tabla_Proyectos[TRL final],"2") -> 0 | H8: =COUNTIFS(Tabla_Proyectos[Sistema productivo],"Cacao",Tabla_Proyectos[TRL final],"3") -> 0 | I8: =COUNTIFS(Tabla_Proyectos[Sistema productivo],"Cacao",Tabla_Proyectos[TRL final],"4") -> 0 | J8: =COUNTIFS(Tabla_Proyectos[Sistema productivo],"Cacao",Tabla_Proyectos[TRL final],"5") -> 1 | K8: =COUNTIFS(Tabla_Proyectos[Sistema productivo],"Cacao",Tabla_Proyectos[TRL final],"6") -> 2 | L8: =COUNTIFS(Tabla_Proyectos[Sistema productivo],"Cacao",Tabla_Proyectos[TRL final],"7") -> 1 | M8: =COUNTIFS(Tabla_Proyectos[Sistema productivo],"Cacao",Tabla_Proyectos[TRL final],"8") -> 0 | N8: =COUNTIFS(Tabla_Proyectos[Sistema productivo],"Cacao",Tabla_Proyectos[TRL final],"9") -> 0
A9: TRL 4 | B9: Validación en laboratorio | C9: Componentes validados en condiciones controladas | E9: Piña | F9: =COUNTIFS(Tabla_Proyectos[Sistema productivo],"Piña",Tabla_Proyectos[TRL final],"1") -> 0 | G9: =COUNTIFS(Tabla_Proyectos[Sistema productivo],"Piña",Tabla_Proyectos[TRL final],"2") -> 0 | H9: =COUNTIFS(Tabla_Proyectos[Sistema productivo],"Piña",Tabla_Proyectos[TRL final],"3") -> 0 | I9: =COUNTIFS(Tabla_Proyectos[Sistema productivo],"Piña",Tabla_Proyectos[TRL final],"4") -> 0 | J9: =COUNTIFS(Tabla_Proyectos[Sistema productivo],"Piña",Tabla_Proyectos[TRL final],"5") -> 0 | K9: =COUNTIFS(Tabla_Proyectos[Sistema productivo],"Piña",Tabla_Proyectos[TRL final],"6") -> 0 | L9: =COUNTIFS(Tabla_Proyectos[Sistema productivo],"Piña",Tabla_Proyectos[TRL final],"7") -> 0 | M9: =COUNTIFS(Tabla_Proyectos[Sistema productivo],"Piña",Tabla_Proyectos[TRL final],"8") -> 0 | N9: =COUNTIFS(Tabla_Proyectos[Sistema productivo],"Piña",Tabla_Proyectos[TRL final],"9") -> 0
A10: TRL 5 | B10: Validación relevante | C10: Componentes validados en condiciones relevantes | E10: Platano | F10: =COUNTIFS(Tabla_Proyectos[Sistema productivo],"Platano",Tabla_Proyectos[TRL final],"1") -> 0 | G10: =COUNTIFS(Tabla_Proyectos[Sistema productivo],"Platano",Tabla_Proyectos[TRL final],"2") -> 0 | H10: =COUNTIFS(Tabla_Proyectos[Sistema productivo],"Platano",Tabla_Proyectos[TRL final],"3") -> 0 | I10: =COUNTIFS(Tabla_Proyectos[Sistema productivo],"Platano",Tabla_Proyectos[TRL final],"4") -> 0 | J10: =COUNTIFS(Tabla_Proyectos[Sistema productivo],"Platano",Tabla_Proyectos[TRL final],"5") -> 0 | K10: =COUNTIFS(Tabla_Proyectos[Sistema productivo],"Platano",Tabla_Proyectos[TRL final],"6") -> 0 | L10: =COUNTIFS(Tabla_Proyectos[Sistema productivo],"Platano",Tabla_Proyectos[TRL final],"7") -> 0 | M10: =COUNTIFS(Tabla_Proyectos[Sistema productivo],"Platano",Tabla_Proyectos[TRL final],"8") -> 0 | N10: =COUNTIFS(Tabla_Proyectos[Sistema productivo],"Platano",Tabla_Proyectos[TRL final],"9") -> 0
A11: TRL 6 | B11: Demostración relevante | C11: Prototipo demostrado en condiciones relevantes | E11: Chontaduro | F11: =COUNTIFS(Tabla_Proyectos[Sistema productivo],"Chontaduro",Tabla_Proyectos[TRL final],"1") -> 0 | G11: =COUNTIFS(Tabla_Proyectos[Sistema productivo],"Chontaduro",Tabla_Proyectos[TRL final],"2") -> 0 | H11: =COUNTIFS(Tabla_Proyectos[Sistema productivo],"Chontaduro",Tabla_Proyectos[TRL final],"3") -> 0 | I11: =COUNTIFS(Tabla_Proyectos[Sistema productivo],"Chontaduro",Tabla_Proyectos[TRL final],"4") -> 0 | J11: =COUNTIFS(Tabla_Proyectos[Sistema productivo],"Chontaduro",Tabla_Proyectos[TRL final],"5") -> 0 | K11: =COUNTIFS(Tabla_Proyectos[Sistema productivo],"Chontaduro",Tabla_Proyectos[TRL final],"6") -> 0 | L11: =COUNTIFS(Tabla_Proyectos[Sistema productivo],"Chontaduro",Tabla_Proyectos[TRL final],"7") -> 0 | M11: =COUNTIFS(Tabla_Proyectos[Sistema productivo],"Chontaduro",Tabla_Proyectos[TRL final],"8") -> 0 | N11: =COUNTIFS(Tabla_Proyectos[Sistema productivo],"Chontaduro",Tabla_Proyectos[TRL final],"9") -> 0
A12: TRL 7 | B12: Demostración en campo | C12: Sistema demostrado en condiciones reales | E12: Guanábana | F12: =COUNTIFS(Tabla_Proyectos[Sistema productivo],"Guanábana",Tabla_Proyectos[TRL final],"1") -> 0 | G12: =COUNTIFS(Tabla_Proyectos[Sistema productivo],"Guanábana",Tabla_Proyectos[TRL final],"2") -> 0 | H12: =COUNTIFS(Tabla_Proyectos[Sistema productivo],"Guanábana",Tabla_Proyectos[TRL final],"3") -> 0 | I12: =COUNTIFS(Tabla_Proyectos[Sistema productivo],"Guanábana",Tabla_Proyectos[TRL final],"4") -> 0 | J12: =COUNTIFS(Tabla_Proyectos[Sistema productivo],"Guanábana",Tabla_Proyectos[TRL final],"5") -> 0 | K12: =COUNTIFS(Tabla_Proyectos[Sistema productivo],"Guanábana",Tabla_Proyectos[TRL final],"6") -> 0 | L12: =COUNTIFS(Tabla_Proyectos[Sistema productivo],"Guanábana",Tabla_Proyectos[TRL final],"7") -> 0 | M12: =COUNTIFS(Tabla_Proyectos[Sistema productivo],"Guanábana",Tabla_Proyectos[TRL final],"8") -> 0 | N12: =COUNTIFS(Tabla_Proyectos[Sistema productivo],"Guanábana",Tabla_Proyectos[TRL final],"9") -> 0
A13: TRL 8 | B13: Completado y calificado | C13: Sistema completo y calificado | E13: Guayaba | F13: =COUNTIFS(Tabla_Proyectos[Sistema productivo],"Guayaba",Tabla_Proyectos[TRL final],"1") -> 0 | G13: =COUNTIFS(Tabla_Proyectos[Sistema productivo],"Guayaba",Tabla_Proyectos[TRL final],"2") -> 0 | H13: =COUNTIFS(Tabla_Proyectos[Sistema productivo],"Guayaba",Tabla_Proyectos[TRL final],"3") -> 0 | I13: =COUNTIFS(Tabla_Proyectos[Sistema productivo],"Guayaba",Tabla_Proyectos[TRL final],"4") -> 0 | J13: =COUNTIFS(Tabla_Proyectos[Sistema productivo],"Guayaba",Tabla_Proyectos[TRL final],"5") -> 0 | K13: =COUNTIFS(Tabla_Proyectos[Sistema productivo],"Guayaba",Tabla_Proyectos[TRL final],"6") -> 0 | L13: =COUNTIFS(Tabla_Proyectos[Sistema productivo],"Guayaba",Tabla_Proyectos[TRL final],"7") -> 0 | M13: =COUNTIFS(Tabla_Proyectos[Sistema productivo],"Guayaba",Tabla_Proyectos[TRL final],"8") -> 0 | N13: =COUNTIFS(Tabla_Proyectos[Sistema productivo],"Guayaba",Tabla_Proyectos[TRL final],"9") -> 0
A14: TRL 9 | B14: Adopción exitosa | C14: Sistema adoptado exitosamente | E14: Naranjas | F14: =COUNTIFS(Tabla_Proyectos[Sistema productivo],"Naranjas",Tabla_Proyectos[TRL final],"1") -> 0 | G14: =COUNTIFS(Tabla_Proyectos[Sistema productivo],"Naranjas",Tabla_Proyectos[TRL final],"2") -> 0 | H14: =COUNTIFS(Tabla_Proyectos[Sistema productivo],"Naranjas",Tabla_Proyectos[TRL final],"3") -> 0 | I14: =COUNTIFS(Tabla_Proyectos[Sistema productivo],"Naranjas",Tabla_Proyectos[TRL final],"4") -> 0 | J14: =COUNTIFS(Tabla_Proyectos[Sistema productivo],"Naranjas",Tabla_Proyectos[TRL final],"5") -> 0 | K14: =COUNTIFS(Tabla_Proyectos[Sistema productivo],"Naranjas",Tabla_Proyectos[TRL final],"6") -> 0 | L14: =COUNTIFS(Tabla_Proyectos[Sistema productivo],"Naranjas",Tabla_Proyectos[TRL final],"7") -> 0 | M14: =COUNTIFS(Tabla_Proyectos[Sistema productivo],"Naranjas",Tabla_Proyectos[TRL final],"8") -> 0 | N14: =COUNTIFS(Tabla_Proyectos[Sistema productivo],"Naranjas",Tabla_Proyectos[TRL final],"9") -> 0
E15: Banano | F15: =COUNTIFS(Tabla_Proyectos[Sistema productivo],"Banano",Tabla_Proyectos[TRL final],"1") -> 0 | G15: =COUNTIFS(Tabla_Proyectos[Sistema productivo],"Banano",Tabla_Proyectos[TRL final],"2") -> 0 | H15: =COUNTIFS(Tabla_Proyectos[Sistema productivo],"Banano",Tabla_Proyectos[TRL final],"3") -> 0 | I15: =COUNTIFS(Tabla_Proyectos[Sistema productivo],"Banano",Tabla_Proyectos[TRL final],"4") -> 0 | J15: =COUNTIFS(Tabla_Proyectos[Sistema productivo],"Banano",Tabla_Proyectos[TRL final],"5") -> 0 | K15: =COUNTIFS(Tabla_Proyectos[Sistema productivo],"Banano",Tabla_Proyectos[TRL final],"6") -> 0 | L15: =COUNTIFS(Tabla_Proyectos[Sistema productivo],"Banano",Tabla_Proyectos[TRL final],"7") -> 0 | M15: =COUNTIFS(Tabla_Proyectos[Sistema productivo],"Banano",Tabla_Proyectos[TRL final],"8") -> 0 | N15: =COUNTIFS(Tabla_Proyectos[Sistema productivo],"Banano",Tabla_Proyectos[TRL final],"9") -> 0
E16: Maiz | F16: =COUNTIFS(Tabla_Proyectos[Sistema productivo],"Maiz",Tabla_Proyectos[TRL final],"1") -> 0 | G16: =COUNTIFS(Tabla_Proyectos[Sistema productivo],"Maiz",Tabla_Proyectos[TRL final],"2") -> 0 | H16: =COUNTIFS(Tabla_Proyectos[Sistema productivo],"Maiz",Tabla_Proyectos[TRL final],"3") -> 0 | I16: =COUNTIFS(Tabla_Proyectos[Sistema productivo],"Maiz",Tabla_Proyectos[TRL final],"4") -> 0 | J16: =COUNTIFS(Tabla_Proyectos[Sistema productivo],"Maiz",Tabla_Proyectos[TRL final],"5") -> 0 | K16: =COUNTIFS(Tabla_Proyectos[Sistema productivo],"Maiz",Tabla_Proyectos[TRL final],"6") -> 0 | L16: =COUNTIFS(Tabla_Proyectos[Sistema productivo],"Maiz",Tabla_Proyectos[TRL final],"7") -> 0 | M16: =COUNTIFS(Tabla_Proyectos[Sistema productivo],"Maiz",Tabla_Proyectos[TRL final],"8") -> 0 | N16: =COUNTIFS(Tabla_Proyectos[Sistema productivo],"Maiz",Tabla_Proyectos[TRL final],"9") -> 0
E17: Frijol | F17: =COUNTIFS(Tabla_Proyectos[Sistema productivo],"Frijol",Tabla_Proyectos[TRL final],"1") -> 0 | G17: =COUNTIFS(Tabla_Proyectos[Sistema productivo],"Frijol",Tabla_Proyectos[TRL final],"2") -> 0 | H17: =COUNTIFS(Tabla_Proyectos[Sistema productivo],"Frijol",Tabla_Proyectos[TRL final],"3") -> 0 | I17: =COUNTIFS(Tabla_Proyectos[Sistema productivo],"Frijol",Tabla_Proyectos[TRL final],"4") -> 0 | J17: =COUNTIFS(Tabla_Proyectos[Sistema productivo],"Frijol",Tabla_Proyectos[TRL final],"5") -> 0 | K17: =COUNTIFS(Tabla_Proyectos[Sistema productivo],"Frijol",Tabla_Proyectos[TRL final],"6") -> 0 | L17: =COUNTIFS(Tabla_Proyectos[Sistema productivo],"Frijol",Tabla_Proyectos[TRL final],"7") -> 0 | M17: =COUNTIFS(Tabla_Proyectos[Sistema productivo],"Frijol",Tabla_Proyectos[TRL final],"8") -> 0 | N17: =COUNTIFS(Tabla_Proyectos[Sistema productivo],"Frijol",Tabla_Proyectos[TRL final],"9") -> 0
E18: Cebolla | F18: =COUNTIFS(Tabla_Proyectos[Sistema productivo],"Cebolla",Tabla_Proyectos[TRL final],"1") -> 0 | G18: =COUNTIFS(Tabla_Proyectos[Sistema productivo],"Cebolla",Tabla_Proyectos[TRL final],"2") -> 0 | H18: =COUNTIFS(Tabla_Proyectos[Sistema productivo],"Cebolla",Tabla_Proyectos[TRL final],"3") -> 0 | I18: =COUNTIFS(Tabla_Proyectos[Sistema productivo],"Cebolla",Tabla_Proyectos[TRL final],"4") -> 0 | J18: =COUNTIFS(Tabla_Proyectos[Sistema productivo],"Cebolla",Tabla_Proyectos[TRL final],"5") -> 0 | K18: =COUNTIFS(Tabla_Proyectos[Sistema productivo],"Cebolla",Tabla_Proyectos[TRL final],"6") -> 0 | L18: =COUNTIFS(Tabla_Proyectos[Sistema productivo],"Cebolla",Tabla_Proyectos[TRL final],"7") -> 0 | M18: =COUNTIFS(Tabla_Proyectos[Sistema productivo],"Cebolla",Tabla_Proyectos[TRL final],"8") -> 0 | N18: =COUNTIFS(Tabla_Proyectos[Sistema productivo],"Cebolla",Tabla_Proyectos[TRL final],"9") -> 0
